Workbook
Name ALPHA_DURABLES: Constants_NonDisaggregated!$M$5:$O$18
Name ALPHA_NON_DURABLES: Constants_NonDisaggregated!$M$37:$M$50
Name ALPHA_QUAIDS_AUSTRIA: Beta_QUAIDS_3!$C$5:$H$65
Name ALPHA_QUAIDS_BELGIUM: Beta_QUAIDS_3!$C$66:$H$126
Name ALPHA_QUAIDS_BULGARIA: Beta_QUAIDS_3!$C$127:$H$187
Name ALPHA_QUAIDS_CHINA: Beta_QUAIDS_3!$C$1713:$H$1773
Name ALPHA_QUAIDS_CROATIA: Beta_QUAIDS_3!$C$188:$H$248
Name ALPHA_QUAIDS_CYPRUS: Beta_QUAIDS_3!$C$249:$H$309
Name ALPHA_QUAIDS_CZECH_REPUBLIC: Beta_QUAIDS_3!$C$310:$H$370
Name ALPHA_QUAIDS_DENMARK: Beta_QUAIDS_3!$C$371:$H$431
Name ALPHA_QUAIDS_EASOC: Beta_QUAIDS_3!$C$1774:$H$1834
Name ALPHA_QUAIDS_ESTONIA: Beta_QUAIDS_3!$C$432:$H$492
Name ALPHA_QUAIDS_FINLAND: Beta_QUAIDS_3!$C$493:$H$553
Name ALPHA_QUAIDS_FRANCE: Beta_QUAIDS_3!$C$554:$H$614
Name ALPHA_QUAIDS_GERMANY: Beta_QUAIDS_3!$C$615:$H$675
Name ALPHA_QUAIDS_GREECE: Beta_QUAIDS_3!$C$676:$H$736
Name ALPHA_QUAIDS_HUNGARY: Beta_QUAIDS_3!$C$737:$H$797
Name ALPHA_QUAIDS_INDIA: Beta_QUAIDS_3!$C$1835:$H$1895
Name ALPHA_QUAIDS_IRELAND: Beta_QUAIDS_3!$C$798:$H$858
Name ALPHA_QUAIDS_ITALY: Beta_QUAIDS_3!$C$859:$H$919
Name ALPHA_QUAIDS_LATAM: Beta_QUAIDS_3!$C$1896:$H$1956
Name ALPHA_QUAIDS_LATVIA: Beta_QUAIDS_3!$C$920:$H$980
Name ALPHA_QUAIDS_LITHUANIA: Beta_QUAIDS_3!$C$981:$H$1041
Name ALPHA_QUAIDS_LROW: Beta_QUAIDS_3!$C$2079:$H$2139
Name ALPHA_QUAIDS_LUXEMBOURG: Beta_QUAIDS_3!$C$1042:$H$1102
Name ALPHA_QUAIDS_MALTA: Beta_QUAIDS_3!$C$1103:$H$1163
Name ALPHA_QUAIDS_NETHERLANDS: Beta_QUAIDS_3!$C$1164:$H$1224
Name ALPHA_QUAIDS_POLAND: Beta_QUAIDS_3!$C$1225:$H$1285
Name ALPHA_QUAIDS_PORTUGAL: Beta_QUAIDS_3!$C$1286:$H$1346
Name ALPHA_QUAIDS_ROMANIA: Beta_QUAIDS_3!$C$1347:$H$1407
Name ALPHA_QUAIDS_RUSSIA: Beta_QUAIDS_3!$C$1957:$H$2017
Name ALPHA_QUAIDS_SLOVAKIA: Beta_QUAIDS_3!$C$1408:$H$1468
Name ALPHA_QUAIDS_SLOVENIA: Beta_QUAIDS_3!$C$1469:$H$1529
Name ALPHA_QUAIDS_SPAIN: Beta_QUAIDS_3!$C$1530:$H$1590
Name ALPHA_QUAIDS_SWEDEN: Beta_QUAIDS_3!$C$1591:$H$1651
Name ALPHA_QUAIDS_UK: Beta_QUAIDS_3!$C$1652:$H$1712
Name ALPHA_QUAIDS_USMCA: Beta_QUAIDS_3!$C$2018:$H$2078
Name BASE_CONSUMPTION_COICOP: Consumption_COICOP!$B$5:$T$39
Name BASE_GROSS_OPERATING_SURPLUS: BASE_Operating_surplus_tot!$A$5:$AI$5
Name BASE_PRICE_COICOP: BASE_Price_COICOP!$B$5:$T$39
Name BASE_SOCIAL_BENEFITS: BASE_Social_benefits!$A$5:$AI$5
Name BASE_TAX_INCOME_CORPORATIONS: BASE_Tax_Income_corp!$A$5:$AI$5
Name BETA_APPLIANCES: Beta_Appliances_1!$B$5:$BJ$39
Name BETA_HH_TRANSPORT: Beta_hh_transport_1!$B$5:$BJ$39
Name BETA_HOUSING: Beta_Housing_1!$B$5:$BJ$39
Name BETA_NON_DURABLES: Beta_NonDurables_1!$B$5:$BJ$39
Name BETA_QUAIDS_AUSTRIA_H1: BETA_QUAIDS_1!$D$5:$I$10
Name BETA_QUAIDS_AUSTRIA_H10: BETA_QUAIDS_1!$D$59:$I$64
Name BETA_QUAIDS_AUSTRIA_H11: BETA_QUAIDS_1!$D$65:$I$70
Name BETA_QUAIDS_AUSTRIA_H12: BETA_QUAIDS_1!$D$71:$I$76
Name BETA_QUAIDS_AUSTRIA_H13: BETA_QUAIDS_1!$D$77:$I$82
Name BETA_QUAIDS_AUSTRIA_H14: BETA_QUAIDS_1!$D$83:$I$88
Name BETA_QUAIDS_AUSTRIA_H15: BETA_QUAIDS_1!$D$89:$I$94
Name BETA_QUAIDS_AUSTRIA_H16: BETA_QUAIDS_1!$D$95:$I$100
Name BETA_QUAIDS_AUSTRIA_H17: BETA_QUAIDS_1!$D$101:$I$106
Name BETA_QUAIDS_AUSTRIA_H18: BETA_QUAIDS_1!$D$107:$I$112
Name BETA_QUAIDS_AUSTRIA_H19: BETA_QUAIDS_1!$D$113:$I$118
Name BETA_QUAIDS_AUSTRIA_H2: BETA_QUAIDS_1!$D$11:$I$16
Name BETA_QUAIDS_AUSTRIA_H20: BETA_QUAIDS_1!$D$119:$I$124
Name BETA_QUAIDS_AUSTRIA_H21: BETA_QUAIDS_1!$D$125:$I$130

Sheet Disclaimer
A1: Disclaimers
A2: Household data (only countries with household heterogeneity) have been compiled by disaggregating national accounts macro-aggregates with household micro-data structures. More specifically, the micro-data sources used come from Eurostat, Household Budget Survey 2010 and 2015 and European Union Statistics on Income and Living Conditions 2010, 2011, 2015 and 2016 for consumption- and income-related variables and from the European Central Bank, Eurosystem Household Finance and Consumption Survey 2010 and 2014 for wealth-related variables. The responsibility for all conclusions drawn from the data lies entirely with the authors. The results published and the related observations and analyses may not correspond to the results or analyses of the data producers. The data provided preclude the respondents’ identification and do not show confidential data. The micro-economic structures used are derived from a synthetic dataset of fused surveys, with the European Union Statistics on Income and Living Conditions survey as the recipient survey. The number of observations from which each micro-economic structure is derived is given below. Eurostat distinguishes three situations according to the number of observations (unweighted sample): less than 20 observations, from 20 to 49 observations, and more than 49 observations. Micro-economic structures based on less than 20 observations are removed and treated as missing values, while those based on from 20 to 49 observations and on more than 49 observations are flagged for information only. When micro-economic structures are not available, those of the most similar country in terms of macro-economic indicators are used.
A15: Individual flags (applies to all household-related information in the model for countries with heterogeneous households).
A16: Household | B16: BEL | C16: BGR | D16: CYP | E16: CZE | F16: DEU | G16: DNK | H16: ESP | I16: EST | J16: FIN | K16: FRA | L16: GRC | M16: HRV | N16: HUN | O16: IRL | P16: LTU | Q16: LUX | R16: LVA | S16: POL | T16: PRT | U16: SVK | V16: SWE
A17: INCOME1_DENSE_SINGLE | B17: More than 49 observations | C17: More than 49 observations | D17: More than 49 observations | E17: More than 49 observations | F17: More than 49 observations | G17: More than 49 observations | H17: More than 49 observations | I17: More than 49 observations | J17: More than 49 observations | K17: More than 49 observations | L17: More than 49 observations | M17: More than 49 observations | N17: More than 49 observations | O17: More than 49 observations | P17: More than 49 observations | Q17: 20-49 observations | R17: More than 49 observations | S17: More than 49 observations | T17: More than 49 observations | U17: More than 49 observations | V17: More than 49 observations
A18: INCOME1_DENSE_SINGLEWCHILDREN | B18: Less than 20 observations | C18: Less than 20 observations | D18: Less than 20 observations | E18: Less than 20 observations | F18: 20-49 observations | G18: Less than 20 observations | H18: 20-49 observations | I18: Less than 20 observations | J18: Less than 20 observations | K18: 20-49 observations | L18: Less than 20 observations | M18: Less than 20 observations | N18: Less than 20 observations | O18: 20-49 observations | P18: Less than 20 observations | Q18: Less than 20 observations | R18: 20-49 observations | S18: Less than 20 observations | T18: Less than 20 observations | U18: Less than 20 observations | V18: Less than 20 observations
A19: INCOME1_DENSE_COUPLE | B19: More than 49 observations | C19: More than 49 observations | D19: More than 49 observations | E19: More than 49 observations | F19: More than 49 observations | G19: More than 49 observations | H19: More than 49 observations | I19: More than 49 observations | J19: More than 49 observations | K19: More than 49 observations | L19: More than 49 observations | M19: More than 49 observations | N19: More than 49 observations | O19: More than 49 observations | P19: More than 49 observations | Q19: 20-49 observations | R19: More than 49 observations | S19: More than 49 observations | T19: More than 49 observations | U19: More than 49 observations | V19: More than 49 observations
A20: INCOME1_DENSE_COUPLEWCHILDREN | B20: More than 49 observations | C20: More than 49 observations | D20: More than 49 observations | E20: More than 49 observations | F20: More than 49 observations | G20: 20-49 observations | H20: More than 49 observations | I20: More than 49 observations | J20: More than 49 observations | K20: More than 49 observations | L20: More than 49 observations | M20: 20-49 observations | N20: 20-49 observations | O20: More than 49 observations | P20: 20-49 observations | Q20: 20-49 observations | R20: More than 49 observations | S20: More than 49 observations | T20: More than 49 observations | U20: 20-49 observations | V20: 20-49 observations
A21: INCOME1_DENSE_OTHER | B21: 20-49 observations | C21: More than 49 observations | D21: More than 49 observations | E21: 20-49 observations | F21: More than 49 observations | G21: Less than 20 observations | H21: More than 49 observations | I21: More than 49 observations | J21: 20-49 observations | K21: More than 49 observations | L21: More than 49 observations | M21: More than 49 observations | N21: More than 49 observations | O21: 20-49 observations | P21: More than 49 observations | Q21: Less than 20 observations | R21: More than 49 observations | S21: More than 49 observations | T21: More than 49 observations | U21: More than 49 observations | V21: Less than 20 observations
A22: INCOME1_DENSE_OTHERWCHILDREN | B22: 20-49 observations | C22: 20-49 observations | D22: 20-49 observations | E22: Less than 20 observations | F22: 20-49 observations | G22: Less than 20 observations | H22: More than 49 observations | I22: 20-49 observations | J22: 20-49 observations | K22: More than 49 observations | L22: 20-49 observations | M22: 20-49 observations | N22: Less than 20 observations | O22: 20-49 observations | P22: 20-49 observations | Q22: Less than 20 observations | R22: More than 49 observations | S22: 20-49 observations | T22: More than 49 observations | U22: 20-49 observations | V22: Less than 20 observations
A23: INCOME1_SPARSE_SINGLE | B23: More than 49 observations | C23: More than 49 observations | D23: More than 49 observations | E23: More than 49 observations | F23: More than 49 observations | G23: More than 49 observations | H23: More than 49 observations | I23: More than 49 observations | J23: More than 49 observations | K23: More than 49 observations | L23: More than 49 observations | M23: More than 49 observations | N23: More than 49 observations | O23: More than 49 observations | P23: More than 49 observations | Q23: More than 49 observations | R23: More than 49 observations | S23: More than 49 observations | T23: More than 49 observations | U23: More than 49 observations | V23: More than 49 observations
A24: INCOME1_SPARSE_SINGLEWCHILDREN | B24: 20-49 observations | C24: Less than 20 observations | D24: Less than 20 observations | E24: Less than 20 observations | F24: 20-49 observations | G24: Less than 20 observations | H24: Less than 20 observations | I24: Less than 20 observations | J24: 20-49 observations | K24: 20-49 observations | L24: 20-49 observations | M24: Less than 20 observations | N24: 20-49 observations | O24: 20-49 observations | P24: Less than 20 observations | Q24: Less than 20 observations | R24: Less than 20 observations | S24: 20-49 observations | T24: 20-49 observations | U24: Less than 20 observations | V24: 20-49 observations
A25: INCOME1_SPARSE_COUPLE | B25: More than 49 observations | C25: More than 49 observations | D25: More than 49 observations | E25: More than 49 observations | F25: More than 49 observations | G25: More than 49 observations | H25: More than 49 observations | I25: More than 49 observations | J25: More than 49 observations | K25: More than 49 observations | L25: More than 49 observations | M25: More than 49 observations | N25: More than 49 observations | O25: More than 49 observations | P25: More than 49 observations | Q25: More than 49 observations | R25: More than 49 observations | S25: More than 49 observations | T25: More than 49 observations | U25: More than 49 observations | V25: More than 49 observations
A26: INCOME1_SPARSE_COUPLEWCHILDREN | B26: More than 49 observations | C26: More than 49 observations | D26: More than 49 observations | E26: More than 49 observations | F26: More than 49 observations | G26: More than 49 observations | H26: More than 49 observations | I26: More than 49 observations | J26: More than 49 observations | K26: More than 49 observations | L26: More than 49 observations | M26: More than 49 observations | N26: More than 49 observations | O26: More than 49 observations | P26: 20-49 observations | Q26: More than 49 observations | R26: More than 49 observations | S26: More than 49 observations | T26: More than 49 observations | U26: More than 49 observations | V26: More than 49 observations
A27: INCOME1_SPARSE_OTHER | B27: More than 49 observations | C27: More than 49 observations | D27: More than 49 observations | E27: More than 49 observations | F27: More than 49 observations | G27: More than 49 observations | H27: More than 49 observations | I27: More than 49 observations | J27: More than 49 observations | K27: More than 49 observations | L27: More than 49 observations | M27: More than 49 observations | N27: More than 49 observations | O27: More than 49 observations | P27: More than 49 observations | Q27: More than 49 observations | R27: More than 49 observations | S27: More than 49 observations | T27: More than 49 observations | U27: More than 49 observations | V27: More than 49 observations
... A76: INCOME5_SPARSE_OTHERWCHILDREN | B76: 20-49 observations | C76: More than 49 observations | D76: 20-49 observations | E76: More than 49 observations | F76: More than 49 observations | G76: More than 49 observations | H76: More than 49 observations | I76: More than 49 observations | J76: More than 49 observations | K76: More than 49 observations | L76: More than 49 observations | M76: More than 49 observations | N76: More than 49 observations | O76: More than 49 observations | P76: More than 49 observations | Q76: More than 49 observations | R76: 20-49 observations | S76: More than 49 observations | T76: More than 49 observations | U76: More than 49 observations | V76: More than 49 observations

Sheet BASE_Operating_surplus_tot
A4: AUT | B4: BEL | C4: BGR | D4: HRV | E4: CYP | F4: CZE | G4: DNK | H4: EST | I4: FIN | J4: FRA | K4: DEU | L4: GRC | M4: HUN | N4: IRL | O4: ITA | P4: LVA | Q4: LTU | R4: LUX | S4: MLT | T4: NLD | U4: POL | V4: PRT | W4: ROU | X4: SVK | Y4: SVN | Z4: ESP | AA4: SWE | AB4: UK | AC4: China | AD4: EASOC | AE4: India | AF4: LATAM | AG4: Russia | AH4: USMCA | AI4: LROW
A5: 125958.36 | B5: 139807.38 | C5: 18359.497 | D5: 13823.514 | E5: 4761.7769 | F5: 77473.059 | G5: 87261.673 | H5: 8089.2857 | I5: 71795.957 | J5: 720359 | K5: 1132389.5 | L5: 76984.484 | M5: 45158.648 | N5: 147419.3 | O5: 595439.02 | P5: 10802.044 | Q5: 18557.341 | R5: 27123.803 | S5: 4239.1879 | T5: 247168.5 | U5: 195791.92 | V5: 75318.359 | W5: 84673.614 | X5: 37648.507 | Y5: 12463.65 | Z5: 421095.04 | AA5: 169355.35 | AB5: 867771.03 | AC5: 2286534.1 | AD5: 2991951.6 | AE5: 870859.71 | AF5: 1376248.8 | AG5: 459374.04 | AH5: 8132428.8 | AI5: 2597196.7

Sheet BASE_Number_households
B4: INCOME1_DENSE_SINGLE | C4: INCOME1_DENSE_SINGLEWCHILDREN | D4: INCOME1_DENSE_COUPLE | E4: INCOME1_DENSE_COUPLEWCHILDREN | F4: INCOME1_DENSE_OTHER | G4: INCOME1_DENSE_OTHERWCHILDREN | H4: INCOME1_SPARSE_SINGLE | I4: INCOME1_SPARSE_SINGLEWCHILDREN | J4: INCOME1_SPARSE_COUPLE | K4: INCOME1_SPARSE_COUPLEWCHILDREN | L4: INCOME1_SPARSE_OTHER | M4: INCOME1_SPARSE_OTHERWCHILDREN | N4: INCOME2_DENSE_SINGLE | O4: INCOME2_DENSE_SINGLEWCHILDREN | P4: INCOME2_DENSE_COUPLE | Q4: INCOME2_DENSE_COUPLEWCHILDREN | R4: INCOME2_DENSE_OTHER | S4: INCOME2_DENSE_OTHERWCHILDREN | T4: INCOME2_SPARSE_SINGLE | U4: INCOME2_SPARSE_SINGLEWCHILDREN | V4: INCOME2_SPARSE_COUPLE | W4: INCOME2_SPARSE_COUPLEWCHILDREN | X4: INCOME2_SPARSE_OTHER | Y4: INCOME2_SPARSE_OTHERWCHILDREN | Z4: INCOME3_DENSE_SINGLE | AA4: INCOME3_DENSE_SINGLEWCHILDREN | AB4: INCOME3_DENSE_COUPLE | AC4: INCOME3_DENSE_COUPLEWCHILDREN | AD4: INCOME3_DENSE_OTHER | AE4: INCOME3_DENSE_OTHERWCHILDREN | AF4: INCOME3_SPARSE_SINGLE | AG4: INCOME3_SPARSE_SINGLEWCHILDREN | AH4: INCOME3_SPARSE_COUPLE | AI4: INCOME3_SPARSE_COUPLEWCHILDREN | AJ4: INCOME3_SPARSE_OTHER | AK4: INCOME3_SPARSE_OTHERWCHILDREN | AL4: INCOME4_DENSE_SINGLE | AM4: INCOME4_DENSE_SINGLEWCHILDREN | AN4: INCOME4_DENSE_COUPLE | AO4: INCOME4_DENSE_COUPLEWCHILDREN | AP4: INCOME4_DENSE_OTHER | AQ4: INCOME4_DENSE_OTHERWCHILDREN | AR4: INCOME4_SPARSE_SINGLE | AS4: INCOME4_SPARSE_SINGLEWCHILDREN | AT4: INCOME4_SPARSE_COUPLE | AU4: INCOME4_SPARSE_COUPLEWCHILDREN | AV4: INCOME4_SPARSE_OTHER | AW4: INCOME4_SPARSE_OTHERWCHILDREN | AX4: INCOME5_DENSE_SINGLE | AY4: INCOME5_DENSE_SINGLEWCHILDREN | AZ4: INCOME5_DENSE_COUPLE | BA4: INCOME5_DENSE_COUPLEWCHILDREN | BB4: INCOME5_DENSE_OTHER | BC4: INCOME5_DENSE_OTHERWCHILDREN | BD4: INCOME5_SPARSE_SINGLE | BE4: INCOME5_SPARSE_SINGLEWCHILDREN | BF4: INCOME5_SPARSE_COUPLE | BG4: INCOME5_SPARSE_COUPLEWCHILDREN | BH4: INCOME5_SPARSE_OTHER | BI4: INCOME5_SPARSE_OTHERWCHILDREN | BJ4: REPRESENTATIVE_HOUSEHOLD
A5: AUT | B5: 0 | C5: 0 | D5: 0 | E5: 0 | F5: 0 | G5: 0 | H5: 0 | I5: 0 | J5: 0 | K5: 0 | L5: 0 | M5: 0 | N5: 0 | O5: 0 | P5: 0 | Q5: 0 | R5: 0 | S5: 0 | T5: 0 | U5: 0 | V5: 0 | W5: 0 | X5: 0 | Y5: 0 | Z5: 0 | AA5: 0 | AB5: 0 | AC5: 0 | AD5: 0 | AE5: 0 | AF5: 0 | AG5: 0 | AH5: 0 | AI5: 0 | AJ5: 0 | AK5: 0 | AL5: 0 | AM5: 0 | AN5: 0 | AO5: 0 | AP5: 0 | AQ5: 0 | AR5: 0 | AS5: 0 | AT5: 0 | AU5: 0 | AV5: 0 | AW5: 0 | AX5: 0 | AY5: 0 | AZ5: 0 | BA5: 0 | BB5: 0 | BC5: 0 | BD5: 0 | BE5: 0 | BF5: 0 | BG5: 0 | BH5: 0 | BI5: 0 | BJ5: 3742195.6
A6: BEL | B6: 131051.81 | C6: 13025.397 | D6: 71147.156 | E6: 44556.515 | F6: 25558.363 | G6: 12661.382 | H6: 198802.95 | I6: 20498.51 | J6: 209977.52 | K6: 109212.68 | L6: 82077.884 | M6: 34018.791 | N6: 132072.62 | O6: 13143.88 | P6: 71240.558 | Q6: 44645.069 | R6: 26317.042 | S6: 12662.353 | T6: 198665.49 | U6: 21109.159 | V6: 207014.14 | W6: 110388.57 | X6: 82188.333 | Y6: 34516.063 | Z6: 131582.79 | AA6: 12935.314 | AB6: 71960.122 | AC6: 44858.714 | AD6: 26180.462 | AE6: 12767.202 | AF6: 197349.44 | AG6: 20524.515 | AH6: 210600.15 | AI6: 109981.78 | AJ6: 82770.634 | AK6: 34672.986 | AL6: 132063.67 | AM6: 13068.64 | AN6: 71364.92 | AO6: 45251.286 | AP6: 26096.639 | AQ6: 13057.716 | AR6: 199022.64 | AS6: 21731.958 | AT6: 208922.14 | AU6: 109017.1 | AV6: 82291.275 | AW6: 34629.306 | AX6: 130841.11 | AY6: 13493.769 | AZ6: 71600.245 | BA6: 44848.416 | BB6: 26421.494 | BC6: 13289.148 | BD6: 197706.48 | BE6: 20555.857 | BF6: 209606.05 | BG6: 110724.88 | BH6: 82492.873 | BI6: 34607.854 | BJ6: 0
A7: BGR | B7: 79559.944 | C7: 5130.8702 | D7: 70091.21 | E7: 42908.618 | F7: 49663.12 | G7: 18020.654 | H7: 88882.89 | I7: 3770.007 | J7: 90070.258 | K7: 38778.839 | L7: 61026.877 | M7: 36091.22 | N7: 80158.714 | O7: 5065.1559 | P7: 70737.836 | Q7: 43543.201 | R7: 49110.482 | S7: 17773.249 | T7: 89252.897 | U7: 3719.8924 | V7: 90479.547 | W7: 37818.594 | X7: 62249.008 | Y7: 36085.24 | Z7: 79822.59 | AA7: 4974.4763 | AB7: 70532.759 | AC7: 43123.062 | AD7: 50836.8 | AE7: 18651.883 | AF7: 89403.452 | AG7: 4428.5996 | AH7: 89952.062 | AI7: 39760.203 | AJ7: 61064.966 | AK7: 36231.102 | AL7: 80908.263 | AM7: 5335.7242 | AN7: 70204.382 | AO7: 43699.201 | AP7: 49409.789 | AQ7: 18311.427 | AR7: 89020.444 | AS7: 3804.0849 | AT7: 90196.723 | AU7: 39623.382 | AV7: 60966.735 | AW7: 36105.121 | AX7: 80177.49 | AY7: 5637.7734 | AZ7: 70751.813 | BA7: 43642.918 | BB7: 50168.809 | BC7: 18411.088 | BD7: 89375.316 | BE7: 4176.6161 | BF7: 90717.41 | BG7: 39071.981 | BH7: 62157.414 | BI7: 36239.316 | BJ7: 0
A8: HRV | B8: 23110.929 | C8: 494.03593 | D8: 21417.64 | E8: 9294.1181 | F8: 18337.211 | G8: 6140.5692 | H8: 49250.622 | I8: 894.9149 | J8: 52800.709 | K8: 29464.489 | L8: 52658.453 | M8: 29675.3 | N8: 23346.926 | O8: 1060.9049 | P8: 21175.827 | Q8: 9943.4642 | R8: 18477.002 | S8: 6388.3603 | T8: 49050.021 | U8: 815.06019 | V8: 52739.064 | W8: 29415.183 | X8: 52691.526 | Y8: 29453.985 | Z8: 23027.194 | AA8: 1760.938 | AB8: 21591.465 | AC8: 10014.237 | AD8: 18548.567 | AE8: 6366.3342 | AF8: 49685.889 | AG8: 935.84139 | AH8: 52934.287 | AI8: 29590.543 | AJ8: 52716.798 | AK8: 29686.252 | AL8: 23398.655 | AM8: 1223.7654 | AN8: 21306.905 | AO8: 9116.6608 | AP8: 18163.679 | AQ8: 5729.8452 | AR8: 49107.562 | AS8: 889.74471 | AT8: 52143.525 | AU8: 28950.695 | AV8: 52705.922 | AW8: 29307.425 | AX8: 23029.296 | AY8: 1533.6758 | AZ8: 21229.163 | BA8: 9742.0196 | BB8: 18902.041 | BC8: 6988.2911 | BD8: 49402.907 | BE8: 1057.0788 | BF8: 53382.415 | BG8: 30111.091 | BH8: 52785.301 | BI8: 30277.039 | BJ8: 0
A9: CYP | B9: 7851.4287 | C9: 511.53552 | D9: 10602.364 | E9: 5296.6159 | F9: 5218.3218 | G9: 2311.9844 | H9: 4774.6032 | I9: 394.51356 | J9: 9409.7224 | K9: 5788.0239 | L9: 4790.3279 | M9: 3058.3455 | N9: 7818.5238 | O9: 543.39945 | P9: 10913.085 | Q9: 5396.362 | R9: 5436.6678 | S9: 2332.5273 | T9: 4762.1109 | U9: 810.14993 | V9: 9354.691 | W9: 5908.3133 | X9: 4816.0408 | Y9: 3262.8026 | Z9: 7829.9143 | AA9: 516.1325 | AB9: 10885.701 | AC9: 5321.9362 | AD9: 5335.6927 | AE9: 2318.5414 | AF9: 4836.914 | AG9: 653.64796 | AH9: 9442.9767 | AI9: 5875.497 | AJ9: 4840.8728 | AK9: 3232.1417 | AL9: 7866.675 | AM9: 503.98388 | AN9: 10796.18 | AO9: 5493.7497 | AP9: 5346.3264 | AQ9: 2340.3214 | AR9: 4841.8397 | AS9: 501.49537 | AT9: 9377.5015 | AU9: 5812.2541 | AV9: 4790.8024 | AW9: 3190.4779 | AX9: 7895.1582 | AY9: 582.67866 | AZ9: 10844.169 | BA9: 5405.3362 | BB9: 5387.2914 | BC9: 2372.3256 | BD9: 4826.8322 | BE9: 680.13317 | BF9: 9485.7085 | BG9: 5906.3118 | BH9: 4895.056 | BI9: 3391.9322 | BJ9: 0
A10: CZE | B10: 96245.029 | C10: 7815.4273 | D10: 89727.42 | E10: 44030.26 | F10: 34041.721 | G10: 11133.379 | H10: 142078.77 | I10: 12758.079 | J10: 180151.16 | K10: 94019.927 | L10: 96193.349 | M10: 42129.228 | N10: 95891.814 | O10: 8417.1864 | P10: 89339.858 | Q10: 44180.681 | R10: 33443.562 | S10: 11589.071 | T10: 141846.09 | U10: 12954.522 | V10: 180222.89 | W10: 94713.882 | X10: 96341.981 | Y10: 43052.756 | Z10: 96156.717 | AA10: 8513.8311 | AB10: 89867.411 | AC10: 44303.758 | AD10: 34603.077 | AE10: 11200.135 | AF10: 142154.15 | AG10: 13103.435 | AH10: 180617.18 | AI10: 94168.651 | AJ10: 95928.795 | AK10: 42886.762 | AL10: 96325.973 | AM10: 8176.7477 | AN10: 89243.968 | AO10: 43960.689 | AP10: 33974.15 | AQ10: 11218.999 | AR10: 142572.27 | AS10: 12579.854 | AT10: 180184.45 | AU10: 94584.552 | AV10: 96759.314 | AW10: 42908.665 | AX10: 96167.468 | AY10: 9021.5075 | AZ10: 89357.343 | BA10: 44586.612 | BB10: 34194.49 | BC10: 11734.715 | BD10: 142026.73 | BE10: 13586.709 | BF10: 180908.32 | BG10: 94386.989 | BH10: 96366.561 | BI10: 43362.589 | BJ10: 0
A11: DNK | B11: 112172.7 | C11: 7480.0232 | D11: 48710.7 | E11: 27771.661 | F11: 7922.8069 | G11: 4047.9251 | H11: 139843.38 | I11: 11142.641 | J11: 110321.22 | K11: 52103.586 | L11: 22524.69 | M11: 13975.866 | N11: 115550.97 | O11: 9061.3337 | P11: 49819.516 | Q11: 27880.642 | R11: 8205.5577 | S11: 4534.157 | T11: 139494.65 | U11: 11039.347 | V11: 110488.42 | W11: 52219.86 | X11: 21565.352 | Y11: 13537.685 | Z11: 114118.14 | AA11: 6685.2467 | AB11: 49544.296 | AC11: 27884.801 | AD11: 7967.8701 | AE11: 5125.5864 | AF11: 139957.85 | AG11: 10646.784 | AH11: 110451.01 | AI11: 52890.259 | AJ11: 22183.052 | AK11: 14649.511 | AL11: 113603.97 | AM11: 9603.6289 | AN11: 49368.887 | AO11: 27913.696 | AP11: 8139.3204 | AQ11: 4592.9564 | AR11: 140608.36 | AS11: 11403.905 | AT11: 110400.8 | AU11: 52871.217 | AV11: 21948.796 | AW11: 14332.128 | AX11: 113965.22 | AY11: 8790.2675 | AZ11: 49505.601 | BA11: 28073.2 | BB11: 8364.1449 | BC11: 4589.375 | BD11: 140147.75 | BE11: 11705.423 | BF11: 110496.55 | BG11: 52530.078 | BH11: 22512.11 | BI11: 14135.511 | BJ11: 0
A12: EST | B12: 25841.755 | C12: 1661.4498 | D12: 19785.686 | E12: 11494.891 | F12: 7556.5731 | G12: 4290.1199 | H12: 16846.541 | I12: 1174.7034 | J12: 12602.685 | K12: 6770.7906 | L12: 5825.2391 | M12: 3446.5638 | N12: 25997.387 | O12: 1699.1011 | P12: 19738.113 | Q12: 11520.625 | R12: 7807.5277 | S12: 4375.5693 | T12: 16961.58 | U12: 1421.1429 | V12: 12554.184 | W12: 6862.346 | X12: 6035.7593 | Y12: 3476.1689 | Z12: 26272.869 | AA12: 1706.3412 | AB12: 19796.939 | AC12: 11569.291 | AD12: 7596.3723 | AE12: 4286.2524 | AF12: 16884.763 | AG12: 1221.2352 | AH12: 12690.624 | AI12: 6851.3888 | AJ12: 5853.5607 | AK12: 3545.2327 | AL12: 25955.034 | AM12: 1718.6287 | AN12: 19854.321 | AO12: 11471.84 | AP12: 7755.6293 | AQ12: 4290.1417 | AR12: 16916.47 | AS12: 1336.6761 | AT12: 12660.244 | AU12: 6789.0356 | AV12: 5924.0758 | AW12: 3497.5572 | AX12: 25954.954 | AY12: 1769.8891 | AZ12: 19893.941 | BA12: 11607.852 | BB12: 7736.8976 | BC12: 4453.5167 | BD12: 16930.545 | BE12: 1383.5124 | BF12: 12659.662 | BG12: 6846.2389 | BH12: 5937.3652 | BI12: 3495.5774 | BJ12: 0
A13: FIN | B13: 92673.46 | C13: 6084.1465 | D13: 64253.486 | E13: 26630.123 | F13: 8966.1031 | G13: 4749.7568 | H13: 119719.12 | I13: 5688.8968 | J13: 109536.86 | K13: 46925.723 | L13: 19283.296 | M13: 12453.056 | N13: 92710.992 | O13: 6352.5086 | P13: 65639.78 | Q13: 26765.554 | R13: 9210.4259 | S13: 5226.2973 | T13: 120649.4 | U13: 5685.2893 | V13: 109908.81 | W13: 47135.083 | X13: 19332.574 | Y13: 12278.244 | Z13: 92314.274 | AA13: 6114.4492 | AB13: 65099.999 | AC13: 27060.773 | AD13: 9305.5126 | AE13: 4661.3785 | AF13: 120153.91 | AG13: 6096.4784 | AH13: 110332.99 | AI13: 46833.069 | AJ13: 19403.842 | AK13: 12701.844 | AL13: 93109.582 | AM13: 6300.8401 | AN13: 65118.643 | AO13: 26888.122 | AP13: 8995.0964 | AQ13: 4870.1409 | AR13: 120214.81 | AS13: 5897.2212 | AT13: 109822.23 | AU13: 47233.905 | AV13: 19507.984 | AW13: 12478.384 | AX13: 92987.691 | AY13: 6266.4555 | AZ13: 65111.092 | BA13: 26840.428 | BB13: 9350.6621 | BC13: 4939.6264 | BD13: 120341.76 | BE13: 5863.3143 | BF13: 110046.11 | BG13: 47139.219 | BH13: 19189.704 | BI13: 12636.772 | BJ13: 0
A14: FRA | B14: 974368.55 | C14: 93676.743 | D14: 685069.92 | E14: 390761.95 | F14: 205461.77 | G14: 110117.69 | H14: 887452.04 | I14: 101148.87 | J14: 878399.42 | K14: 494859.52 | L14: 272612.25 | M14: 147848.8 | N14: 998736.3 | O14: 98200.503 | P14: 686111.94 | Q14: 391291.63 | R14: 209633.18 | S14: 110183.72 | T14: 885797.47 | U14: 105068.87 | V14: 879567.68 | W14: 496300.14 | X14: 273308.09 | Y14: 145916.79 | Z14: 960785.83 | AA14: 101613.05 | AB14: 683883.67 | AC14: 392330.52 | AD14: 206352.44 | AE14: 110220.04 | AF14: 894614.58 | AG14: 105121.51 | AH14: 879760.14 | AI14: 496236.55 | AJ14: 270731.26 | AK14: 149174.99 | AL14: 986468.07 | AM14: 95363.067 | AN14: 686709.12 | AO14: 392316.47 | AP14: 210319.15 | AQ14: 110970.65 | AR14: 889162.26 | AS14: 99451.171 | AT14: 879881.95 | AU14: 495896.15 | AV14: 271203.53 | AW14: 150041.68 | AX14: 980981.25 | AY14: 99243.634 | AZ14: 686905.35 | BA14: 391999.44 | BB14: 207953.46 | BC14: 110391.9 | BD14: 889773.65 | BE14: 109111.58 | BF14: 879090.81 | BG14: 496697.64 | BH14: 274264.88 | BI14: 148873.73 | BJ14: 0
A15: DEU | B15: 1595675 | C15: 90452.036 | D15: 983546.29 | E15: 296009.97 | F15: 166379.5 | G15: 35389.534 | H15: 1736708.7 | I15: 123865.2 | J15: 1689931.3 | K15: 739425.58 | L15: 544741.19 | M15: 156339.16 | N15: 1594602.7 | O15: 95399.012 | P15: 984159.81 | Q15: 296522.92 | R15: 169093.48 | S15: 39212.329 | T15: 1741172.5 | U15: 123928.23 | V15: 1689575.6 | W15: 737579.42 | X15: 537607.07 | Y15: 162300.95 | Z15: 1594017.6 | AA15: 89649.797 | AB15: 984207.88 | AC15: 298633.89 | AD15: 167539.63 | AE15: 36587.68 | AF15: 1748164.8 | AG15: 123449.51 | AH15: 1687390.6 | AI15: 738872.32 | AJ15: 541926.62 | AK15: 159924.59 | AL15: 1591953.7 | AM15: 90849.628 | AN15: 983863.41 | AO15: 296358.63 | AP15: 168622.96 | AQ15: 38174.713 | AR15: 1735536.8 | AS15: 125666.7 | AT15: 1692501.6 | AU15: 741209.07 | AV15: 541432.18 | AW15: 155674.75 | AX15: 1596161.1 | AY15: 94293.526 | AZ15: 984522.61 | BA15: 298784.59 | BB15: 170034.43 | BC15: 37484.745 | BD15: 1741557.1 | BE15: 123269.36 | BF15: 1691100.9 | BG15: 740373.61 | BH15: 544242.94 | BI15: 165745.55 | BJ15: 0
A16: GRC | B16: 96779.29 | C16: 3756.8336 | D16: 85285.77 | E16: 55018.899 | F16: 70490.102 | G16: 16920.25 | H16: 114913.32 | I16: 4241.8737 | J16: 152358.85 | K16: 83452.051 | L16: 104465 | M16: 35968.407 | N16: 96136.872 | O16: 4009.0026 | P16: 85531.002 | Q16: 54799.254 | R16: 70194.589 | S16: 17495.619 | T16: 114764.81 | U16: 3133.4705 | V16: 152349.93 | W16: 82803.13 | X16: 104449.43 | Y16: 36354.938 | Z16: 96577.22 | AA16: 4078.255 | AB16: 85236.843 | AC16: 54346.291 | AD16: 70948.839 | AE16: 17466.863 | AF16: 115262.64 | AG16: 3717.955 | AH16: 152184.06 | AI16: 82445.425 | AJ16: 104878.62 | AK16: 36319.46 | AL16: 96535.461 | AM16: 3879.1712 | AN16: 85010.119 | AO16: 55251.329 | AP16: 71094.204 | AQ16: 17443.967 | AR16: 115409.13 | AS16: 3918.3341 | AT16: 152434.93 | AU16: 83066.129 | AV16: 104426.97 | AW16: 36626.879 | AX16: 96417.158 | AY16: 4095.7376 | AZ16: 85105.267 | BA16: 54709.227 | BB16: 70749.267 | BC16: 17534.6 | BD16: 114481.1 | BE16: 3509.4667 | BF16: 152356.23 | BG16: 83447.266 | BH16: 104767.98 | BI16: 36414.317 | BJ16: 0
... A39: LROW | B39: 0 | C39: 0 | D39: 0 | E39: 0 | F39: 0 | G39: 0 | H39: 0 | I39: 0 | J39: 0 | K39: 0 | L39: 0 | M39: 0 | N39: 0 | O39: 0 | P39: 0 | Q39: 0 | R39: 0 | S39: 0 | T39: 0 | U39: 0 | V39: 0 | W39: 0 | X39: 0 | Y39: 0 | Z39: 0 | AA39: 0 | AB39: 0 | AC39: 0 | AD39: 0 | AE39: 0 | AF39: 0 | AG39: 0 | AH39: 0 | AI39: 0 | AJ39: 0 | AK39: 0 | AL39: 0 | AM39: 0 | AN39: 0 | AO39: 0 | AP39: 0 | AQ39: 0 | AR39: 0 | AS39: 0 | AT39: 0 | AU39: 0 | AV39: 0 | AW39: 0 | AX39: 0 | AY39: 0 | AZ39: 0 | BA39: 0 | BB39: 0 | BC39: 0 | BD39: 0 | BE39: 0 | BF39: 0 | BG39: 0 | BH39: 0 | BI39: 0 | BJ39: 633760000

Sheet BASE_Social_benefits
A4: AUT | B4: BEL | C4: BGR | D4: HRV | E4: CYP | F4: CZE | G4: DNK | H4: EST | I4: FIN | J4: FRA | K4: DEU | L4: GRC | M4: HUN | N4: IRL | O4: ITA | P4: LVA | Q4: LTU | R4: LUX | S4: MLT | T4: NLD | U4: POL | V4: PRT | W4: ROU | X4: SVK | Y4: SVN | Z4: ESP | AA4: SWE | AB4: UK | AC4: China | AD4: EASOC | AE4: India | AF4: LATAM | AG4: Russia | AH4: USMCA | AI4: LROW
A5: 72243.303 | B5: 78492.97 | C5: 6015.8127 | D5: 7187.3017 | E5: 2733.1753 | F5: 23107.76 | G5: 51439.623 | H5: 2597.5928 | I5: 46112.487 | J5: 483738.97 | K5: 521171.73 | L5: 38877.35 | M5: 16023.809 | N5: 25621.106 | O5: 369372.55 | P5: 2838.0244 | Q5: 4497.9674 | R5: 8805.3203 | S5: 1094.424 | T5: 86842.724 | U5: 68235.734 | V5: 35102.231 | W5: 18775.3 | X5: 12168.366 | Y5: 7302.5954 | Z5: 188893.55 | AA5: 66518.266 | AB5: 398168.19 | AC5: 994231.73 | AD5: 817551.29 | AE5: 182879.94 | AF5: 374968.45 | AG5: 137102.68 | AH5: 2831960.1 | AI5: 682617.12

Sheet BASE_Price_COICOP
B4: HH_HOUSING | C4: HH_APPLIANCES | D4: HH_VEHICLES | E4: HH_ELECTRICITY | F4: HH_GAS | G4: HH_LIQUID_FUELS | H4: HH_SOLID_FUELS | I4: HH_HEAT | J4: HH_FUEL_TRANSPORT | K4: HH_RAILWAY | L4: HH_ROAD | M4: HH_AIR | N4: HH_MARITIME | O4: HH_FOOD | P4: HH_TEXTILES | Q4: HH_FURNITURE_EQUIPMENT | R4: HH_SERVICES | S4: HH_LEISURE | T4: HH_OTHER
A5: AUT | B5: 108.41699 | C5: 125.56626 | D5: 123.60792 | E5: 112.61824 | F5: 142.60035 | G5: 225.65951 | H5: 154.84646 | I5: 116.33614 | J5: 229.4824 | K5: 100.89665 | L5: 100.16766 | M5: 104.7807 | N5: 101.86396 | O5: 185.39031 | P5: 193.57755 | Q5: 156.74703 | R5: 113.99535 | S5: 125.68488 | T5: 116.18727
A6: BEL | B6: 101.81458 | C6: 138.08368 | D6: 116.85905 | E6: 110.41112 | F6: 127.01496 | G6: 177.80093 | H6: 141.00789 | I6: 119.84678 | J6: 178.42025 | K6: 93.631152 | L6: 84.84648 | M6: 100.94122 | N6: 102.34742 | O6: 187.13257 | P6: 192.62499 | Q6: 146.2836 | R6: 105.71398 | S6: 119.84538 | T6: 118.09092
A7: BGR | B7: 117.05639 | C7: 494.3599 | D7: 375.62148 | E7: 114.62009 | F7: 1731.11 | G7: 2100.7644 | H7: 537.3489 | I7: 127.96521 | J7: 2225.5013 | K7: 103.72237 | L7: 104.63168 | M7: 107.02507 | N7: 103.64774 | O7: 315.37754 | P7: 336.13296 | Q7: 365.56952 | R7: 210.25751 | S7: 323.33533 | T7: 270.79232
A8: HRV | B8: 109.38192 | C8: 146.89984 | D8: 139.11488 | E8: 122.99824 | F8: 140.91361 | G8: 198.07384 | H8: 130.75822 | I8: 125.50387 | J8: 200.69625 | K8: 134.58525 | L8: 138.41247 | M8: 100.83155 | N8: 97.464913 | O8: 165.68182 | P8: 177.55179 | Q8: 145.57901 | R8: 114.07847 | S8: 129.89057 | T8: 115.02921
A9: CYP | B9: 111.24987 | C9: 140.39439 | D9: 132.95199 | E9: 120.62949 | F9: 170.63801 | G9: 181.2284 | H9: 130.66177 | I9: 129.99184 | J9: 193.98937 | K9: 92.033085 | L9: 96.640567 | M9: 100.10294 | N9: 100.4072 | O9: 237.76367 | P9: 260.06095 | Q9: 212.2142 | R9: 123.03912 | S9: 132.41136 | T9: 121.96149
A10: CZE | B10: 104.03731 | C10: 108.31642 | D10: 107.60041 | E10: 109.04542 | F10: 114.2821 | G10: 184.05401 | H10: 115.33521 | I10: 109.19605 | J10: 193.99228 | K10: 86.99111 | L10: 84.066441 | M10: 100.91308 | N10: 103.65265 | O10: 170.31825 | P10: 180.74338 | Q10: 125.9971 | R10: 110.58641 | S10: 116.36339 | T10: 108.85613
A11: DNK | B11: 104.28841 | C11: 140.72382 | D11: 162.24063 | E11: 161.31967 | F11: 159.626 | G11: 141.49598 | H11: 135.93815 | I11: 155.72277 | J11: 136.42436 | K11: 97.950812 | L11: 94.534573 | M11: 106.06965 | N11: 103.8402 | O11: 155.83559 | P11: 160.72615 | Q11: 147.97949 | R11: 106.52323 | S11: 130.23306 | T11: 109.26327
A12: EST | B12: 105.75019 | C12: 107.9539 | D12: 121.06407 | E12: 117.25856 | F12: 147.38906 | G12: 184.78068 | H12: 146.18103 | I12: 117.09075 | J12: 188.44191 | K12: 97.637788 | L12: 96.408657 | M12: 100.00516 | N12: 97.672246 | O12: 178.12243 | P12: 185.95605 | Q12: 137.70173 | R12: 109.5472 | S12: 120.10075 | T12: 111.46716
A13: FIN | B13: 104.12045 | C13: 120.42628 | D13: 131.27937 | E13: 122.2366 | F13: 140.79595 | G13: 143.30225 | H13: 134.93613 | I13: 122.3406 | J13: 145.30307 | K13: 100.67907 | L13: 100.11404 | M13: 102.18581 | N13: 100.68291 | O13: 196.58071 | P13: 208.73449 | Q13: 144.87536 | R13: 107.20489 | S13: 122.078 | T13: 113.34047
A14: FRA | B14: 103.51513 | C14: 129.0604 | D14: 133.30803 | E14: 114.1687 | F14: 125.23239 | G14: 179.11923 | H14: 138.85114 | I14: 120.91386 | J14: 181.96758 | K14: 91.3271 | L14: 88.636422 | M14: 104.8826 | N14: 99.619568 | O14: 175.5092 | P14: 183.09315 | Q14: 151.98919 | R14: 109.58799 | S14: 121.70217 | T14: 116.81129
A15: DEU | B15: 103.38738 | C15: 121.64983 | D15: 120.15036 | E15: 122.38722 | F15: 131.24527 | G15: 181.13317 | H15: 127.72961 | I15: 121.61289 | J15: 187.50114 | K15: 95.816054 | L15: 94.1495 | M15: 110.08362 | N15: 101.74958 | O15: 170.53026 | P15: 174.75843 | Q15: 150.44886 | R15: 113.38413 | S15: 125.03111 | T15: 113.77202
A16: GRC | B16: 129.17575 | C16: 1206.9664 | D16: 3824.2623 | E16: 120.26529 | F16: 441.34833 | G16: 699.4996 | H16: 441.64691 | I16: 420.17778 | J16: 676.66363 | K16: 109.85181 | L16: 110.38825 | M16: 102.81291 | N16: 100.00482 | O16: 397.18029 | P16: 456.86203 | Q16: 1002.8052 | R16: 282.1329 | S16: 300.43222 | T16: 462.50712
... A39: LROW | B39: 102.6612 | C39: 121.03006 | D39: 119.73088 | E39: 106.87398 | F39: 134.23844 | G39: 188.32564 | H39: 136.32006 | I39: 115.34969 | J39: 190.24142 | K39: 104.91646 | L39: 104.97157 | M39: 104.75595 | N39: 101.51484 | O39: 125.04664 | P39: 132.72588 | Q39: 124.46045 | R39: 105.71905 | S39: 113.49597 | T39: 107.80199

Sheet BASE_Tax_Income_corp
A4: AUT | B4: BEL | C4: BGR | D4: HRV | E4: CYP | F4: CZE | G4: DNK | H4: EST | I4: FIN | J4: FRA | K4: DEU | L4: GRC | M4: HUN | N4: IRL | O4: ITA | P4: LVA | Q4: LTU | R4: LUX | S4: MLT | T4: NLD | U4: POL | V4: PRT | W4: ROU | X4: SVK | Y4: SVN | Z4: ESP | AA4: SWE | AB4: UK | AC4: China | AD4: EASOC | AE4: India | AF4: LATAM | AG4: Russia | AH4: USMCA | AI4: LROW
A5: 9000.0278 | B5: 15363.48 | C5: 1097.7006 | D5: 590.91423 | E5: 381.26505 | F5: 5967.8058 | G5: 8583.6498 | H5: 470.76423 | I5: 5056.3344 | J5: 64491.796 | K5: 81802.331 | L5: 4441.1626 | M5: 2040.5627 | N5: 7700.1908 | O5: 37198.21 | P5: 431.18587 | Q5: 636.73069 | R5: 2546.4118 | S5: 267.30242 | T5: 21006.685 | U5: 8790.5298 | V5: 6228.362 | W5: 2286.4316 | X5: 3333.6735 | Y5: 631.43254 | Z5: 26363.148 | AA5: 14674.136 | AB5: 68874.047 | AC5: 108163.05 | AD5: 227623.74 | AE5: 15260.505 | AF5: 39499.039 | AG5: 17267.521 | AH5: 453101.15 | AI5: 198546.27

Sheet HH_Property_income_rec
B4: INCOME1_DENSE_SINGLE | C4: INCOME1_DENSE_SINGLEWCHILDREN | D4: INCOME1_DENSE_COUPLE | E4: INCOME1_DENSE_COUPLEWCHILDREN | F4: INCOME1_DENSE_OTHER | G4: INCOME1_DENSE_OTHERWCHILDREN | H4: INCOME1_SPARSE_SINGLE | I4: INCOME1_SPARSE_SINGLEWCHILDREN | J4: INCOME1_SPARSE_COUPLE | K4: INCOME1_SPARSE_COUPLEWCHILDREN | L4: INCOME1_SPARSE_OTHER | M4: INCOME1_SPARSE_OTHERWCHILDREN | N4: INCOME2_DENSE_SINGLE | O4: INCOME2_DENSE_SINGLEWCHILDREN | P4: INCOME2_DENSE_COUPLE | Q4: INCOME2_DENSE_COUPLEWCHILDREN | R4: INCOME2_DENSE_OTHER | S4: INCOME2_DENSE_OTHERWCHILDREN | T4: INCOME2_SPARSE_SINGLE | U4: INCOME2_SPARSE_SINGLEWCHILDREN | V4: INCOME2_SPARSE_COUPLE | W4: INCOME2_SPARSE_COUPLEWCHILDREN | X4: INCOME2_SPARSE_OTHER | Y4: INCOME2_SPARSE_OTHERWCHILDREN | Z4: INCOME3_DENSE_SINGLE | AA4: INCOME3_DENSE_SINGLEWCHILDREN | AB4: INCOME3_DENSE_COUPLE | AC4: INCOME3_DENSE_COUPLEWCHILDREN | AD4: INCOME3_DENSE_OTHER | AE4: INCOME3_DENSE_OTHERWCHILDREN | AF4: INCOME3_SPARSE_SINGLE | AG4: INCOME3_SPARSE_SINGLEWCHILDREN | AH4: INCOME3_SPARSE_COUPLE | AI4: INCOME3_SPARSE_COUPLEWCHILDREN | AJ4: INCOME3_SPARSE_OTHER | AK4: INCOME3_SPARSE_OTHERWCHILDREN | AL4: INCOME4_DENSE_SINGLE | AM4: INCOME4_DENSE_SINGLEWCHILDREN | AN4: INCOME4_DENSE_COUPLE | AO4: INCOME4_DENSE_COUPLEWCHILDREN | AP4: INCOME4_DENSE_OTHER | AQ4: INCOME4_DENSE_OTHERWCHILDREN | AR4: INCOME4_SPARSE_SINGLE | AS4: INCOME4_SPARSE_SINGLEWCHILDREN | AT4: INCOME4_SPARSE_COUPLE | AU4: INCOME4_SPARSE_COUPLEWCHILDREN | AV4: INCOME4_SPARSE_OTHER | AW4: INCOME4_SPARSE_OTHERWCHILDREN | AX4: INCOME5_DENSE_SINGLE | AY4: INCOME5_DENSE_SINGLEWCHILDREN | AZ4: INCOME5_DENSE_COUPLE | BA4: INCOME5_DENSE_COUPLEWCHILDREN | BB4: INCOME5_DENSE_OTHER | BC4: INCOME5_DENSE_OTHERWCHILDREN | BD4: INCOME5_SPARSE_SINGLE | BE4: INCOME5_SPARSE_SINGLEWCHILDREN | BF4: INCOME5_SPARSE_COUPLE | BG4: INCOME5_SPARSE_COUPLEWCHILDREN | BH4: INCOME5_SPARSE_OTHER | BI4: INCOME5_SPARSE_OTHERWCHILDREN | BJ4: REPRESENTATIVE_HOUSEHOLD
A5: AUT | B5: 0 | C5: 0 | D5: 0 | E5: 0 | F5: 0 | G5: 0 | H5: 0 | I5: 0 | J5: 0 | K5: 0 | L5: 0 | M5: 0 | N5: 0 | O5: 0 | P5: 0 | Q5: 0 | R5: 0 | S5: 0 | T5: 0 | U5: 0 | V5: 0 | W5: 0 | X5: 0 | Y5: 0 | Z5: 0 | AA5: 0 | AB5: 0 | AC5: 0 | AD5: 0 | AE5: 0 | AF5: 0 | AG5: 0 | AH5: 0 | AI5: 0 | AJ5: 0 | AK5: 0 | AL5: 0 | AM5: 0 | AN5: 0 | AO5: 0 | AP5: 0 | AQ5: 0 | AR5: 0 | AS5: 0 | AT5: 0 | AU5: 0 | AV5: 0 | AW5: 0 | AX5: 0 | AY5: 0 | AZ5: 0 | BA5: 0 | BB5: 0 | BC5: 0 | BD5: 0 | BE5: 0 | BF5: 0 | BG5: 0 | BH5: 0 | BI5: 0 | BJ5: 7905.6854
A6: BEL | B6: 1164.9838 | C6: 909.32097 | D6: 2108.8772 | E6: 909.23729 | F6: 1538.351 | G6: 3537.284 | H6: 1825.2791 | I6: 912.86263 | J6: 4527.7918 | K6: 3092.5088 | L6: 5555.8175 | M6: 2255.4574 | N6: 1897.1255 | O6: 2166.353 | P6: 3264.5235 | Q6: 3509.3084 | R6: 5746.9252 | S6: 3830.0088 | T6: 2759.9298 | U6: 1566.627 | V6: 7353.6076 | W6: 6801.4694 | X6: 7322.5486 | Y6: 7660.2871 | Z6: 1854.1566 | AA6: 2099.0066 | AB6: 7110.1462 | AC6: 5032.8898 | AD6: 9620.9067 | AE6: 4070.5592 | AF6: 4005.4497 | AG6: 2187.4184 | AH6: 7873.3563 | AI6: 8323.6206 | AJ6: 11176.885 | AK6: 6966.9354 | AL6: 3912.2977 | AM6: 1651.3924 | AN6: 7676.1284 | AO6: 7716.1963 | AP6: 7496.3095 | AQ6: 6567.0714 | AR6: 4880.7816 | AS6: 2132.8942 | AT6: 8969.1933 | AU6: 8756.0209 | AV6: 15624.124 | AW6: 9508.8756 | AX6: 6232.3765 | AY6: 7670.3811 | AZ6: 16444.251 | BA6: 11730.93 | BB6: 12856.209 | BC6: 13985.797 | BD6: 6896.3474 | BE6: 4128.8708 | BF6: 14510.482 | BG6: 9089.732 | BH6: 15835.325 | BI6: 16449.28 | BJ6: 0
A7: BGR | B7: 211.88351 | C7: 103.14743 | D7: 383.2624 | E7: 245.23431 | F7: 388.39939 | G7: 433.76392 | H7: 179.29205 | I7: 144.67291 | J7: 254.61776 | K7: 495.63086 | L7: 281.66273 | M7: 494.94006 | N7: 239.77521 | O7: 90.811927 | P7: 385.77702 | Q7: 660.5382 | R7: 507.19804 | S7: 906.11291 | T7: 257.12665 | U7: 303.91293 | V7: 419.70948 | W7: 655.69583 | X7: 494.3632 | Y7: 435.12783 | Z7: 289.32257 | AA7: 139.58795 | AB7: 484.53092 | AC7: 866.4777 | AD7: 4039.7341 | AE7: 964.27774 | AF7: 276.42298 | AG7: 273.24746 | AH7: 522.22505 | AI7: 544.63978 | AJ7: 929.19413 | AK7: 1174.0707 | AL7: 335.79234 | AM7: 249.24609 | AN7: 609.04932 | AO7: 2875.8501 | AP7: 956.09564 | AQ7: 1180.6903 | AR7: 340.92479 | AS7: 577.65662 | AT7: 629.03406 | AU7: 702.31682 | AV7: 728.91074 | AW7: 690.55387 | AX7: 607.40585 | AY7: 411.54552 | AZ7: 1502.2403 | BA7: 1757.8199 | BB7: 1797.7284 | BC7: 2500.5292 | BD7: 469.46828 | BE7: 803.30175 | BF7: 861.84643 | BG7: 1207.5244 | BH7: 1777.558 | BI7: 1941.7139 | BJ7: 0
A8: HRV | B8: 200.68786 | C8: 100.59604 | D8: 409.73461 | E8: 411.76268 | F8: 381.50433 | G8: 280.77637 | H8: 224.16444 | I8: 105.28588 | J8: 270.36495 | K8: 242.6487 | L8: 361.18818 | M8: 478.41808 | N8: 221.20563 | O8: 382.69224 | P8: 332.78597 | Q8: 520.44331 | R8: 784.54987 | S8: 386.97217 | T8: 303.72369 | U8: 270.40788 | V8: 321.98092 | W8: 511.09906 | X8: 528.43355 | Y8: 557.76102 | Z8: 256.41616 | AA8: 165.23179 | AB8: 487.7779 | AC8: 553.9178 | AD8: 610.31673 | AE8: 523.69651 | AF8: 294.94742 | AG8: 293.63117 | AH8: 354.73859 | AI8: 567.35225 | AJ8: 684.08632 | AK8: 748.81432 | AL8: 288.51729 | AM8: 248.95469 | AN8: 611.67789 | AO8: 1658.1365 | AP8: 866.48871 | AQ8: 1105.3764 | AR8: 278.23225 | AS8: 560.70541 | AT8: 568.1422 | AU8: 617.75995 | AV8: 601.79481 | AW8: 951.67954 | AX8: 591.61203 | AY8: 877.83592 | AZ8: 1233.9078 | BA8: 1497.6565 | BB8: 2063.7461 | BC8: 2309.1414 | BD8: 410.09378 | BE8: 770.45904 | BF8: 852.19157 | BG8: 1254.8874 | BH8: 1467.9711 | BI8: 1649.8852 | BJ8: 0
A9: CYP | B9: 814.42375 | C9: 434.60885 | D9: 1442.7189 | E9: 1549.1251 | F9: 3013.4921 | G9: 2940.2419 | H9: 1011.9902 | I9: 790.4435 | J9: 1269.4387 | K9: 1380.9054 | L9: 2145.5313 | M9: 2634.0561 | N9: 1569.4054 | O9: 1005.0792 | P9: 1692.7181 | Q9: 2165.4323 | R9: 3115.5174 | S9: 4307.9268 | T9: 1444.5368 | U9: 1636.5062 | V9: 2073.6523 | W9: 3024.775 | X9: 3123.0816 | Y9: 3126.5393 | Z9: 1716.4049 | AA9: 983.36616 | AB9: 3813.8729 | AC9: 3468.3314 | AD9: 4322.6128 | AE9: 3710.8239 | AF9: 1238.7195 | AG9: 2248.6542 | AH9: 1707.1875 | AI9: 2857.3426 | AJ9: 3493.9756 | AK9: 2171.78 | AL9: 1881.7738 | AM9: 795.5228 | AN9: 3357.5477 | AO9: 7420.6106 | AP9: 6819.5726 | AQ9: 5637.7941 | AR9: 1426.1796 | AS9: 1921.025 | AT9: 2277.4036 | AU9: 3364.9531 | AV9: 4061.2046 | AW9: 3840.6795 | AX9: 5599.8248 | AY9: 3656.1459 | AZ9: 10154.747 | BA9: 6475.0096 | BB9: 10289.164 | BC9: 8886.1563 | BD9: 5214.1168 | BE9: 4172.764 | BF9: 5528.9204 | BG9: 7669.1935 | BH9: 6934.0312 | BI9: 8039.9812 | BJ9: 0
A10: CZE | B10: 429.48546 | C10: 230.62201 | D10: 620.10581 | E10: 743.65739 | F10: 739.9942 | G10: 757.2821 | H10: 425.21748 | I10: 489.54088 | J10: 452.62031 | K10: 865.9322 | L10: 1373.6986 | M10: 614.50348 | N10: 515.86577 | O10: 705.92345 | P10: 659.55202 | Q10: 1068.9564 | R10: 1224.921 | S10: 1367.451 | T10: 545.10201 | U10: 839.62359 | V10: 704.16856 | W10: 1381.2538 | X10: 864.38004 | Y10: 1846.7212 | Z10: 432.8803 | AA10: 362.22094 | AB10: 926.04829 | AC10: 764.2038 | AD10: 1563.0857 | AE10: 1304.8563 | AF10: 345.12673 | AG10: 757.31294 | AH10: 750.30564 | AI10: 1926.1978 | AJ10: 1125.2498 | AK10: 1310.9118 | AL10: 513.2946 | AM10: 584.85669 | AN10: 1616.0344 | AO10: 1668.7112 | AP10: 1758.1165 | AQ10: 2159.7701 | AR10: 624.30721 | AS10: 880.63414 | AT10: 1190.3502 | AU10: 963.80601 | AV10: 2060.3277 | AW10: 2647.0554 | AX10: 1059.3792 | AY10: 1749.0891 | AZ10: 2062.002 | BA10: 2570.5338 | BB10: 3354.3487 | BC10: 4342.3774 | BD10: 750.37539 | BE10: 1562.6515 | BF10: 3075.5316 | BG10: 1871.3168 | BH10: 3071.7903 | BI10: 2672.9975 | BJ10: 0
A11: DNK | B11: 1879.4862 | C11: 686.44553 | D11: 1939.9121 | E11: 2101.4411 | F11: 1029.2391 | G11: 2979.8982 | H11: 2042.7877 | I11: 1087.0214 | J11: 2953.6853 | K11: 1393.6007 | L11: 2900.8 | M11: 2544.0771 | N11: 2038.5805 | O11: 1671.7666 | P11: 2006.9445 | Q11: 7490.4236 | R11: 2000.183 | S11: 3030.5493 | T11: 2491.0172 | U11: 723.68833 | V11: 3673.6902 | W11: 2754.7353 | X11: 4006.7148 | Y11: 3080.8427 | Z11: 3225.0066 | AA11: 1608.3578 | AB11: 9237.6039 | AC11: 9855.1025 | AD11: 3596.7101 | AE11: 3467.7233 | AF11: 3294.8943 | AG11: 1988.1858 | AH11: 6298.2487 | AI11: 3823.7975 | AJ11: 5290.7617 | AK11: 5807.8803 | AL11: 3862.9016 | AM11: 1239.145 | AN11: 6540.6316 | AO11: 26854.747 | AP11: 24835.238 | AQ11: 7053.8553 | AR11: 3276.8612 | AS11: 917.07638 | AT11: 6326.8941 | AU11: 5086.8386 | AV11: 7723.447 | AW11: 5292.0576 | AX11: 11547.78 | AY11: 5802.2464 | AZ11: 18120.933 | BA11: 47389.078 | BB11: 17347.022 | BC11: 15975.154 | BD11: 9869.1826 | BE11: 4342.1568 | BF11: 23917.358 | BG11: 15448.822 | BH11: 27799.75 | BI11: 13011.763 | BJ11: 0
A12: EST | B12: 620.82679 | C12: 354.43607 | D12: 924.12225 | E12: 1124.7457 | F12: 1107.9452 | G12: 1163.0627 | H12: 615.21166 | I12: 710.83328 | J12: 659.86389 | K12: 1312.6782 | L12: 1991.4488 | M12: 952.18096 | N12: 738.34497 | O12: 984.84538 | P12: 979.51753 | Q12: 1596.9412 | R12: 1837.9467 | S12: 2073.9517 | T12: 756.99778 | U12: 1221.6264 | V12: 1044.462 | W12: 2167.9436 | X12: 1292.5826 | Y12: 2893.5221 | Z12: 631.34829 | AA12: 547.00663 | AB12: 1366.0249 | AC12: 1168.1086 | AD12: 2401.9097 | AE12: 1939.876 | AF12: 486.47875 | AG12: 1070.0461 | AH12: 1114.3861 | AI12: 3022.3022 | AJ12: 1690.5781 | AK12: 1951.1351 | AL12: 778.1821 | AM12: 907.08801 | AN12: 2374.4717 | AO12: 2491.7478 | AP12: 2724.093 | AQ12: 3206.5614 | AR12: 912.42726 | AS12: 1317.0629 | AT12: 1785.4138 | AU12: 1484.8797 | AV12: 3083.1834 | AW12: 3869.8423 | AX12: 1594.625 | AY12: 2534.3625 | AZ12: 3054.164 | BA12: 3777.2911 | BB12: 5041.6456 | BC12: 6348.2759 | BD12: 1102.0061 | BE12: 2286.4129 | BF12: 4583.3182 | BG12: 2837.1919 | BH12: 4545.9299 | BI12: 3911.403 | BJ12: 0
A13: FIN | B13: 373.97646 | C13: 408.2127 | D13: 638.42808 | E13: 1516.8019 | F13: 2611.8393 | G13: 2002.6595 | H13: 823.68641 | I13: 693.1036 | J13: 2015.7764 | K13: 2341.9247 | L13: 3666.6689 | M13: 4556.1662 | N13: 813.29514 | O13: 1110.0072 | P13: 1794.0075 | Q13: 2537.3707 | R13: 4792.1748 | S13: 3721.4626 | T13: 1078.3289 | U13: 1315.8948 | V13: 3053.7502 | W13: 2853.7682 | X13: 5030.9248 | Y13: 3871.2754 | Z13: 1103.5089 | AA13: 743.65319 | AB13: 3249.9131 | AC13: 3252.1773 | AD13: 5277.9516 | AE13: 4155.5006 | AF13: 1373.1387 | AG13: 1264.2613 | AH13: 3767.3429 | AI13: 3676.4838 | AJ13: 6184.5737 | AK13: 4254.7581 | AL13: 1844.0387 | AM13: 735.41685 | AN13: 4832.0292 | AO13: 4633.9854 | AP13: 7053.9577 | AQ13: 4606.1328 | AR13: 2095.242 | AS13: 1778.8318 | AT13: 4290.0137 | AU13: 4007.6648 | AV13: 5353.6211 | AW13: 4853.3975 | AX13: 5244.2684 | AY13: 2950.7669 | AZ13: 14768.604 | BA13: 8138.5544 | BB13: 17003.093 | BC13: 18850.582 | BD13: 4251.5634 | BE13: 2605.3476 | BF13: 8967.4679 | BG13: 6666.3117 | BH13: 9219.62 | BI13: 8567.1292 | BJ13: 0
A14: FRA | B14: 759.90747 | C14: 284.31917 | D14: 1179.2891 | E14: 675.74917 | F14: 2550.2437 | G14: 1590.8349 | H14: 1056.8799 | I14: 447.50329 | J14: 1894.0848 | K14: 687.2641 | L14: 2218.724 | M14: 2184.1865 | N14: 812.04867 | O14: 658.91669 | P14: 1498.3261 | Q14: 1648.1037 | R14: 3646.8588 | S14: 2095.1175 | T14: 1079.5975 | U14: 826.2544 | V14: 1994.8422 | W14: 1591.9661 | X14: 2695.7656 | Y14: 2381.5755 | Z14: 1178.0078 | AA14: 639.00924 | AB14: 2024.6697 | AC14: 2901.6652 | AD14: 4521.1625 | AE14: 3017.2969 | AF14: 1913.2223 | AG14: 825.07835 | AH14: 2613.4269 | AI14: 2194.2272 | AJ14: 4439.5821 | AK14: 3062.3568 | AL14: 1930.994 | AM14: 475.38524 | AN14: 4318.2371 | AO14: 3319.3407 | AP14: 6400.2615 | AQ14: 4666.643 | AR14: 1791.1716 | AS14: 1013.6507 | AT14: 3272.4748 | AU14: 3023.4931 | AV14: 4217.4171 | AW14: 3508.0558 | AX14: 9704.8439 | AY14: 1896.9817 | AZ14: 23960.741 | BA14: 8319.2619 | BB14: 11905.133 | BC14: 31594.11 | BD14: 4864.82 | BE14: 1597.0277 | BF14: 9296.6079 | BG14: 6866.16 | BH14: 8018.402 | BI14: 10047.244 | BJ14: 0
A15: DEU | B15: 3489.4028 | C15: 1236.5754 | D15: 2484.0521 | E15: 1804.6885 | F15: 6016.2709 | G15: 2163.1237 | H15: 2522.7172 | I15: 1281.8235 | J15: 3702.4516 | K15: 1892.0376 | L15: 4129.9243 | M15: 3967.6337 | N15: 2838.4058 | O15: 2728.5449 | P15: 3424.3566 | Q15: 3230.784 | R15: 5018.7296 | S15: 4176.8995 | T15: 3277.1757 | U15: 1751.1384 | V15: 3834.0497 | W15: 2981.7408 | X15: 5512.2356 | Y15: 4651.0168 | Z15: 3371.2934 | AA15: 2712.0723 | AB15: 4981.8198 | AC15: 5203.2081 | AD15: 10273.287 | AE15: 5785.421 | AF15: 4948.6661 | AG15: 2529.8789 | AH15: 5427.3297 | AI15: 4301.5899 | AJ15: 7159.3873 | AK15: 5858.3819 | AL15: 5883.5552 | AM15: 2290.4663 | AN15: 9248.9752 | AO15: 28842.781 | AP15: 22201.96 | AQ15: 8865.3851 | AR15: 4101.4463 | AS15: 1756.6607 | AT15: 7262.4575 | AU15: 5785.8976 | AV15: 9165.6234 | AW15: 6821.4908 | AX15: 23657.465 | AY15: 10359.854 | AZ15: 50798.325 | BA15: 20409.023 | BB15: 37671.599 | BC15: 80348.42 | BD15: 12248.61 | BE15: 4777.0444 | BF15: 44517.921 | BG15: 19373.034 | BH15: 25094.538 | BI15: 25157.516 | BJ15: 0
A16: GRC | B16: 529.38466 | C16: 502.90144 | D16: 906.56073 | E16: 954.39621 | F16: 1042.1631 | G16: 713.81001 | H16: 757.16202 | I16: 702.06998 | J16: 1020.653 | K16: 1139.9535 | L16: 1586.6413 | M16: 1572.3932 | N16: 812.62011 | O16: 1200.3305 | P16: 1248.0617 | Q16: 1030.9093 | R16: 1532.5594 | S16: 1233.3286 | T16: 974.81143 | U16: 1321.7515 | V16: 1442.927 | W16: 1633.9352 | X16: 1622.0106 | Y16: 1904.9222 | Z16: 911.2535 | AA16: 908.63988 | AB16: 1672.0683 | AC16: 2084.5018 | AD16: 2034.7613 | AE16: 1237.1498 | AF16: 845.49564 | AG16: 1284.827 | AH16: 1460.716 | AI16: 1899.3989 | AJ16: 2173.2146 | AK16: 2434.9255 | AL16: 1069.5044 | AM16: 896.52981 | AN16: 2261.091 | AO16: 2050.9296 | AP16: 3107.6839 | AQ16: 2524.5398 | AR16: 1122.8777 | AS16: 1737.3668 | AT16: 2001.8257 | AU16: 2083.587 | AV16: 2589.0431 | AW16: 2361.6409 | AX16: 2113.4872 | AY16: 3383.5449 | AZ16: 3311.8941 | BA16: 4934.1171 | BB16: 4015.164 | BC16: 3614.699 | BD16: 1726.6338 | BE16: 2598.3548 | BF16: 3071.9238 | BG16: 3772.7623 | BH16: 3903.2445 | BI16: 6008.9313 | BJ16: 0
... A39: LROW | B39: 0 | C39: 0 | D39: 0 | E39: 0 | F39: 0 | G39: 0 | H39: 0 | I39: 0 | J39: 0 | K39: 0 | L39: 0 | M39: 0 | N39: 0 | O39: 0 | P39: 0 | Q39: 0 | R39: 0 | S39: 0 | T39: 0 | U39: 0 | V39: 0 | W39: 0 | X39: 0 | Y39: 0 | Z39: 0 | AA39: 0 | AB39: 0 | AC39: 0 | AD39: 0 | AE39: 0 | AF39: 0 | AG39: 0 | AH39: 0 | AI39: 0 | AJ39: 0 | AK39: 0 | AL39: 0 | AM39: 0 | AN39: 0 | AO39: 0 | AP39: 0 | AQ39: 0 | AR39: 0 | AS39: 0 | AT39: 0 | AU39: 0 | AV39: 0 | AW39: 0 | AX39: 0 | AY39: 0 | AZ39: 0 | BA39: 0 | BB39: 0 | BC39: 0 | BD39: 0 | BE39: 0 | BF39: 0 | BG39: 0 | BH39: 0 | BI39: 0 | BJ39: 120.71603

Sheet HH_Property_income_paid
B4: INCOME1_DENSE_SINGLE | C4: INCOME1_DENSE_SINGLEWCHILDREN | D4: INCOME1_DENSE_COUPLE | E4: INCOME1_DENSE_COUPLEWCHILDREN | F4: INCOME1_DENSE_OTHER | G4: INCOME1_DENSE_OTHERWCHILDREN | H4: INCOME1_SPARSE_SINGLE | I4: INCOME1_SPARSE_SINGLEWCHILDREN | J4: INCOME1_SPARSE_COUPLE | K4: INCOME1_SPARSE_COUPLEWCHILDREN | L4: INCOME1_SPARSE_OTHER | M4: INCOME1_SPARSE_OTHERWCHILDREN | N4: INCOME2_DENSE_SINGLE | O4: INCOME2_DENSE_SINGLEWCHILDREN | P4: INCOME2_DENSE_COUPLE | Q4: INCOME2_DENSE_COUPLEWCHILDREN | R4: INCOME2_DENSE_OTHER | S4: INCOME2_DENSE_OTHERWCHILDREN | T4: INCOME2_SPARSE_SINGLE | U4: INCOME2_SPARSE_SINGLEWCHILDREN | V4: INCOME2_SPARSE_COUPLE | W4: INCOME2_SPARSE_COUPLEWCHILDREN | X4: INCOME2_SPARSE_OTHER | Y4: INCOME2_SPARSE_OTHERWCHILDREN | Z4: INCOME3_DENSE_SINGLE | AA4: INCOME3_DENSE_SINGLEWCHILDREN | AB4: INCOME3_DENSE_COUPLE | AC4: INCOME3_DENSE_COUPLEWCHILDREN | AD4: INCOME3_DENSE_OTHER | AE4: INCOME3_DENSE_OTHERWCHILDREN | AF4: INCOME3_SPARSE_SINGLE | AG4: INCOME3_SPARSE_SINGLEWCHILDREN | AH4: INCOME3_SPARSE_COUPLE | AI4: INCOME3_SPARSE_COUPLEWCHILDREN | AJ4: INCOME3_SPARSE_OTHER | AK4: INCOME3_SPARSE_OTHERWCHILDREN | AL4: INCOME4_DENSE_SINGLE | AM4: INCOME4_DENSE_SINGLEWCHILDREN | AN4: INCOME4_DENSE_COUPLE | AO4: INCOME4_DENSE_COUPLEWCHILDREN | AP4: INCOME4_DENSE_OTHER | AQ4: INCOME4_DENSE_OTHERWCHILDREN | AR4: INCOME4_SPARSE_SINGLE | AS4: INCOME4_SPARSE_SINGLEWCHILDREN | AT4: INCOME4_SPARSE_COUPLE | AU4: INCOME4_SPARSE_COUPLEWCHILDREN | AV4: INCOME4_SPARSE_OTHER | AW4: INCOME4_SPARSE_OTHERWCHILDREN | AX4: INCOME5_DENSE_SINGLE | AY4: INCOME5_DENSE_SINGLEWCHILDREN | AZ4: INCOME5_DENSE_COUPLE | BA4: INCOME5_DENSE_COUPLEWCHILDREN | BB4: INCOME5_DENSE_OTHER | BC4: INCOME5_DENSE_OTHERWCHILDREN | BD4: INCOME5_SPARSE_SINGLE | BE4: INCOME5_SPARSE_SINGLEWCHILDREN | BF4: INCOME5_SPARSE_COUPLE | BG4: INCOME5_SPARSE_COUPLEWCHILDREN | BH4: INCOME5_SPARSE_OTHER | BI4: INCOME5_SPARSE_OTHERWCHILDREN | BJ4: REPRESENTATIVE_HOUSEHOLD
A5: AUT | B5: 0 | C5: 0 | D5: 0 | E5: 0 | F5: 0 | G5: 0 | H5: 0 | I5: 0 | J5: 0 | K5: 0 | L5: 0 | M5: 0 | N5: 0 | O5: 0 | P5: 0 | Q5: 0 | R5: 0 | S5: 0 | T5: 0 | U5: 0 | V5: 0 | W5: 0 | X5: 0 | Y5: 0 | Z5: 0 | AA5: 0 | AB5: 0 | AC5: 0 | AD5: 0 | AE5: 0 | AF5: 0 | AG5: 0 | AH5: 0 | AI5: 0 | AJ5: 0 | AK5: 0 | AL5: 0 | AM5: 0 | AN5: 0 | AO5: 0 | AP5: 0 | AQ5: 0 | AR5: 0 | AS5: 0 | AT5: 0 | AU5: 0 | AV5: 0 | AW5: 0 | AX5: 0 | AY5: 0 | AZ5: 0 | BA5: 0 | BB5: 0 | BC5: 0 | BD5: 0 | BE5: 0 | BF5: 0 | BG5: 0 | BH5: 0 | BI5: 0 | BJ5: 481.78451
A6: BEL | B6: 33.953954 | C6: 353.36577 | D6: 86.456648 | E6: 171.31109 | F6: 99.516393 | G6: 155.48172 | H6: 158.61597 | I6: 208.55394 | J6: 124.30246 | K6: 804.74378 | L6: 398.31155 | M6: 508.98545 | N6: 140.47116 | O6: 174.02862 | P6: 267.19113 | Q6: 435.43468 | R6: 506.33484 | S6: 263.07079 | T6: 163.18333 | U6: 348.09019 | V6: 258.73301 | W6: 1349.8997 | X6: 521.40219 | Y6: 648.85944 | Z6: 188.59721 | AA6: 291.17001 | AB6: 356.79989 | AC6: 1194.6258 | AD6: 318.21253 | AE6: 601.74545 | AF6: 271.68476 | AG6: 224.86526 | AH6: 407.68072 | AI6: 1829.2158 | AJ6: 616.38386 | AK6: 900.03421 | AL6: 357.73778 | AM6: 399.37609 | AN6: 621.2217 | AO6: 1669.2717 | AP6: 302.99459 | AQ6: 1006.4756 | AR6: 319.08022 | AS6: 405.37758 | AT6: 489.87636 | AU6: 1558.5807 | AV6: 2507.8527 | AW6: 1228.3238 | AX6: 469.80582 | AY6: 150.7434 | AZ6: 457.54523 | BA6: 1322.3892 | BB6: 121.87346 | BC6: 1556.7157 | BD6: 273.84509 | BE6: 792.74899 | BF6: 343.29504 | BG6: 1165.5467 | BH6: 356.93252 | BI6: 1233.6052 | BJ6: 0
A7: BGR | B7: 151.80714 | C7: 8.573292 | D7: 64.825029 | E7: 53.696973 | F7: 64.159877 | G7: 48.926762 | H7: 88.241398 | I7: 28.495111 | J7: 68.640798 | K7: 112.76193 | L7: 118.00749 | M7: 128.13419 | N7: 44.941212 | O7: 11.582897 | P7: 108.86185 | Q7: 189.57554 | R7: 260.97327 | S7: 140.36886 | T7: 144.49375 | U7: 65.355129 | V7: 112.66157 | W7: 144.87246 | X7: 136.33382 | Y7: 175.18138 | Z7: 63.275161 | AA7: 1.6687288 | AB7: 171.43655 | AC7: 286.46509 | AD7: 253.07771 | AE7: 200.56891 | AF7: 97.402845 | AG7: 102.21515 | AH7: 91.003046 | AI7: 148.64405 | AJ7: 168.23593 | AK7: 170.80049 | AL7: 100.17659 | AM7: 2.4698504 | AN7: 110.47834 | AO7: 133.19421 | AP7: 322.71628 | AQ7: 272.10539 | AR7: 59.769883 | AS7: 139.07517 | AT7: 139.63544 | AU7: 173.97775 | AV7: 176.53897 | AW7: 295.41867 | AX7: 81.011725 | AY7: 173.63941 | AZ7: 271.88494 | BA7: 241.82275 | BB7: 369.40908 | BC7: 579.62763 | BD7: 98.54281 | BE7: 175.93518 | BF7: 157.48474 | BG7: 163.69147 | BH7: 441.21876 | BI7: 198.42519 | BJ7: 0
A8: HRV | B8: 54.087136 | C8: 144.73614 | D8: 57.731513 | E8: 218.626 | F8: 159.68843 | G8: 159.33187 | H8: 33.032526 | I8: 0 | J8: 73.981018 | K8: 133.22558 | L8: 110.28032 | M8: 188.67831 | N8: 110.41949 | O8: 405.58593 | P8: 195.64794 | Q8: 421.04778 | R8: 359.50342 | S8: 408.80873 | T8: 37.778868 | U8: 115.70121 | V8: 61.282499 | W8: 249.64543 | X8: 314.50228 | Y8: 96.846964 | Z8: 133.36785 | AA8: 113.24773 | AB8: 317.64648 | AC8: 397.80846 | AD8: 346.81011 | AE8: 200.10012 | AF8: 57.483117 | AG8: 238.75334 | AH8: 154.63556 | AI8: 371.9808 | AJ8: 317.77231 | AK8: 430.7002 | AL8: 47.525116 | AM8: 500.71668 | AN8: 376.82211 | AO8: 425.44005 | AP8: 410.97535 | AQ8: 317.07514 | AR8: 91.886461 | AS8: 361.80547 | AT8: 282.32597 | AU8: 470.9663 | AV8: 551.28033 | AW8: 352.11601 | AX8: 291.71064 | AY8: 509.32004 | AZ8: 937.8113 | BA8: 1158.0172 | BB8: 396.61687 | BC8: 1382.5161 | BD8: 91.398777 | BE8: 484.85761 | BF8: 729.53771 | BG8: 798.39357 | BH8: 585.5893 | BI8: 637.32456 | BJ8: 0
A9: CYP | B9: 242.14295 | C9: 1182.5009 | D9: 426.25974 | E9: 1049.6104 | F9: 974.92305 | G9: 1240.1375 | H9: 282.90311 | I9: 305.28025 | J9: 459.99551 | K9: 708.90737 | L9: 1021.3562 | M9: 910.79052 | N9: 416.45366 | O9: 582.36822 | P9: 458.78398 | Q9: 854.31314 | R9: 1271.189 | S9: 1764.2869 | T9: 364.42514 | U9: 184.71194 | V9: 566.31319 | W9: 943.54589 | X9: 813.06314 | Y9: 895.03576 | Z9: 307.01061 | AA9: 974.3694 | AB9: 1195.3598 | AC9: 1213.1634 | AD9: 1407.3649 | AE9: 1241.5434 | AF9: 271.37648 | AG9: 876.55012 | AH9: 858.55237 | AI9: 1121.425 | AJ9: 1223.414 | AK9: 1186.4897 | AL9: 485.70181 | AM9: 1336.4695 | AN9: 1095.2643 | AO9: 1872.4771 | AP9: 1257.7104 | AQ9: 1675.6174 | AR9: 162.92839 | AS9: 326.41806 | AT9: 713.31361 | AU9: 808.69102 | AV9: 1799.0714 | AW9: 2387.9142 | AX9: 751.55149 | AY9: 504.44672 | AZ9: 1893.8277 | BA9: 2122.6648 | BB9: 1342.1451 | BC9: 2531.8916 | BD9: 575.52225 | BE9: 997.27569 | BF9: 1224.7193 | BG9: 1337.0295 | BH9: 2174.3557 | BI9: 1824.7141 | BJ9: 0
A10: CZE | B10: 47.079835 | C10: 220.64371 | D10: 79.268003 | E10: 249.56065 | F10: 108.07156 | G10: 32.018516 | H10: 30.229487 | I10: 43.362282 | J10: 64.432644 | K10: 184.17426 | L10: 95.65206 | M10: 118.4919 | N10: 1.1507293 | O10: 108.66451 | P10: 33.163857 | Q10: 228.60936 | R10: 111.0438 | S10: 91.859801 | T10: 43.407633 | U10: 81.834122 | V10: 73.96059 | W10: 214.61499 | X10: 147.71566 | Y10: 140.69511 | Z10: 36.411946 | AA10: 181.8083 | AB10: 44.387194 | AC10: 278.17155 | AD10: 271.72296 | AE10: 131.25575 | AF10: 58.028886 | AG10: 120.30596 | AH10: 76.298849 | AI10: 252.56904 | AJ10: 169.468 | AK10: 177.59767 | AL10: 82.09082 | AM10: 249.37283 | AN10: 93.336368 | AO10: 252.39194 | AP10: 324.77497 | AQ10: 178.07046 | AR10: 64.014852 | AS10: 158.7778 | AT10: 61.10954 | AU10: 240.02989 | AV10: 105.62808 | AW10: 379.39474 | AX10: 250.77425 | AY10: 94.125085 | AZ10: 221.31376 | BA10: 675.98547 | BB10: 185.49599 | BC10: 379.31831 | BD10: 68.84205 | BE10: 197.24964 | BF10: 122.72388 | BG10: 327.36362 | BH10: 232.17996 | BI10: 369.7872 | BJ10: 0
A11: DNK | B11: 1072.0727 | C11: 1725.8077 | D11: 942.85995 | E11: 589.27252 | F11: 1444.9279 | G11: 1992.2813 | H11: 679.87251 | I11: 1336.4972 | J11: 777.96645 | K11: 1172.4114 | L11: 1766.5007 | M11: 1137.0346 | N11: 1206.8115 | O11: 849.94064 | P11: 1883.0148 | Q11: 1132.5179 | R11: 1884.022 | S11: 2834.3276 | T11: 1553.0981 | U11: 808.65693 | V11: 2301.843 | W11: 3800.794 | X11: 1337.9718 | Y11: 2590.6629 | Z11: 903.95613 | AA11: 1422.049 | AB11: 1290.2184 | AC11: 2583.917 | AD11: 2085.8476 | AE11: 1994.54 | AF11: 1557.1238 | AG11: 3837.4797 | AH11: 1629.1304 | AI11: 5551.6705 | AJ11: 1758.8961 | AK11: 6307.1462 | AL11: 3309.4266 | AM11: 1950.5181 | AN11: 2431.6385 | AO11: 3647.5743 | AP11: 1864.0455 | AQ11: 2691.88 | AR11: 1299.275 | AS11: 1429.0371 | AT11: 3222.9705 | AU11: 4410.1483 | AV11: 2257.7299 | AW11: 3234.8578 | AX11: 1624.2241 | AY11: 736.21767 | AZ11: 4781.0951 | BA11: 11861.174 | BB11: 1989.1856 | BC11: 4067.4849 | BD11: 2189.5275 | BE11: 4366.0084 | BF11: 3701.6526 | BG11: 5438.4863 | BH11: 2642.0576 | BI11: 4723.0105 | BJ11: 0
A12: EST | B12: -26.115713 | C12: -41.486178 | D12: -24.524841 | E12: -65.117865 | F12: -16.342802 | G12: -112.20716 | H12: -6.2897669 | I12: -11.706268 | J12: -18.973068 | K12: -116.56567 | L12: -109.13972 | M12: -81.362491 | N12: -33.495569 | O12: -116.25438 | P12: -19.557175 | Q12: -75.708294 | R12: -21.352016 | S12: -121.66861 | T12: -7.2442045 | U12: -41.58324 | V12: -25.365085 | W12: -173.80765 | X12: -82.392802 | Y12: -186.41433 | Z12: -41.450336 | AA12: -32.460556 | AB12: -14.241783 | AC12: -215.56616 | AD12: -131.13995 | AE12: -210.54278 | AF12: -12.199044 | AG12: -68.076539 | AH12: -74.909352 | AI12: -232.08479 | AJ12: -182.95654 | AK12: -145.15767 | AL12: -47.543275 | AM12: -143.52201 | AN12: -108.95963 | AO12: -320.99818 | AP12: -220.36646 | AQ12: -232.33718 | AR12: -55.044725 | AS12: -258.0587 | AT12: -55.820963 | AU12: -262.30614 | AV12: -196.77558 | AW12: -301.36592 | AX12: -73.731047 | AY12: -145.98801 | AZ12: -216.32475 | BA12: -517.5606 | BB12: -268.95654 | BC12: -328.67027 | BD12: -50.725604 | BE12: -85.49406 | BF12: -222.02289 | BG12: -476.98258 | BH12: -388.21518 | BI12: -358.48299 | BJ12: 0
A13: FIN | B13: 39.160521 | C13: 275.00893 | D13: 104.8351 | E13: 381.58674 | F13: 363.90734 | G13: 632.32508 | H13: 54.232685 | I13: 231.28918 | J13: 175.18722 | K13: 789.55872 | L13: 439.6415 | M13: 660.44976 | N13: 33.389115 | O13: 135.43877 | P13: 170.69392 | Q13: 738.69223 | R13: 476.28383 | S13: 689.37699 | T13: 72.719669 | U13: 139.94313 | V13: 145.62741 | W13: 895.83592 | X13: 565.46559 | Y13: 608.99096 | Z13: 87.569711 | AA13: 226.60473 | AB13: 339.66747 | AC13: 886.79525 | AD13: 709.58326 | AE13: 724.12068 | AF13: 44.64263 | AG13: 664.09981 | AH13: 267.88043 | AI13: 934.63415 | AJ13: 518.78408 | AK13: 991.36294 | AL13: 200.30562 | AM13: 310.81673 | AN13: 557.88042 | AO13: 1128.8297 | AP13: 590.20052 | AQ13: 1129.0068 | AR13: 187.18281 | AS13: 247.3038 | AT13: 416.61394 | AU13: 992.95449 | AV13: 682.73403 | AW13: 765.48114 | AX13: 467.15287 | AY13: 117.31691 | AZ13: 752.80701 | BA13: 1251.0426 | BB13: 952.86134 | BC13: 1795.8487 | BD13: 316.96874 | BE13: 755.565 | BF13: 671.07561 | BG13: 1084.5855 | BH13: 910.76895 | BI13: 1503.7249 | BJ13: 0
A14: FRA | B14: 230.02138 | C14: 64.243702 | D14: 338.73916 | E14: 172.06327 | F14: 197.7259 | G14: 252.23563 | H14: 341.56078 | I14: 34.477903 | J14: 672.56523 | K14: 122.85408 | L14: 416.66069 | M14: 140.95519 | N14: 297.32114 | O14: 180.02651 | P14: 272.37958 | Q14: 447.72136 | R14: 389.79955 | S14: 426.77574 | T14: 493.51641 | U14: 122.4731 | V14: 528.71195 | W14: 462.7733 | X14: 422.19396 | Y14: 448.82152 | Z14: 323.6164 | AA14: 50.267015 | AB14: 256.40643 | AC14: 754.76146 | AD14: 664.76382 | AE14: 976.20248 | AF14: 689.79184 | AG14: 200.50252 | AH14: 282.15316 | AI14: 576.36219 | AJ14: 1029.8241 | AK14: 698.06536 | AL14: 311.13399 | AM14: 222.25198 | AN14: 719.50395 | AO14: 1105.1563 | AP14: 1224.9413 | AQ14: 1632.79 | AR14: 808.88576 | AS14: 760.04775 | AT14: 522.52914 | AU14: 651.74276 | AV14: 1082.9378 | AW14: 748.42546 | AX14: 952.98366 | AY14: 226.07073 | AZ14: 3019.3879 | BA14: 2404.067 | BB14: 1395.5495 | BC14: 2525.4362 | BD14: 664.74505 | BE14: 251.8015 | BF14: 1221.843 | BG14: 1349.6285 | BH14: 1178.5048 | BI14: 2165.7843 | BJ14: 0
A15: DEU | B15: 60.760613 | C15: 632.34817 | D15: 154.7142 | E15: 306.56125 | F15: 178.08462 | G15: 278.23459 | H15: 283.84333 | I15: 373.20735 | J15: 222.4393 | K15: 1440.0893 | L15: 712.77865 | M15: 910.82963 | N15: 251.37318 | O15: 311.42427 | P15: 478.13862 | Q15: 779.2105 | R15: 906.08636 | S15: 470.76527 | T15: 292.01663 | U15: 622.90751 | V15: 463.00281 | W15: 2415.646 | X15: 933.0494 | Y15: 1161.1342 | Z15: 337.49476 | AA15: 521.04883 | AB15: 638.49351 | AC15: 2137.7832 | AD15: 569.44142 | AE15: 1076.8237 | AF15: 486.17997 | AG15: 402.39645 | AH15: 729.54478 | AI15: 3273.3822 | AJ15: 1103.0191 | AK15: 1610.6115 | AL15: 640.17188 | AM15: 714.68365 | AN15: 1111.6764 | AO15: 2987.1623 | AP15: 542.20892 | AQ15: 1801.0884 | AR15: 570.99416 | AS15: 725.42331 | AT15: 876.63391 | AU15: 2789.0806 | AV15: 4487.8033 | AW15: 2198.0858 | AX15: 840.71766 | AY15: 269.75537 | AZ15: 818.77734 | BA15: 2366.4159 | BB15: 218.09259 | BC15: 2785.7433 | BD15: 490.04588 | BE15: 1418.6246 | BF15: 614.32659 | BG15: 2085.7461 | BH15: 638.73087 | BI15: 2207.5369 | BJ15: 0
A16: GRC | B16: 66.939965 | C16: 465.32941 | D16: 141.34696 | E16: 196.71019 | F16: 189.43214 | G16: 124.13601 | H16: 86.404228 | I16: 200.77291 | J16: 171.686 | K16: 270.97605 | L16: 267.88716 | M16: 171.95353 | N16: 56.02932 | O16: 229.16943 | P16: 130.15288 | Q16: 226.4258 | R16: 323.19303 | S16: 425.25581 | T16: 65.429298 | U16: 335.10314 | V16: 145.97063 | W16: 356.63336 | X16: 436.34052 | Y16: 343.82295 | Z16: 147.94477 | AA16: 383.42697 | AB16: 221.09909 | AC16: 481.35587 | AD16: 307.65577 | AE16: 110.59293 | AF16: 93.022319 | AG16: 216.47566 | AH16: 150.1022 | AI16: 580.32238 | AJ16: 380.78591 | AK16: 418.4552 | AL16: 89.985605 | AM16: 525.91806 | AN16: 267.05051 | AO16: 358.9784 | AP16: 394.229 | AQ16: 452.05261 | AR16: 68.975615 | AS16: 390.25317 | AT16: 257.49871 | AU16: 530.45993 | AV16: 337.42237 | AW16: 649.81534 | AX16: 136.28935 | AY16: 198.50632 | AZ16: 428.61619 | BA16: 867.20261 | BB16: 410.73603 | BC16: 561.34785 | BD16: 217.34669 | BE16: 763.17196 | BF16: 360.16931 | BG16: 578.25239 | BH16: 464.79615 | BI16: 720.58769 | BJ16: 0
... A39: LROW | B39: 0 | C39: 0 | D39: 0 | E39: 0 | F39: 0 | G39: 0 | H39: 0 | I39: 0 | J39: 0 | K39: 0 | L39: 0 | M39: 0 | N39: 0 | O39: 0 | P39: 0 | Q39: 0 | R39: 0 | S39: 0 | T39: 0 | U39: 0 | V39: 0 | W39: 0 | X39: 0 | Y39: 0 | Z39: 0 | AA39: 0 | AB39: 0 | AC39: 0 | AD39: 0 | AE39: 0 | AF39: 0 | AG39: 0 | AH39: 0 | AI39: 0 | AJ39: 0 | AK39: 0 | AL39: 0 | AM39: 0 | AN39: 0 | AO39: 0 | AP39: 0 | AQ39: 0 | AR39: 0 | AS39: 0 | AT39: 0 | AU39: 0 | AV39: 0 | AW39: 0 | AX39: 0 | AY39: 0 | AZ39: 0 | BA39: 0 | BB39: 0 | BC39: 0 | BD39: 0 | BE39: 0 | BF39: 0 | BG39: 0 | BH39: 0 | BI39: 0 | BJ39: 98.48023

Sheet HH_Other_transfers_rec
B4: INCOME1_DENSE_SINGLE | C4: INCOME1_DENSE_SINGLEWCHILDREN | D4: INCOME1_DENSE_COUPLE | E4: INCOME1_DENSE_COUPLEWCHILDREN | F4: INCOME1_DENSE_OTHER | G4: INCOME1_DENSE_OTHERWCHILDREN | H4: INCOME1_SPARSE_SINGLE | I4: INCOME1_SPARSE_SINGLEWCHILDREN | J4: INCOME1_SPARSE_COUPLE | K4: INCOME1_SPARSE_COUPLEWCHILDREN | L4: INCOME1_SPARSE_OTHER | M4: INCOME1_SPARSE_OTHERWCHILDREN | N4: INCOME2_DENSE_SINGLE | O4: INCOME2_DENSE_SINGLEWCHILDREN | P4: INCOME2_DENSE_COUPLE | Q4: INCOME2_DENSE_COUPLEWCHILDREN | R4: INCOME2_DENSE_OTHER | S4: INCOME2_DENSE_OTHERWCHILDREN | T4: INCOME2_SPARSE_SINGLE | U4: INCOME2_SPARSE_SINGLEWCHILDREN | V4: INCOME2_SPARSE_COUPLE | W4: INCOME2_SPARSE_COUPLEWCHILDREN | X4: INCOME2_SPARSE_OTHER | Y4: INCOME2_SPARSE_OTHERWCHILDREN | Z4: INCOME3_DENSE_SINGLE | AA4: INCOME3_DENSE_SINGLEWCHILDREN | AB4: INCOME3_DENSE_COUPLE | AC4: INCOME3_DENSE_COUPLEWCHILDREN | AD4: INCOME3_DENSE_OTHER | AE4: INCOME3_DENSE_OTHERWCHILDREN | AF4: INCOME3_SPARSE_SINGLE | AG4: INCOME3_SPARSE_SINGLEWCHILDREN | AH4: INCOME3_SPARSE_COUPLE | AI4: INCOME3_SPARSE_COUPLEWCHILDREN | AJ4: INCOME3_SPARSE_OTHER | AK4: INCOME3_SPARSE_OTHERWCHILDREN | AL4: INCOME4_DENSE_SINGLE | AM4: INCOME4_DENSE_SINGLEWCHILDREN | AN4: INCOME4_DENSE_COUPLE | AO4: INCOME4_DENSE_COUPLEWCHILDREN | AP4: INCOME4_DENSE_OTHER | AQ4: INCOME4_DENSE_OTHERWCHILDREN | AR4: INCOME4_SPARSE_SINGLE | AS4: INCOME4_SPARSE_SINGLEWCHILDREN | AT4: INCOME4_SPARSE_COUPLE | AU4: INCOME4_SPARSE_COUPLEWCHILDREN | AV4: INCOME4_SPARSE_OTHER | AW4: INCOME4_SPARSE_OTHERWCHILDREN | AX4: INCOME5_DENSE_SINGLE | AY4: INCOME5_DENSE_SINGLEWCHILDREN | AZ4: INCOME5_DENSE_COUPLE | BA4: INCOME5_DENSE_COUPLEWCHILDREN | BB4: INCOME5_DENSE_OTHER | BC4: INCOME5_DENSE_OTHERWCHILDREN | BD4: INCOME5_SPARSE_SINGLE | BE4: INCOME5_SPARSE_SINGLEWCHILDREN | BF4: INCOME5_SPARSE_COUPLE | BG4: INCOME5_SPARSE_COUPLEWCHILDREN | BH4: INCOME5_SPARSE_OTHER | BI4: INCOME5_SPARSE_OTHERWCHILDREN | BJ4: REPRESENTATIVE_HOUSEHOLD
A5: AUT | B5: 0 | C5: 0 | D5: 0 | E5: 0 | F5: 0 | G5: 0 | H5: 0 | I5: 0 | J5: 0 | K5: 0 | L5: 0 | M5: 0 | N5: 0 | O5: 0 | P5: 0 | Q5: 0 | R5: 0 | S5: 0 | T5: 0 | U5: 0 | V5: 0 | W5: 0 | X5: 0 | Y5: 0 | Z5: 0 | AA5: 0 | AB5: 0 | AC5: 0 | AD5: 0 | AE5: 0 | AF5: 0 | AG5: 0 | AH5: 0 | AI5: 0 | AJ5: 0 | AK5: 0 | AL5: 0 | AM5: 0 | AN5: 0 | AO5: 0 | AP5: 0 | AQ5: 0 | AR5: 0 | AS5: 0 | AT5: 0 | AU5: 0 | AV5: 0 | AW5: 0 | AX5: 0 | AY5: 0 | AZ5: 0 | BA5: 0 | BB5: 0 | BC5: 0 | BD5: 0 | BE5: 0 | BF5: 0 | BG5: 0 | BH5: 0 | BI5: 0 | BJ5: 1667.7827
A6: BEL | B6: 614.81606 | C6: 1750.6591 | D6: 1229.6321 | E6: 2517.9498 | F6: 2261.2587 | G6: 3841.7597 | H6: 614.81606 | I6: 1852.9528 | J6: 1229.6321 | K6: 2585.1815 | L6: 2200.7349 | M6: 3235.0663 | N6: 614.81606 | O6: 1733.2604 | P6: 1229.6321 | Q6: 2516.2009 | R6: 2305.1902 | S6: 3479.0837 | T6: 614.81606 | U6: 1702.8065 | V6: 1229.6321 | W6: 2461.0947 | X6: 2218.369 | Y6: 2994.8618 | Z6: 614.81606 | AA6: 1520.0046 | AB6: 1229.6321 | AC6: 2275.3374 | AD6: 2373.8199 | AE6: 3194.4182 | AF6: 614.81606 | AG6: 1479.9246 | AH6: 1229.6321 | AI6: 2355.2702 | AJ6: 2180.5821 | AK6: 3066.5816 | AL6: 614.81606 | AM6: 1539.4691 | AN6: 1229.6321 | AO6: 2305.9396 | AP6: 2135.7411 | AQ6: 2923.8562 | AR6: 614.81606 | AS6: 1448.504 | AT6: 1229.6321 | AU6: 2278.7288 | AV6: 2107.5896 | AW6: 2799.545 | AX6: 614.81606 | AY6: 1401.0417 | AZ6: 1229.6321 | BA6: 2149.5388 | BB6: 2184.3497 | BC6: 2989.3159 | BD6: 614.81606 | BE6: 1385.8803 | BF6: 1229.6321 | BG6: 2220.0949 | BH6: 2015.2958 | BI6: 2767.0413 | BJ6: 0
A7: BGR | B7: 187.17099 | C7: 476.98134 | D7: 374.34197 | E7: 711.31431 | F7: 621.79245 | G7: 1016.2514 | H7: 187.17099 | I7: 534.88402 | J7: 374.34197 | K7: 771.73364 | L7: 659.34166 | M7: 1152.2636 | N7: 187.17099 | O7: 472.24093 | P7: 374.34197 | Q7: 679.95307 | R7: 654.7684 | S7: 946.07962 | T7: 187.17099 | U7: 491.54192 | V7: 374.34197 | W7: 682.92057 | X7: 635.74024 | Y7: 1009.2673 | Z7: 187.17099 | AA7: 414.13763 | AB7: 374.34197 | AC7: 643.51583 | AD7: 633.43538 | AE7: 897.09661 | AF7: 187.17099 | AG7: 427.20354 | AH7: 374.34197 | AI7: 642.69762 | AJ7: 632.65288 | AK7: 1003.6161 | AL7: 187.17099 | AM7: 419.4409 | AN7: 374.34197 | AO7: 628.20825 | AP7: 632.8929 | AQ7: 837.14182 | AR7: 187.17099 | AS7: 418.1335 | AT7: 374.34197 | AU7: 638.15966 | AV7: 649.10202 | AW7: 918.43774 | AX7: 187.17099 | AY7: 381.72524 | AZ7: 374.34197 | BA7: 607.88502 | BB7: 626.84715 | BC7: 811.62916 | BD7: 187.17099 | BE7: 400.05619 | BF7: 374.34197 | BG7: 627.69466 | BH7: 617.95091 | BI7: 892.57168 | BJ7: 0
A8: HRV | B8: 353.17536 | C8: 1030.344 | D8: 706.35072 | E8: 1502.5834 | F8: 1244.0027 | G8: 2110.6057 | H8: 353.17536 | I8: 992.31847 | J8: 706.35072 | K8: 1532.4434 | L8: 1292.1672 | M8: 1945.8752 | N8: 353.17536 | O8: 1020.1041 | P8: 706.35072 | Q8: 1424.7101 | R8: 1304.3323 | S8: 1611.8965 | T8: 353.17536 | U8: 911.91008 | V8: 706.35072 | W8: 1470.2108 | X8: 1343.8704 | Y8: 1913.6178 | Z8: 353.17536 | AA8: 894.59316 | AB8: 706.35072 | AC8: 1234.6122 | AD8: 1287.6754 | AE8: 1672.2312 | AF8: 353.17536 | AG8: 792.54933 | AH8: 706.35072 | AI8: 1374.8399 | AJ8: 1337.9295 | AK8: 1921.0171 | AL8: 353.17536 | AM8: 906.04892 | AN8: 706.35072 | AO8: 1273.5783 | AP8: 1241.5722 | AQ8: 1601.7154 | AR8: 353.17536 | AS8: 775.72255 | AT8: 706.35072 | AU8: 1315.6132 | AV8: 1268.8265 | AW8: 1846.4098 | AX8: 353.17536 | AY8: 824.57803 | AZ8: 706.35072 | BA8: 1190.986 | BB8: 1208.8031 | BC8: 1574.329 | BD8: 353.17536 | BE8: 742.18547 | BF8: 706.35072 | BG8: 1226.7289 | BH8: 1272.9315 | BI8: 1748.2299 | BJ8: 0
A9: CYP | B9: 489.90446 | C9: 1273.5437 | D9: 979.80893 | E9: 1983.6234 | F9: 1883.7583 | G9: 2332.8006 | H9: 489.90446 | I9: 1543.8567 | J9: 979.80893 | K9: 1924.0481 | L9: 1935.6844 | M9: 2725.9779 | N9: 489.90446 | O9: 1260.8867 | P9: 979.80893 | Q9: 1683.567 | R9: 1829.5846 | S9: 2264.0939 | T9: 489.90446 | U9: 1418.7567 | V9: 979.80893 | W9: 2075.2534 | X9: 1856.906 | Y9: 2728.4302 | Z9: 489.90446 | AA9: 1105.7505 | AB9: 979.80893 | AC9: 1844.9902 | AD9: 1879.9847 | AE9: 2470.7588 | AF9: 489.90446 | AG9: 1233.0543 | AH9: 979.80893 | AI9: 1856.2896 | AJ9: 2019.0265 | AK9: 2500.837 | AL9: 489.90446 | AM9: 1119.9103 | AN9: 979.80893 | AO9: 1819.9476 | AP9: 1736.9714 | AQ9: 2423.3616 | AR9: 489.90446 | AS9: 1206.8751 | AT9: 979.80893 | AU9: 1748.9766 | AV9: 1832.7593 | AW9: 2611.4655 | AX9: 489.90446 | AY9: 1019.2092 | AZ9: 979.80893 | BA9: 1748.5019 | BB9: 1692.5861 | BC9: 2270.2506 | BD9: 489.90446 | BE9: 1154.6979 | BF9: 979.80893 | BG9: 1767.4785 | BH9: 1723.3762 | BI9: 2408.536 | BJ9: 0
A10: CZE | B10: 699.81534 | C10: 1803.3756 | D10: 1399.6307 | E10: 2679.2366 | F10: 2473.8144 | G10: 3131.1447 | H10: 699.81534 | I10: 1981.1615 | J10: 1399.6307 | K10: 2851.328 | L10: 2511.6276 | M10: 3511.3165 | N10: 699.81534 | O10: 1785.453 | P10: 1399.6307 | Q10: 2628.7115 | R10: 2265.796 | S10: 3347.3375 | T10: 699.81534 | U10: 1820.6264 | V10: 1399.6307 | W10: 2725.0518 | X10: 2472.979 | Y10: 3160.8504 | Z10: 699.81534 | AA10: 1565.7755 | AB10: 1399.6307 | AC10: 2456.6888 | AD10: 2232.0269 | AE10: 3159.3145 | AF10: 699.81534 | AG10: 1582.3229 | AH10: 1399.6307 | AI10: 2556.2169 | AJ10: 2441.1328 | AK10: 3177.6542 | AL10: 699.81534 | AM10: 1585.8261 | AN10: 1399.6307 | AO10: 2511.7863 | AP10: 2272.9355 | AQ10: 2996.1932 | AR10: 699.81534 | AS10: 1548.7283 | AT10: 1399.6307 | AU10: 2395.9794 | AV10: 2403.497 | AW10: 3061.845 | AX10: 699.81534 | AY10: 1443.2304 | AZ10: 1399.6307 | BA10: 2360.5759 | BB10: 2322.0911 | BC10: 3054.2265 | BD10: 699.81534 | BE10: 1481.7716 | BF10: 1399.6307 | BG10: 2515.3624 | BH10: 2368.1122 | BI10: 3171.211 | BJ10: 0
A11: DNK | B11: 1115.4369 | C11: 3059.3907 | D11: 2230.8738 | E11: 4571.3647 | F11: 3834.5892 | G11: 6424.3853 | H11: 1115.4369 | I11: 3189.654 | J11: 2230.8738 | K11: 4547.4703 | L11: 3911.3842 | M11: 5420.5675 | N11: 1115.4369 | O11: 2883.5504 | P11: 2230.8738 | Q11: 4334.7173 | R11: 3705.0857 | S11: 5117.0307 | T11: 1115.4369 | U11: 2946.1614 | V11: 2230.8738 | W11: 4552.4022 | X11: 3945.91 | Y11: 5210.0799 | Z11: 1115.4369 | AA11: 2454.8077 | AB11: 2230.8738 | AC11: 3849.1688 | AD11: 3709.4432 | AE11: 5198.8733 | AF11: 1115.4369 | AG11: 2626.3857 | AH11: 2230.8738 | AI11: 4302.3393 | AJ11: 3573.8686 | AK11: 5278.9189 | AL11: 1115.4369 | AM11: 2370.9865 | AN11: 2230.8738 | AO11: 3958.6162 | AP11: 3659.6721 | AQ11: 5049.1585 | AR11: 1115.4369 | AS11: 2578.9969 | AT11: 2230.8738 | AU11: 4201.0019 | AV11: 3611.5303 | AW11: 4845.405 | AX11: 1115.4369 | AY11: 2422.2978 | AZ11: 2230.8738 | BA11: 3864.6981 | BB11: 3678.8144 | BC11: 4752.3209 | BD11: 1115.4369 | BE11: 2332.688 | BF11: 2230.8738 | BG11: 4055.8528 | BH11: 3589.2846 | BI11: 4859.9566 | BJ11: 0
A12: EST | B12: 482.65912 | C12: 1227.9447 | D12: 965.31824 | E12: 1837.079 | F12: 1570.3466 | G12: 2425.0282 | H12: 482.65912 | I12: 1363.9889 | J12: 965.31824 | K12: 1922.7257 | L12: 1622.2872 | M12: 2665.3376 | N12: 482.65912 | O12: 1215.7409 | P12: 965.31824 | Q12: 1694.637 | R12: 1612.5802 | S12: 2321.2104 | T12: 482.65912 | U12: 1253.4637 | V12: 965.31824 | W12: 1880.1288 | X12: 1672.3065 | Y12: 2594.1034 | Z12: 482.65912 | AA12: 1066.1593 | AB12: 965.31824 | AC12: 1721.1629 | AD12: 1626.097 | AE12: 2197.2629 | AF12: 482.65912 | AG12: 1089.3967 | AH12: 965.31824 | AI12: 1738.7101 | AJ12: 1673.4436 | AK12: 2498.0324 | AL12: 482.65912 | AM12: 1079.8121 | AN12: 965.31824 | AO12: 1720.1 | AP12: 1560.7338 | AQ12: 2159.6502 | AR12: 482.65912 | AS12: 1066.2675 | AT12: 965.31824 | AU12: 1786.9264 | AV12: 1632.619 | AW12: 2300.2329 | AX12: 482.65912 | AY12: 982.71662 | AZ12: 965.31824 | BA12: 1652.407 | BB12: 1668.3193 | BC12: 2212.2899 | BD12: 482.65912 | BE12: 1020.1692 | BF12: 965.31824 | BG12: 1722.1686 | BH12: 1629.0188 | BI12: 2152.7557 | BJ12: 0
A13: FIN | B13: 433.72215 | C13: 1171.5606 | D13: 867.44431 | E13: 1809.5158 | F13: 1561.3632 | G13: 2519.0306 | H13: 433.72215 | I13: 1363.3783 | J13: 867.44431 | K13: 1989.2349 | L13: 1548.7053 | M13: 3030.4533 | N13: 433.72215 | O13: 1159.9172 | P13: 867.44431 | Q13: 1668.7531 | R13: 1419.5871 | S13: 1923.8159 | T13: 433.72215 | U13: 1252.9026 | V13: 867.44431 | W13: 1720.319 | X13: 1487.7223 | Y13: 2316.0517 | Z13: 433.72215 | AA13: 1017.204 | AB13: 867.44431 | AC13: 1581.6465 | AD13: 1414.9598 | AE13: 1995.826 | AF13: 433.72215 | AG13: 1088.909 | AH13: 867.44431 | AI13: 1714.7399 | AJ13: 1481.418 | AK13: 2091.7229 | AL13: 433.72215 | AM13: 1030.2298 | AN13: 867.44431 | AO13: 1540.9459 | AP13: 1357.0574 | AQ13: 1911.6645 | AR13: 433.72215 | AS13: 1065.7902 | AT13: 867.44431 | AU13: 1526.9075 | AV13: 1404.0293 | AW13: 1992.9371 | AX13: 433.72215 | AY13: 937.59273 | AZ13: 867.44431 | BA13: 1517.5805 | BB13: 1438.9067 | BC13: 1878.9786 | BD13: 433.72215 | BE13: 1019.7125 | BF13: 867.44431 | BG13: 1527.8322 | BH13: 1383.3361 | BI13: 1883.5245 | BJ13: 0
A14: FRA | B14: 1096.9931 | C14: 3690.0275 | D14: 2193.9862 | E14: 4650.6016 | F14: 4184.2452 | G14: 6420.8363 | H14: 1096.9931 | I14: 3118.3466 | J14: 2193.9862 | K14: 4633.8217 | L14: 3828.3114 | M14: 5855.1829 | N14: 1096.9931 | O14: 3179.9789 | P14: 2193.9862 | Q14: 4266.6268 | R14: 3868.6707 | S14: 5114.2039 | T14: 1096.9931 | U14: 2880.2975 | V14: 2193.9862 | W14: 4473.1535 | X14: 3900.7584 | Y14: 5459.609 | Z14: 1096.9931 | AA14: 2661.8457 | AB14: 2193.9862 | AC14: 4132.1305 | AD14: 4008.2601 | AE14: 5196.0013 | AF14: 1096.9931 | AG14: 2567.6707 | AH14: 2193.9862 | AI14: 4088.9375 | AJ14: 3846.3173 | AK14: 5174.5238 | AL14: 1096.9931 | AM14: 2565.3839 | AN14: 2193.9862 | AO14: 4050.8131 | AP14: 3551.2942 | AQ14: 5046.3693 | AR14: 1096.9931 | AS14: 2521.3412 | AT14: 2193.9862 | AU14: 3855.034 | AV14: 3712.9158 | AW14: 4848.3683 | AX14: 1096.9931 | AY14: 2405.3487 | AZ14: 2193.9862 | BA14: 3939.6208 | BB14: 3659.8524 | BC14: 4749.6956 | BD14: 1096.9931 | BE14: 2280.5388 | BF14: 2193.9862 | BG14: 3889.3226 | BH14: 3509.5216 | BI14: 4837.272 | BJ14: 0
A15: DEU | B15: 968.83331 | C15: 2493.1596 | D15: 1937.6666 | E15: 3864.9057 | F15: 3212.1029 | G15: 5046.4147 | H15: 968.83331 | I15: 2581.2366 | J15: 1937.6666 | K15: 3869.761 | L15: 3307.4846 | M15: 5188.7695 | N15: 968.83331 | O15: 2272.8148 | P15: 1937.6666 | Q15: 3635.146 | R15: 3398.9499 | S15: 4780.738 | T15: 968.83331 | U15: 2445.3094 | V15: 1937.6666 | W15: 3769.993 | X15: 3355.0934 | Y15: 5002.0747 | Z15: 968.83331 | AA15: 2134.7787 | AB15: 1937.6666 | AC15: 3488.7122 | AD15: 3180.0581 | AE15: 4217.6901 | AF15: 968.83331 | AG15: 2315.6582 | AH15: 1937.6666 | AI15: 3644.3745 | AJ15: 3255.9538 | AK15: 4375.2915 | AL15: 968.83331 | AM15: 2121.5643 | AN15: 1937.6666 | AO15: 3409.6498 | AP15: 3200.9365 | AQ15: 4110.8764 | AR15: 968.83331 | AS15: 2160.2095 | AT15: 1937.6666 | AU15: 3510.6644 | AV15: 3207.4391 | AW15: 4250.656 | AX15: 968.83331 | AY15: 2011.7496 | AZ15: 1937.6666 | BA15: 3259.4772 | BB15: 3075.6065 | BC15: 4099.1026 | BD15: 968.83331 | BE15: 2073.7206 | BF15: 1937.6666 | BG15: 3330.9095 | BH15: 3153.465 | BI15: 4459.1679 | BJ15: 0
A16: GRC | B16: 218.87503 | C16: 583.26271 | D16: 437.75006 | E16: 857.56898 | F16: 801.01537 | G16: 1062.9385 | H16: 218.87503 | I16: 635.5654 | J16: 437.75006 | K16: 870.39828 | L16: 809.80123 | M16: 1169.2007 | N16: 218.87503 | O16: 577.46603 | P16: 437.75006 | Q16: 810.22208 | R16: 786.62149 | S16: 1075.8588 | T16: 218.87503 | U16: 584.065 | V16: 437.75006 | W16: 876.51567 | X16: 779.27317 | Y16: 1197.99 | Z16: 218.87503 | AA16: 506.41611 | AB16: 437.75006 | AC16: 792.85116 | AD16: 760.35398 | AE16: 1011.5726 | AF16: 218.87503 | AG16: 507.61619 | AH16: 437.75006 | AI16: 815.65066 | AJ16: 773.78957 | AK16: 1117.2438 | AL16: 218.87503 | AM16: 512.90105 | AN16: 437.75006 | AO16: 779.53394 | AP16: 761.68509 | AQ16: 997.13754 | AR16: 218.87503 | AS16: 496.83889 | AT16: 437.75006 | AU16: 796.95002 | AV16: 776.68937 | AW16: 1099.692 | AX16: 218.87503 | AY16: 466.78157 | AZ16: 437.75006 | BA16: 741.85359 | BB16: 730.96798 | BC16: 926.41173 | BD16: 218.87503 | BE16: 475.35888 | BF16: 437.75006 | BG16: 749.64005 | BH16: 746.84363 | BI16: 1178.7964 | BJ16: 0
... A39: LROW | B39: 0 | C39: 0 | D39: 0 | E39: 0 | F39: 0 | G39: 0 | H39: 0 | I39: 0 | J39: 0 | K39: 0 | L39: 0 | M39: 0 | N39: 0 | O39: 0 | P39: 0 | Q39: 0 | R39: 0 | S39: 0 | T39: 0 | U39: 0 | V39: 0 | W39: 0 | X39: 0 | Y39: 0 | Z39: 0 | AA39: 0 | AB39: 0 | AC39: 0 | AD39: 0 | AE39: 0 | AF39: 0 | AG39: 0 | AH39: 0 | AI39: 0 | AJ39: 0 | AK39: 0 | AL39: 0 | AM39: 0 | AN39: 0 | AO39: 0 | AP39: 0 | AQ39: 0 | AR39: 0 | AS39: 0 | AT39: 0 | AU39: 0 | AV39: 0 | AW39: 0 | AX39: 0 | AY39: 0 | AZ39: 0 | BA39: 0 | BB39: 0 | BC39: 0 | BD39: 0 | BE39: 0 | BF39: 0 | BG39: 0 | BH39: 0 | BI39: 0 | BJ39: 357.32774

Sheet HH_Other_transfers_paid
B4: INCOME1_DENSE_SINGLE | C4: INCOME1_DENSE_SINGLEWCHILDREN | D4: INCOME1_DENSE_COUPLE | E4: INCOME1_DENSE_COUPLEWCHILDREN | F4: INCOME1_DENSE_OTHER | G4: INCOME1_DENSE_OTHERWCHILDREN | H4: INCOME1_SPARSE_SINGLE | I4: INCOME1_SPARSE_SINGLEWCHILDREN | J4: INCOME1_SPARSE_COUPLE | K4: INCOME1_SPARSE_COUPLEWCHILDREN | L4: INCOME1_SPARSE_OTHER | M4: INCOME1_SPARSE_OTHERWCHILDREN | N4: INCOME2_DENSE_SINGLE | O4: INCOME2_DENSE_SINGLEWCHILDREN | P4: INCOME2_DENSE_COUPLE | Q4: INCOME2_DENSE_COUPLEWCHILDREN | R4: INCOME2_DENSE_OTHER | S4: INCOME2_DENSE_OTHERWCHILDREN | T4: INCOME2_SPARSE_SINGLE | U4: INCOME2_SPARSE_SINGLEWCHILDREN | V4: INCOME2_SPARSE_COUPLE | W4: INCOME2_SPARSE_COUPLEWCHILDREN | X4: INCOME2_SPARSE_OTHER | Y4: INCOME2_SPARSE_OTHERWCHILDREN | Z4: INCOME3_DENSE_SINGLE | AA4: INCOME3_DENSE_SINGLEWCHILDREN | AB4: INCOME3_DENSE_COUPLE | AC4: INCOME3_DENSE_COUPLEWCHILDREN | AD4: INCOME3_DENSE_OTHER | AE4: INCOME3_DENSE_OTHERWCHILDREN | AF4: INCOME3_SPARSE_SINGLE | AG4: INCOME3_SPARSE_SINGLEWCHILDREN | AH4: INCOME3_SPARSE_COUPLE | AI4: INCOME3_SPARSE_COUPLEWCHILDREN | AJ4: INCOME3_SPARSE_OTHER | AK4: INCOME3_SPARSE_OTHERWCHILDREN | AL4: INCOME4_DENSE_SINGLE | AM4: INCOME4_DENSE_SINGLEWCHILDREN | AN4: INCOME4_DENSE_COUPLE | AO4: INCOME4_DENSE_COUPLEWCHILDREN | AP4: INCOME4_DENSE_OTHER | AQ4: INCOME4_DENSE_OTHERWCHILDREN | AR4: INCOME4_SPARSE_SINGLE | AS4: INCOME4_SPARSE_SINGLEWCHILDREN | AT4: INCOME4_SPARSE_COUPLE | AU4: INCOME4_SPARSE_COUPLEWCHILDREN | AV4: INCOME4_SPARSE_OTHER | AW4: INCOME4_SPARSE_OTHERWCHILDREN | AX4: INCOME5_DENSE_SINGLE | AY4: INCOME5_DENSE_SINGLEWCHILDREN | AZ4: INCOME5_DENSE_COUPLE | BA4: INCOME5_DENSE_COUPLEWCHILDREN | BB4: INCOME5_DENSE_OTHER | BC4: INCOME5_DENSE_OTHERWCHILDREN | BD4: INCOME5_SPARSE_SINGLE | BE4: INCOME5_SPARSE_SINGLEWCHILDREN | BF4: INCOME5_SPARSE_COUPLE | BG4: INCOME5_SPARSE_COUPLEWCHILDREN | BH4: INCOME5_SPARSE_OTHER | BI4: INCOME5_SPARSE_OTHERWCHILDREN | BJ4: REPRESENTATIVE_HOUSEHOLD
A5: AUT | B5: 0 | C5: 0 | D5: 0 | E5: 0 | F5: 0 | G5: 0 | H5: 0 | I5: 0 | J5: 0 | K5: 0 | L5: 0 | M5: 0 | N5: 0 | O5: 0 | P5: 0 | Q5: 0 | R5: 0 | S5: 0 | T5: 0 | U5: 0 | V5: 0 | W5: 0 | X5: 0 | Y5: 0 | Z5: 0 | AA5: 0 | AB5: 0 | AC5: 0 | AD5: 0 | AE5: 0 | AF5: 0 | AG5: 0 | AH5: 0 | AI5: 0 | AJ5: 0 | AK5: 0 | AL5: 0 | AM5: 0 | AN5: 0 | AO5: 0 | AP5: 0 | AQ5: 0 | AR5: 0 | AS5: 0 | AT5: 0 | AU5: 0 | AV5: 0 | AW5: 0 | AX5: 0 | AY5: 0 | AZ5: 0 | BA5: 0 | BB5: 0 | BC5: 0 | BD5: 0 | BE5: 0 | BF5: 0 | BG5: 0 | BH5: 0 | BI5: 0 | BJ5: 2976.7711
A6: BEL | B6: 867.77234 | C6: 2533.3894 | D6: 1735.5447 | E6: 3553.9201 | F6: 3191.6176 | G6: 5708.0314 | H6: 867.77234 | I6: 2615.3207 | J6: 1735.5447 | K6: 3648.8132 | L6: 3106.1923 | M6: 4566.0829 | N6: 867.77234 | O6: 2309.489 | P6: 1735.5447 | Q6: 3551.4516 | R6: 3253.624 | S6: 4359.2965 | T6: 867.77234 | U6: 2403.3991 | V6: 1735.5447 | W6: 3473.673 | X6: 3131.0815 | Y6: 4227.05 | Z6: 867.77234 | AA6: 2169.2256 | AB6: 1735.5447 | AC6: 3211.4888 | AD6: 3350.4903 | AE6: 4522.4688 | AF6: 867.77234 | AG6: 2088.816 | AH6: 1735.5447 | AI6: 3324.3086 | AJ6: 3077.7479 | AK6: 4328.2778 | AL6: 867.77234 | AM6: 2155.7979 | AN6: 1735.5447 | AO6: 3254.6817 | AP6: 3014.4578 | AQ6: 4331.7621 | AR6: 867.77234 | AS6: 2044.4679 | AT6: 1735.5447 | AU6: 3216.2755 | AV6: 2974.7238 | AW6: 3951.3731 | AX6: 867.77234 | AY6: 2044.2113 | AZ6: 1735.5447 | BA6: 3033.9323 | BB6: 3083.0657 | BC6: 4257.697 | BD6: 867.77234 | BE6: 1956.0787 | BF6: 1735.5447 | BG6: 3133.5176 | BH6: 2844.4572 | BI6: 3905.4963 | BJ6: 0
A7: BGR | B7: 34.661294 | C7: 88.329878 | D7: 69.322587 | E7: 131.72487 | F7: 115.14675 | G7: 188.1947 | H7: 34.661294 | I7: 92.306754 | J7: 69.322587 | K7: 142.91364 | L7: 122.10031 | M7: 213.38216 | N7: 34.661294 | O7: 87.452024 | P7: 69.322587 | Q7: 125.91724 | R7: 121.25341 | S7: 175.19993 | T7: 34.661294 | U7: 93.069843 | V7: 69.322587 | W7: 126.46677 | X7: 117.72967 | Y7: 186.90134 | Z7: 34.661294 | AA7: 76.692154 | AB7: 69.322587 | AC7: 119.1696 | AD7: 117.30285 | AE7: 166.129 | AF7: 34.661294 | AG7: 77.554503 | AH7: 69.322587 | AI7: 119.01808 | AJ7: 117.15794 | AK7: 185.85484 | AL7: 34.661294 | AM7: 77.67424 | AN7: 69.322587 | AO7: 116.33486 | AP7: 117.20239 | AQ7: 155.02626 | AR7: 34.661294 | AS7: 79.868522 | AT7: 69.322587 | AU7: 118.17771 | AV7: 120.20408 | AW7: 170.08106 | AX7: 34.661294 | AY7: 70.68986 | AZ7: 69.322587 | BA7: 112.5713 | BB7: 116.08281 | BC7: 150.3017 | BD7: 34.661294 | BE7: 77.785632 | BF7: 69.322587 | BG7: 116.23975 | BH7: 114.43535 | BI7: 165.29105 | BJ7: 0
A8: HRV | B8: 140.48239 | C8: 409.83945 | D8: 280.96478 | E8: 597.68188 | F8: 494.82635 | G8: 733.86652 | H8: 140.48239 | I8: 367.59188 | J8: 280.96478 | K8: 609.55927 | L8: 513.98473 | M8: 774.00985 | N8: 140.48239 | O8: 405.76632 | P8: 280.96478 | Q8: 566.70625 | R8: 518.82364 | S8: 678.56145 | T8: 140.48239 | U8: 370.63072 | V8: 280.96478 | W8: 584.80502 | X8: 534.55067 | Y8: 761.17884 | Z8: 140.48239 | AA8: 355.84189 | AB8: 280.96478 | AC8: 491.09109 | AD8: 512.19801 | AE8: 658.55205 | AF8: 140.48239 | AG8: 308.8442 | AH8: 280.96478 | AI8: 546.8694 | AJ8: 532.18758 | AK8: 764.12206 | AL8: 140.48239 | AM8: 360.39864 | AN8: 280.96478 | AO8: 506.59061 | AP8: 493.85957 | AQ8: 668.71199 | AR8: 140.48239 | AS8: 318.05928 | AT8: 280.96478 | AU8: 523.31082 | AV8: 504.70049 | AW8: 734.44552 | AX8: 140.48239 | AY8: 327.992 | AZ8: 280.96478 | BA8: 473.73793 | BB8: 480.82504 | BC8: 664.99639 | BD8: 140.48239 | BE8: 309.76462 | BF8: 280.96478 | BG8: 487.95535 | BH8: 506.33335 | BI8: 695.39258 | BJ8: 0
A9: CYP | B9: 609.10582 | C9: 1583.4166 | D9: 1218.2116 | E9: 2466.2698 | F9: 2342.1059 | G9: 2900.4072 | H9: 609.10582 | I9: 1776.7643 | J9: 1218.2116 | K9: 2392.1989 | L9: 2406.6664 | M9: 3389.2506 | N9: 609.10582 | O9: 1567.68 | P9: 1218.2116 | Q9: 2093.205 | R9: 2274.751 | S9: 2814.9831 | T9: 609.10582 | U9: 1791.4526 | V9: 1218.2116 | W9: 2580.1947 | X9: 2308.72 | Y9: 3392.2995 | Z9: 609.10582 | AA9: 1374.7968 | AB9: 1218.2116 | AC9: 2293.9049 | AD9: 2337.4141 | AE9: 3071.9328 | AF9: 609.10582 | AG9: 1492.806 | AH9: 1218.2116 | AI9: 2307.9537 | AJ9: 2510.2869 | AK9: 3109.3295 | AL9: 609.10582 | AM9: 1392.4018 | AN9: 1218.2116 | AO9: 2262.7691 | AP9: 2159.6035 | AQ9: 3013.003 | AR9: 609.10582 | AS9: 1537.3473 | AT9: 1218.2116 | AU9: 2174.5297 | AV9: 2278.698 | AW9: 3246.8755 | AX9: 609.10582 | AY9: 1267.1986 | AZ9: 1218.2116 | BA9: 2173.9395 | BB9: 2104.4185 | BC9: 2822.6377 | BD9: 609.10582 | BE9: 1497.2548 | BF9: 1218.2116 | BG9: 2197.5335 | BH9: 2142.7004 | BI9: 2994.5702 | BJ9: 0
A10: CZE | B10: 651.91163 | C10: 1679.931 | D10: 1303.8233 | E10: 2495.8377 | F10: 2304.477 | G10: 2900.8951 | H10: 651.91163 | I10: 1719.5627 | J10: 1303.8233 | K10: 2656.149 | L10: 2339.7019 | M10: 3270.9601 | N10: 651.91163 | O10: 1663.2353 | P10: 1303.8233 | Q10: 2448.7712 | R10: 2110.6979 | S10: 2815.4566 | T10: 651.91163 | U10: 1733.7782 | V10: 1303.8233 | W10: 2538.5167 | X10: 2303.6988 | Y10: 2944.4841 | Z10: 651.91163 | AA10: 1458.5951 | AB10: 1303.8233 | AC10: 2288.5237 | AD10: 2079.2404 | AE10: 3072.4495 | AF10: 651.91163 | AG10: 1444.7462 | AH10: 1303.8233 | AI10: 2381.2389 | AJ10: 2274.0325 | AK10: 2960.1376 | AL10: 651.91163 | AM10: 1477.2732 | AN10: 1303.8233 | AO10: 2339.8497 | AP10: 2117.3487 | AQ10: 3013.5099 | AR10: 651.91163 | AS10: 1487.8536 | AT10: 1303.8233 | AU10: 2231.97 | AV10: 2238.973 | AW10: 2852.2558 | AX10: 651.91163 | AY10: 1344.4385 | AZ10: 1303.8233 | BA10: 2198.9899 | BB10: 2163.1394 | BC10: 2823.1126 | BD10: 651.91163 | BE10: 1449.0519 | BF10: 1303.8233 | BG10: 2343.181 | BH10: 2206.0103 | BI10: 2954.1355 | BJ10: 0
A11: DNK | B11: 1185.6173 | C11: 3168.4063 | D11: 2371.2346 | E11: 4858.983 | F11: 4292.3978 | G11: 6828.5909 | H11: 1185.6173 | I11: 3390.3388 | J11: 2371.2346 | K11: 4833.5853 | L11: 4157.4784 | M11: 5761.6155 | N11: 1185.6173 | O11: 2888.3832 | P11: 2371.2346 | Q11: 4607.4465 | R11: 3968.6665 | S11: 5438.981 | T11: 1185.6173 | U11: 3131.5263 | V11: 2371.2346 | W11: 4838.8275 | X11: 4194.1764 | Y11: 5537.8846 | Z11: 1185.6173 | AA11: 2712.9615 | AB11: 2371.2346 | AC11: 4091.3484 | AD11: 4111.8639 | AE11: 5525.9729 | AF11: 1185.6173 | AG11: 2791.6311 | AH11: 2371.2346 | AI11: 4573.0313 | AJ11: 3798.7271 | AK11: 5611.0548 | AL11: 1185.6173 | AM11: 2696.1681 | AN11: 2371.2346 | AO11: 4207.6821 | AP11: 3643.0865 | AQ11: 5366.8385 | AR11: 1185.6173 | AS11: 2741.2607 | AT11: 2371.2346 | AU11: 4465.318 | AV11: 3838.7584 | AW11: 5150.2652 | AX11: 1185.6173 | AY11: 2556.6113 | AZ11: 2371.2346 | BA11: 4107.8548 | BB11: 3754.4507 | BC11: 5051.3245 | BD11: 1185.6173 | BE11: 2479.4547 | BF11: 2371.2346 | BG11: 4311.0365 | BH11: 3815.1131 | BI11: 5165.7324 | BJ11: 0
A12: EST | B12: 277.61338 | C12: 706.28288 | D12: 555.22675 | E12: 1056.6416 | F12: 903.22382 | G12: 1394.8152 | H12: 277.61338 | I12: 729.16733 | J12: 555.22675 | K12: 1105.9034 | L12: 933.09873 | M12: 1533.0351 | N12: 277.61338 | O12: 699.26358 | P12: 555.22675 | Q12: 974.71251 | R12: 927.51556 | S12: 1335.1018 | T12: 277.61338 | U12: 735.19527 | V12: 555.22675 | W12: 1081.4028 | X12: 961.86862 | Y12: 1492.063 | Z12: 277.61338 | AA12: 613.22801 | AB12: 555.22675 | AC12: 989.96957 | AD12: 935.29008 | AE12: 1263.8103 | AF12: 277.61338 | AG12: 612.6335 | AH12: 555.22675 | AI12: 1000.0623 | AJ12: 962.52266 | AK12: 1436.8053 | AL12: 277.61338 | AM12: 621.08074 | AN12: 555.22675 | AO12: 989.35821 | AP12: 897.6948 | AQ12: 1242.1764 | AR12: 277.61338 | AS12: 630.91285 | AT12: 555.22675 | AU12: 1027.7951 | AV12: 939.04137 | AW12: 1323.0361 | AX12: 277.61338 | AY12: 565.23386 | AZ12: 555.22675 | BA12: 950.4229 | BB12: 959.57527 | BC12: 1272.4534 | BD12: 277.61338 | BE12: 614.45928 | BF12: 555.22675 | BG12: 990.54805 | BH12: 936.97059 | BI12: 1238.2109 | BJ12: 0
A13: FIN | B13: 845.74806 | C13: 2343.3693 | D13: 1691.4961 | E13: 3528.5134 | F13: 3044.6217 | G13: 4912.0508 | H13: 845.74806 | I13: 2658.5558 | J13: 1691.4961 | K13: 3878.9616 | L13: 3019.9392 | M13: 5909.3131 | N13: 845.74806 | O13: 2136.2629 | P13: 1691.4961 | Q13: 3254.0295 | R13: 2768.1617 | S13: 3751.396 | T13: 845.74806 | U13: 2443.1308 | V13: 1691.4961 | W13: 3354.5819 | X13: 2901.0236 | Y13: 4516.2467 | Z13: 845.74806 | AA13: 2006.5201 | AB13: 1691.4961 | AC13: 3084.1737 | AD13: 2759.1385 | AE13: 3891.814 | AF13: 845.74806 | AG13: 2123.3472 | AH13: 1691.4961 | AI13: 3343.7028 | AJ13: 2888.7306 | AK13: 4078.8107 | AL13: 845.74806 | AM13: 1994.0996 | AN13: 1691.4961 | AO13: 3004.8084 | AP13: 2646.2303 | AQ13: 3727.7012 | AR13: 845.74806 | AS13: 2078.266 | AT13: 1691.4961 | AU13: 2977.4339 | AV13: 2737.8243 | AW13: 3886.1808 | AX13: 845.74806 | AY13: 1890.8827 | AZ13: 1691.4961 | BA13: 2959.2465 | BB13: 2805.8344 | BC13: 3663.9644 | BD13: 845.74806 | BE13: 1988.4156 | BF13: 1691.4961 | BG13: 2979.237 | BH13: 2697.4731 | BI13: 3672.8287 | BJ13: 0
A14: FRA | B14: 1129.0803 | C14: 3797.9615 | D14: 2258.1607 | E14: 4786.6326 | F14: 4306.6351 | G14: 6608.6469 | H14: 1129.0803 | I14: 3209.5588 | J14: 2258.1607 | K14: 4769.3618 | L14: 3940.2902 | M14: 6026.448 | N14: 1129.0803 | O14: 3272.9939 | P14: 2258.1607 | Q14: 4391.4264 | R14: 3981.83 | S14: 5263.7953 | T14: 1129.0803 | U14: 2964.5467 | V14: 2258.1607 | W14: 4603.994 | X14: 4014.8563 | Y14: 5619.3035 | Z14: 1129.0803 | AA14: 2739.7051 | AB14: 2258.1607 | AC14: 4252.9961 | AD14: 4125.5024 | AE14: 5347.9853 | AF14: 1129.0803 | AG14: 2642.7755 | AH14: 2258.1607 | AI14: 4208.5396 | AJ14: 3958.8227 | AK14: 5325.8796 | AL14: 1129.0803 | AM14: 2640.4219 | AN14: 2258.1607 | AO14: 4169.3002 | AP14: 3655.1702 | AQ14: 5193.9765 | AR14: 1129.0803 | AS14: 2595.0909 | AT14: 2258.1607 | AU14: 3967.7945 | AV14: 3821.5193 | AW14: 4990.1839 | AX14: 1129.0803 | AY14: 2475.7056 | AZ14: 2258.1607 | BA14: 4054.8554 | BB14: 3766.9037 | BC14: 4888.625 | BD14: 1129.0803 | BE14: 2347.245 | BF14: 2258.1607 | BG14: 4003.0859 | BH14: 3612.1758 | BI14: 4978.7631 | BJ14: 0
A15: DEU | B15: 1303.5927 | C15: 3354.6171 | D15: 2607.1855 | E15: 5200.3403 | F15: 4321.9757 | G15: 6790.0942 | H15: 1303.5927 | I15: 3473.1272 | J15: 2607.1855 | K15: 5206.8733 | L15: 4450.3144 | M15: 6981.6368 | N15: 1303.5927 | O15: 3058.1368 | P15: 2607.1855 | Q15: 4891.1922 | R15: 4573.3836 | S15: 6432.6187 | T15: 1303.5927 | U15: 3290.2333 | V15: 2607.1855 | W15: 5072.6327 | X15: 4514.3735 | Y15: 6730.4335 | Z15: 1303.5927 | AA15: 2872.4053 | AB15: 2607.1855 | AC15: 4694.1614 | AD15: 4278.8585 | AE15: 5675.0218 | AF15: 1303.5927 | AG15: 3115.7838 | AH15: 2607.1855 | AI15: 4903.6094 | AJ15: 4380.9783 | AK15: 5887.0789 | AL15: 1303.5927 | AM15: 2854.625 | AN15: 2607.1855 | AO15: 4587.7806 | AP15: 4306.9509 | AQ15: 5531.301 | AR15: 1303.5927 | AS15: 2906.6233 | AT15: 2607.1855 | AU15: 4723.6987 | AV15: 4315.7004 | AW15: 5719.3783 | AX15: 1303.5927 | AY15: 2706.8663 | AZ15: 2607.1855 | BA15: 4385.7191 | BB15: 4138.3159 | BC15: 5515.459 | BD15: 1303.5927 | BE15: 2790.2499 | BF15: 2607.1855 | BG15: 4481.8333 | BH15: 4243.0767 | BI15: 5999.9371 | BJ15: 0
A16: GRC | B16: 405.46037 | C16: 1080.4792 | D16: 810.92074 | E16: 1588.6245 | F16: 1483.8604 | G16: 1969.0662 | H16: 405.46037 | I16: 1101.0359 | J16: 810.92074 | K16: 1612.3905 | L16: 1500.136 | M16: 2165.9143 | N16: 405.46037 | O16: 1069.741 | P16: 810.92074 | Q16: 1500.9156 | R16: 1457.1961 | S16: 1993.0008 | T16: 405.46037 | U16: 1110.1381 | V16: 810.92074 | W16: 1623.7228 | X16: 1443.5835 | Y16: 2219.2457 | Z16: 405.46037 | AA16: 938.12284 | AB16: 810.92074 | AC16: 1468.7364 | AD16: 1408.5362 | AE16: 1873.9123 | AF16: 405.46037 | AG16: 925.07093 | AH16: 810.92074 | AI16: 1510.9719 | AJ16: 1433.4253 | AK16: 2069.6654 | AL16: 405.46037 | AM16: 950.13603 | AN16: 810.92074 | AO16: 1444.0666 | AP16: 1411.0021 | AQ16: 1847.1717 | AR16: 405.46037 | AS16: 952.67257 | AT16: 810.92074 | AU16: 1476.3295 | AV16: 1438.7971 | AW16: 2037.1512 | AX16: 405.46037 | AY16: 864.70087 | AZ16: 810.92074 | BA16: 1374.2647 | BB16: 1354.0994 | BC16: 1716.1539 | BD16: 405.46037 | BE16: 927.82783 | BF16: 810.92074 | BG16: 1388.6889 | BH16: 1383.5086 | BI16: 2183.69 | BJ16: 0
... A39: LROW | B39: 0 | C39: 0 | D39: 0 | E39: 0 | F39: 0 | G39: 0 | H39: 0 | I39: 0 | J39: 0 | K39: 0 | L39: 0 | M39: 0 | N39: 0 | O39: 0 | P39: 0 | Q39: 0 | R39: 0 | S39: 0 | T39: 0 | U39: 0 | V39: 0 | W39: 0 | X39: 0 | Y39: 0 | Z39: 0 | AA39: 0 | AB39: 0 | AC39: 0 | AD39: 0 | AE39: 0 | AF39: 0 | AG39: 0 | AH39: 0 | AI39: 0 | AJ39: 0 | AK39: 0 | AL39: 0 | AM39: 0 | AN39: 0 | AO39: 0 | AP39: 0 | AQ39: 0 | AR39: 0 | AS39: 0 | AT39: 0 | AU39: 0 | AV39: 0 | AW39: 0 | AX39: 0 | AY39: 0 | AZ39: 0 | BA39: 0 | BB39: 0 | BC39: 0 | BD39: 0 | BE39: 0 | BF39: 0 | BG39: 0 | BH39: 0 | BI39: 0 | BJ39: 121.59717

Sheet HH_Cons_COICOP
C4: HH_HOUSING | D4: HH_APPLIANCES | E4: HH_VEHICLES | F4: HH_ELECTRICITY | G4: HH_GAS | H4: HH_LIQUID_FUELS | I4: HH_SOLID_FUELS | J4: HH_HEAT | K4: HH_FUEL_TRANSPORT | L4: HH_RAILWAY | M4: HH_ROAD | N4: HH_AIR | O4: HH_MARITIME | P4: HH_FOOD | Q4: HH_TEXTILES | R4: HH_FURNITURE_EQUIPMENT | S4: HH_SERVICES | T4: HH_LEISURE | U4: HH_OTHER
A5: AUT | B5: INCOME1_DENSE_SINGLE | C5: 0 | D5: 0 | E5: 0 | F5: 1.0000001e-07 | G5: 1.0000001e-07 | H5: 1.0000001e-07 | I5: 1.0000001e-07 | J5: 1.0000001e-07 | K5: 1.0000001e-07 | L5: 1.0000001e-07 | M5: 1.0000001e-07 | N5: 1e-07 | O5: 1.0000001e-07 | P5: 0 | Q5: 0 | R5: 0 | S5: 0 | T5: 0 | U5: 0
A6: AUT | B6: INCOME1_DENSE_SINGLEWCHILDREN | C6: 0 | D6: 0 | E6: 0 | F6: 1.0000001e-07 | G6: 1.0000001e-07 | H6: 1.0000001e-07 | I6: 1.0000001e-07 | J6: 1.0000001e-07 | K6: 1.0000001e-07 | L6: 1.0000001e-07 | M6: 1.0000001e-07 | N6: 1e-07 | O6: 1.0000001e-07 | P6: 0 | Q6: 0 | R6: 0 | S6: 0 | T6: 0 | U6: 0
A7: AUT | B7: INCOME1_DENSE_COUPLE | C7: 0 | D7: 0 | E7: 0 | F7: 1.0000001e-07 | G7: 1.0000001e-07 | H7: 1.0000001e-07 | I7: 1.0000001e-07 | J7: 1.0000001e-07 | K7: 1.0000001e-07 | L7: 1.0000001e-07 | M7: 1.0000001e-07 | N7: 1e-07 | O7: 1.0000001e-07 | P7: 0 | Q7: 0 | R7: 0 | S7: 0 | T7: 0 | U7: 0
A8: AUT | B8: INCOME1_DENSE_COUPLEWCHILDREN | C8: 0 | D8: 0 | E8: 0 | F8: 1.0000001e-07 | G8: 1.0000001e-07 | H8: 1.0000001e-07 | I8: 1.0000001e-07 | J8: 1.0000001e-07 | K8: 1.0000001e-07 | L8: 1.0000001e-07 | M8: 1.0000001e-07 | N8: 1e-07 | O8: 1.0000001e-07 | P8: 0 | Q8: 0 | R8: 0 | S8: 0 | T8: 0 | U8: 0
A9: AUT | B9: INCOME1_DENSE_OTHER | C9: 0 | D9: 0 | E9: 0 | F9: 1.0000001e-07 | G9: 1.0000001e-07 | H9: 1.0000001e-07 | I9: 1.0000001e-07 | J9: 1.0000001e-07 | K9: 1.0000001e-07 | L9: 1.0000001e-07 | M9: 1.0000001e-07 | N9: 1e-07 | O9: 1.0000001e-07 | P9: 0 | Q9: 0 | R9: 0 | S9: 0 | T9: 0 | U9: 0
A10: AUT | B10: INCOME1_DENSE_OTHERWCHILDREN | C10: 0 | D10: 0 | E10: 0 | F10: 1.0000001e-07 | G10: 1.0000001e-07 | H10: 1.0000001e-07 | I10: 1.0000001e-07 | J10: 1.0000001e-07 | K10: 1.0000001e-07 | L10: 1.0000001e-07 | M10: 1.0000001e-07 | N10: 1e-07 | O10: 1.0000001e-07 | P10: 0 | Q10: 0 | R10: 0 | S10: 0 | T10: 0 | U10: 0
A11: AUT | B11: INCOME1_SPARSE_SINGLE | C11: 0 | D11: 0 | E11: 0 | F11: 1.0000001e-07 | G11: 1.0000001e-07 | H11: 1.0000001e-07 | I11: 1.0000001e-07 | J11: 1.0000001e-07 | K11: 1.0000001e-07 | L11: 1.0000001e-07 | M11: 1.0000001e-07 | N11: 1e-07 | O11: 1.0000001e-07 | P11: 0 | Q11: 0 | R11: 0 | S11: 0 | T11: 0 | U11: 0
A12: AUT | B12: INCOME1_SPARSE_SINGLEWCHILDREN | C12: 0 | D12: 0 | E12: 0 | F12: 1.0000001e-07 | G12: 1.0000001e-07 | H12: 1.0000001e-07 | I12: 1.0000001e-07 | J12: 1.0000001e-07 | K12: 1.0000001e-07 | L12: 1.0000001e-07 | M12: 1.0000001e-07 | N12: 1e-07 | O12: 1.0000001e-07 | P12: 0 | Q12: 0 | R12: 0 | S12: 0 | T12: 0 | U12: 0
A13: AUT | B13: INCOME1_SPARSE_COUPLE | C13: 0 | D13: 0 | E13: 0 | F13: 1.0000001e-07 | G13: 1.0000001e-07 | H13: 1.0000001e-07 | I13: 1.0000001e-07 | J13: 1.0000001e-07 | K13: 1.0000001e-07 | L13: 1.0000001e-07 | M13: 1.0000001e-07 | N13: 1e-07 | O13: 1.0000001e-07 | P13: 0 | Q13: 0 | R13: 0 | S13: 0 | T13: 0 | U13: 0
A14: AUT | B14: INCOME1_SPARSE_COUPLEWCHILDREN | C14: 0 | D14: 0 | E14: 0 | F14: 1.0000001e-07 | G14: 1.0000001e-07 | H14: 1.0000001e-07 | I14: 1.0000001e-07 | J14: 1.0000001e-07 | K14: 1.0000001e-07 | L14: 1.0000001e-07 | M14: 1.0000001e-07 | N14: 1e-07 | O14: 1.0000001e-07 | P14: 0 | Q14: 0 | R14: 0 | S14: 0 | T14: 0 | U14: 0
A15: AUT | B15: INCOME1_SPARSE_OTHER | C15: 0 | D15: 0 | E15: 0 | F15: 1.0000001e-07 | G15: 1.0000001e-07 | H15: 1.0000001e-07 | I15: 1.0000001e-07 | J15: 1.0000001e-07 | K15: 1.0000001e-07 | L15: 1.0000001e-07 | M15: 1.0000001e-07 | N15: 1e-07 | O15: 1.0000001e-07 | P15: 0 | Q15: 0 | R15: 0 | S15: 0 | T15: 0 | U15: 0
A16: AUT | B16: INCOME1_SPARSE_OTHERWCHILDREN | C16: 0 | D16: 0 | E16: 0 | F16: 1.0000001e-07 | G16: 1.0000001e-07 | H16: 1.0000001e-07 | I16: 1.0000001e-07 | J16: 1.0000001e-07 | K16: 1.0000001e-07 | L16: 1.0000001e-07 | M16: 1.0000001e-07 | N16: 1e-07 | O16: 1.0000001e-07 | P16: 0 | Q16: 0 | R16: 0 | S16: 0 | T16: 0 | U16: 0
... A2139: LROW | B2139: REPRESENTATIVE_HOUSEHOLD | C2139: 907.53031 | D2139: 61.357683 | E2139: 303.1833 | F2139: 185.85274 | G2139: 103.55688 | H2139: 49.170264 | I2139: 41.914549 | J2139: 4.159395 | K2139: 442.94582 | L2139: 56.01339 | M2139: 96.213087 | N2139: 160.85053 | O2139: 10.136705 | P2139: 2093.2136 | Q2139: 349.34167 | R2139: 480.80331 | S2139: 1038.2577 | T2139: 1218.9142 | U2139: 1026.3815

Sheet Consumption_COICOP
B4: HH_HOUSING | C4: HH_APPLIANCES | D4: HH_VEHICLES | E4: HH_ELECTRICITY | F4: HH_GAS | G4: HH_LIQUID_FUELS | H4: HH_SOLID_FUELS | I4: HH_HEAT | J4: HH_FUEL_TRANSPORT | K4: HH_RAILWAY | L4: HH_ROAD | M4: HH_AIR | N4: HH_MARITIME | O4: HH_FOOD | P4: HH_TEXTILES | Q4: HH_FURNITURE_EQUIPMENT | R4: HH_SERVICES | S4: HH_LEISURE | T4: HH_OTHER
A5: AUT | B5: 35473.998 | C5: 1783.024 | D5: 7776.6381 | E5: 3563.8207 | F5: 2001.3287 | G5: 749.98014 | H5: 575.23099 | I5: 209.57491 | J5: 6877.5025 | K5: 2013.0211 | L5: 2551.528 | M5: 1340.2415 | N5: 251.54737 | O5: 23759.387 | P5: 6996.3312 | Q5: 11959.663 | R5: 22945.224 | S5: 29338.472 | T5: 23911.025
A6: BEL | B6: 37919.326 | C6: 1731.2752 | D6: 8769.0259 | E6: 4341.4023 | F6: 2972.7404 | G6: 1042.8561 | H6: 439.70052 | I6: 89.425417 | J6: 9642.0233 | K6: 899.75355 | L6: 879.80788 | M6: 1767.5735 | N6: 139.54335 | O6: 29164.835 | P6: 8127.7703 | Q6: 10279.047 | R6: 35401.399 | S6: 22065.035 | T6: 36970.53
A7: BGR | B7: 4360.3325 | C7: 434.12588 | D7: 1444.8487 | E7: 1691.7446 | F7: 200.53981 | G7: 222.47005 | H7: 204.40115 | I7: 195.06944 | J7: 1917.2272 | K7: 381.18342 | L7: 387.54903 | M7: 321.87706 | N7: 35.664389 | O7: 6610.6913 | P7: 1931.1211 | Q7: 1673.1675 | R7: 2540.8367 | S7: 3331.5847 | T7: 2648.6046
A8: HRV | B8: 4975.9729 | C8: 422.76288 | D8: 925.74971 | E8: 414.99906 | F8: 213.84646 | G8: 72.131409 | H8: 76.347291 | I8: 44.917472 | J8: 630.81665 | K8: 181.37174 | L8: 202.84341 | M8: 53.645549 | N8: 23.895893 | O8: 5439.4048 | P8: 1510.9737 | Q8: 1759.0451 | R8: 3237.7419 | S8: 3986.941 | T8: 3559.3241
A9: CYP | B9: 1978.3647 | C9: 56.106569 | D9: 364.35915 | E9: 476.97143 | F9: 29.732133 | G9: 35.199794 | H9: 25.085566 | I9: 7.5060644 | J9: 285.05046 | K9: 31.899404 | L9: 18.128815 | M9: 496.06551 | N9: 663.39973 | O9: 2010.2104 | P9: 590.01072 | Q9: 566.3067 | R9: 1388.9222 | S9: 1827.1402 | T9: 2023.74
A10: CZE | B10: 13359.998 | C10: 743.24118 | D10: 4294.0355 | E10: 3601.3796 | F10: 2589.6828 | G10: 261.07943 | H10: 438.06091 | I10: 342.86638 | J10: 2175.6479 | K10: 782.61908 | L10: 1225.9795 | M10: 469.78439 | N10: 65.412438 | O10: 16586.865 | P10: 4800.8697 | Q10: 4388.9891 | R10: 6650.0012 | S10: 11094.912 | T10: 9753.4675
A11: DNK | B11: 28669.576 | C11: 1057.4704 | D11: 4427.5862 | E11: 7533.6633 | F11: 3066.2118 | G11: 325.94069 | H11: 564.35207 | I11: 126.92765 | J11: 2709.0684 | K11: 735.71201 | L11: 1293.8816 | M11: 368.98378 | N11: 490.19636 | O11: 12842.935 | P11: 3498.6563 | Q11: 5941.4542 | R11: 23472.866 | S11: 13288.323 | T11: 20503.087
A12: EST | B12: 1749.6562 | C12: 77.434628 | D12: 427.83602 | E12: 309.08851 | F12: 75.24534 | G12: 46.574378 | H12: 43.473028 | I12: 116.61438 | J12: 418.00529 | K12: 98.774609 | L12: 145.29154 | M12: 95.33021 | N12: 101.99717 | O12: 2057.0738 | P12: 595.99104 | Q12: 595.95348 | R12: 1098.4593 | S12: 1229.3294 | T12: 1191.2662
A13: FIN | B13: 28754.652 | C13: 1028.33 | D13: 4491.0049 | E13: 2458.0249 | F13: 331.09124 | G13: 411.42788 | H13: 742.66437 | I13: 100.06312 | J13: 3760.0698 | K13: 812.23373 | L13: 840.45477 | M13: 848.37401 | N13: 522.49228 | O13: 15624.456 | P13: 4614.9515 | Q13: 5773.8886 | R13: 17727.674 | S13: 13346.784 | T13: 16604.774
A14: FRA | B14: 281830.79 | C14: 9389.8045 | D14: 66866.177 | E14: 25555.196 | F14: 17628.996 | G14: 4270.8567 | H14: 3509.027 | I14: 451.78842 | J14: 38740.414 | K14: 7773.2706 | L14: 8961.7147 | M14: 17720.903 | N14: 1985.164 | O14: 159674.84 | P14: 44337.093 | Q14: 56008.084 | R14: 165410.26 | S14: 142057.75 | T14: 174863.55
A15: DEU | B15: 320146.87 | C15: 18015.224 | D15: 99305.625 | E15: 36958.474 | F15: 37493.93 | G15: 7899.5364 | H15: 7571.5138 | I15: 1500.6051 | J15: 68544.76 | K15: 14684.943 | L15: 21001.601 | M15: 33711.361 | N15: 3940.5425 | O15: 160116.91 | P15: 50487.752 | Q15: 101191.5 | R15: 200429.25 | S15: 214277.61 | T15: 271838.16
A16: GRC | B16: 22726.011 | C16: 893.08753 | D16: 5053.1786 | E16: 2758.1032 | F16: 768.23483 | G16: 599.06719 | H16: 237.01475 | I16: 67.614556 | J16: 5447.9853 | K16: 2023.1159 | L16: 1725.1896 | M16: 1100.7743 | N16: 580.34583 | O16: 23240.454 | P16: 6381.9941 | Q16: 5457.1995 | R16: 13138.511 | S16: 23182.771 | T16: 12796.15
... A39: LROW | B39: 575156.41 | C39: 38886.045 | D39: 192145.45 | E39: 117786.03 | F39: 65630.209 | G39: 31162.146 | H39: 26563.765 | I39: 2636.0582 | J39: 280721.34 | K39: 35499.046 | L39: 60976.006 | M39: 101940.63 | N39: 6424.2383 | O39: 1326595.1 | P39: 221398.78 | Q39: 304713.9 | R39: 658006.19 | S39: 772499.09 | T39: 650479.56

Sheet HH_Disposable_income
B4: INCOME1_DENSE_SINGLE | C4: INCOME1_DENSE_SINGLEWCHILDREN | D4: INCOME1_DENSE_COUPLE | E4: INCOME1_DENSE_COUPLEWCHILDREN | F4: INCOME1_DENSE_OTHER | G4: INCOME1_DENSE_OTHERWCHILDREN | H4: INCOME1_SPARSE_SINGLE | I4: INCOME1_SPARSE_SINGLEWCHILDREN | J4: INCOME1_SPARSE_COUPLE | K4: INCOME1_SPARSE_COUPLEWCHILDREN | L4: INCOME1_SPARSE_OTHER | M4: INCOME1_SPARSE_OTHERWCHILDREN | N4: INCOME2_DENSE_SINGLE | O4: INCOME2_DENSE_SINGLEWCHILDREN | P4: INCOME2_DENSE_COUPLE | Q4: INCOME2_DENSE_COUPLEWCHILDREN | R4: INCOME2_DENSE_OTHER | S4: INCOME2_DENSE_OTHERWCHILDREN | T4: INCOME2_SPARSE_SINGLE | U4: INCOME2_SPARSE_SINGLEWCHILDREN | V4: INCOME2_SPARSE_COUPLE | W4: INCOME2_SPARSE_COUPLEWCHILDREN | X4: INCOME2_SPARSE_OTHER | Y4: INCOME2_SPARSE_OTHERWCHILDREN | Z4: INCOME3_DENSE_SINGLE | AA4: INCOME3_DENSE_SINGLEWCHILDREN | AB4: INCOME3_DENSE_COUPLE | AC4: INCOME3_DENSE_COUPLEWCHILDREN | AD4: INCOME3_DENSE_OTHER | AE4: INCOME3_DENSE_OTHERWCHILDREN | AF4: INCOME3_SPARSE_SINGLE | AG4: INCOME3_SPARSE_SINGLEWCHILDREN | AH4: INCOME3_SPARSE_COUPLE | AI4: INCOME3_SPARSE_COUPLEWCHILDREN | AJ4: INCOME3_SPARSE_OTHER | AK4: INCOME3_SPARSE_OTHERWCHILDREN | AL4: INCOME4_DENSE_SINGLE | AM4: INCOME4_DENSE_SINGLEWCHILDREN | AN4: INCOME4_DENSE_COUPLE | AO4: INCOME4_DENSE_COUPLEWCHILDREN | AP4: INCOME4_DENSE_OTHER | AQ4: INCOME4_DENSE_OTHERWCHILDREN | AR4: INCOME4_SPARSE_SINGLE | AS4: INCOME4_SPARSE_SINGLEWCHILDREN | AT4: INCOME4_SPARSE_COUPLE | AU4: INCOME4_SPARSE_COUPLEWCHILDREN | AV4: INCOME4_SPARSE_OTHER | AW4: INCOME4_SPARSE_OTHERWCHILDREN | AX4: INCOME5_DENSE_SINGLE | AY4: INCOME5_DENSE_SINGLEWCHILDREN | AZ4: INCOME5_DENSE_COUPLE | BA4: INCOME5_DENSE_COUPLEWCHILDREN | BB4: INCOME5_DENSE_OTHER | BC4: INCOME5_DENSE_OTHERWCHILDREN | BD4: INCOME5_SPARSE_SINGLE | BE4: INCOME5_SPARSE_SINGLEWCHILDREN | BF4: INCOME5_SPARSE_COUPLE | BG4: INCOME5_SPARSE_COUPLEWCHILDREN | BH4: INCOME5_SPARSE_OTHER | BI4: INCOME5_SPARSE_OTHERWCHILDREN | BJ4: REPRESENTATIVE_HOUSEHOLD
A5: AUT | B5: 0 | C5: 0 | D5: 0 | E5: 0 | F5: 0 | G5: 0 | H5: 0 | I5: 0 | J5: 0 | K5: 0 | L5: 0 | M5: 0 | N5: 0 | O5: 0 | P5: 0 | Q5: 0 | R5: 0 | S5: 0 | T5: 0 | U5: 0 | V5: 0 | W5: 0 | X5: 0 | Y5: 0 | Z5: 0 | AA5: 0 | AB5: 0 | AC5: 0 | AD5: 0 | AE5: 0 | AF5: 0 | AG5: 0 | AH5: 0 | AI5: 0 | AJ5: 0 | AK5: 0 | AL5: 0 | AM5: 0 | AN5: 0 | AO5: 0 | AP5: 0 | AQ5: 0 | AR5: 0 | AS5: 0 | AT5: 0 | AU5: 0 | AV5: 0 | AW5: 0 | AX5: 0 | AY5: 0 | AZ5: 0 | BA5: 0 | BB5: 0 | BC5: 0 | BD5: 0 | BE5: 0 | BF5: 0 | BG5: 0 | BH5: 0 | BI5: 0 | BJ5: 62561.847
A6: BEL | B6: 14571.618 | C6: 19412.391 | D6: 24597.308 | E6: 31848.534 | F6: 30427.452 | G6: 49619.401 | H6: 18700.931 | I6: 26380.363 | J6: 33554.667 | K6: 44202.723 | L6: 49957.301 | M6: 48472.14 | N6: 23203.054 | O6: 34612.421 | P6: 41132.414 | Q6: 51496.55 | R6: 54945.243 | S6: 53192.097 | T6: 26537.005 | U6: 30812.034 | V6: 48864.408 | W6: 71647.716 | X6: 73905.445 | Y6: 71363.097 | Z6: 28394.476 | AA6: 39347.444 | AB6: 58238.1 | AC6: 67407.085 | AD6: 84115.55 | AE6: 72420.425 | AF6: 31763.868 | AG6: 34087.83 | AH6: 60347.005 | AI6: 85554.808 | AJ6: 92184.849 | AK6: 86926.74 | AL6: 40085.621 | AM6: 40627.979 | AN6: 72048.354 | AO6: 91451.936 | AP6: 94286.391 | AQ6: 79548.847 | AR6: 38980.497 | AS6: 42506.079 | AT6: 73638.87 | AU6: 96736.679 | AV6: 108336.85 | AW6: 102127.1 | AX6: 68233.197 | AY6: 68360.672 | AZ6: 107401.98 | BA6: 121160.2 | BB6: 135361.84 | BC6: 135674.43 | BD6: 55525.931 | BE6: 58035.839 | BF6: 98673.891 | BG6: 113888.06 | BH6: 141598.07 | BI6: 132926.99 | BJ6: 0
A7: BGR | B7: 2945.3316 | C7: 1218.993 | D7: 5182.7644 | E7: 7394.0763 | F7: 8783.2331 | G7: 7155.4496 | H7: 2055.7232 | I7: 1287.1249 | J7: 3745.1249 | K7: 3668.7422 | L7: 5519.5336 | M7: 5123.6503 | N7: 4201.2575 | O7: 2819.9003 | P7: 7805.9822 | Q7: 10864.579 | R7: 14569.565 | S7: 12330.669 | T7: 2940.7723 | U7: 2822.2762 | V7: 5763.916 | W7: 6784.6108 | X7: 9245.9888 | Y7: 8291.1788 | Z7: 5459.1359 | AA7: 4359.6756 | AB7: 10146.48 | AC7: 13622.238 | AD7: 21229.342 | AE7: 16240.713 | AF7: 3703.8926 | AG7: 2946.6425 | AH7: 7465.14 | AI7: 9872.5747 | AJ7: 12276.846 | AK7: 12576.965 | AL7: 7739.2822 | AM7: 8364.7406 | AN7: 13542.478 | AO7: 20647.435 | AP7: 23136.18 | AQ7: 20728.148 | AR7: 4746.7197 | AS7: 4451.4079 | AT7: 9691.0227 | AU7: 13065.131 | AV7: 16264.259 | AW7: 14542.234 | AX7: 13840.18 | AY7: 14464.987 | AZ7: 23864.11 | BA7: 31886.901 | BB7: 40976.539 | BC7: 32372.503 | BD7: 7946.4158 | BE7: 12169.958 | BF7: 16230.248 | BG7: 20416.613 | BH7: 25185.193 | BI7: 23902.65 | BJ7: 0
A8: HRV | B8: 4378.5237 | C8: 4741.6341 | D8: 8900.3041 | E8: 14428.284 | F8: 15192.059 | G8: 15548.787 | H8: 3360.0049 | I8: 3199.1296 | J8: 6403.1351 | K8: 11687.029 | L8: 11877.625 | M8: 13476.121 | N8: 7575.2897 | O8: 9050.825 | P8: 13886.853 | Q8: 23485.776 | R8: 24070.414 | S8: 26003.242 | T8: 5334.8198 | U8: 8798.705 | V8: 10351.651 | W8: 18777.04 | X8: 19897.971 | Y8: 21554.1 | Z8: 10354.117 | AA8: 12041.548 | AB8: 18100.421 | AC8: 26431.311 | AD8: 31084.336 | AE8: 33038.685 | AF8: 6615.6635 | AG8: 8775.4363 | AH8: 13584.625 | AI8: 22577.484 | AJ8: 26154.532 | AK8: 27581.701 | AL8: 14471.685 | AM8: 18651.347 | AN8: 24097.818 | AO8: 36838.103 | AP8: 38796.882 | AQ8: 35736.188 | AR8: 8912.2388 | AS8: 13267.925 | AT8: 18218.983 | AU8: 28660.02 | AV8: 32614.083 | AW8: 33657.993 | AX8: 26834.776 | AY8: 27956.471 | AZ8: 43927.676 | BA8: 59785.778 | BB8: 62719.467 | BC8: 56751.418 | BD8: 18829.473 | BE8: 25673.427 | BF8: 32943.662 | BG8: 43470.513 | BH8: 51206.219 | BI8: 47386.053 | BJ8: 0
A9: CYP | B9: 8921.7266 | C9: 5258.4556 | D9: 15087.214 | E9: 20162.66 | F9: 28324.991 | G9: 28073.197 | H9: 9620.4468 | I9: 8664.5118 | J9: 15598.915 | K9: 20089.993 | L9: 27970.936 | M9: 27570.151 | N9: 14450.359 | O9: 14110.318 | P9: 22902.325 | Q9: 33057 | R9: 43141.887 | S9: 47130.078 | T9: 12700.849 | U9: 17042.057 | V9: 20654.17 | W9: 36653.871 | X9: 40148.505 | Y9: 43145.948 | Z9: 21703.902 | AA9: 16069.36 | AB9: 34541.573 | AC9: 50275.359 | AD9: 59355.597 | AE9: 61960.485 | AF9: 15695.629 | AG9: 19372.061 | AH9: 25799.14 | AI9: 44018.534 | AJ9: 56587.614 | AK9: 44728.629 | AL9: 30646.726 | AM9: 21947.631 | AN9: 46020.968 | AO9: 68556.469 | AP9: 74198.971 | AQ9: 80433.437 | AR9: 22580.162 | AS9: 24914.209 | AT9: 36050.029 | AU9: 50411.523 | AV9: 62921.337 | AW9: 63455.541 | AX9: 54625.605 | AY9: 37784.044 | AZ9: 90311.282 | BA9: 110589.75 | BB9: 130069.76 | BC9: 121544.9 | BD9: 37598.51 | BE9: 31385.056 | BF9: 55667.791 | BG9: 76472.123 | BH9: 89598.586 | BI9: 92660.973 | BJ9: 0
A10: CZE | B10: 7031.3739 | C10: 2070.0302 | D10: 12458.86 | E10: 13707.178 | F10: 18453.46 | G10: 15533.08 | H10: 6567.9405 | I10: 4030.1238 | J10: 13145.13 | K10: 14982.18 | L10: 21144.213 | M10: 17979.919 | N10: 10264.47 | O10: 6459.3966 | P10: 17892.313 | Q10: 21559.085 | R10: 24974.833 | S10: 23015.133 | T10: 9140.5443 | U10: 7911.2629 | V10: 17265.605 | W10: 21745.652 | X10: 27383.212 | Y10: 26455.701 | Z10: 12076.466 | AA10: 8266.9067 | AB10: 21623.501 | AC10: 26489.307 | AD10: 30360.965 | AE10: 33172.169 | AF10: 10536.546 | AG10: 7708.1894 | AH10: 19471.114 | AI10: 25758.698 | AJ10: 32002.847 | AK10: 30719.518 | AL10: 14174.126 | AM10: 14839.639 | AN10: 27782.924 | AO10: 36730.527 | AP10: 38643.886 | AQ10: 47330.25 | AR10: 12510.701 | AS10: 10718.215 | AT10: 23561.955 | AU10: 28418.147 | AV10: 38006.909 | AW10: 35099.111 | AX10: 32503.768 | AY10: 25691.359 | AZ10: 55098.046 | BA10: 69598.171 | BB10: 82864.256 | BC10: 78875.813 | BD10: 23364.134 | BE10: 24827.871 | BF10: 43218.443 | BG10: 57498.779 | BH10: 58642.751 | BI10: 54922.799 | BJ10: 0
A11: DNK | B11: 12928.805 | C11: 15379.877 | D11: 32848.158 | E11: 54606.718 | F11: 58805.767 | G11: 82612.606 | H11: 20013.508 | I11: 17760.513 | J11: 41161.793 | K11: 57332.848 | L11: 74631.11 | M11: 78643.721 | N11: 21440.178 | O11: 31123.857 | P11: 44242.458 | Q11: 83859.702 | R11: 76429.015 | S11: 104042.38 | T11: 26354.275 | U11: 33949.535 | V11: 46168.341 | W11: 80065.285 | X11: 87599.689 | Y11: 83101.902 | Z11: 31991.425 | AA11: 38377.54 | AB11: 62396.681 | AC11: 87140.079 | AD11: 94453.613 | AE11: 133647.8 | AF11: 30254.261 | AG11: 32107.85 | AH11: 62494.4 | AI11: 82664.158 | AJ11: 97266.665 | AK11: 93826.634 | AL11: 38889.813 | AM11: 42585.709 | AN11: 76534.626 | AO11: 124357.04 | AP11: 126555.51 | AQ11: 163284.45 | AR11: 35326.004 | AS11: 50814.731 | AT11: 72926.348 | AU11: 98336.819 | AV11: 110695.9 | AW11: 102859.99 | AX11: 59550.285 | AY11: 74296.935 | AZ11: 102265.16 | BA11: 141390.78 | BB11: 147965.37 | BC11: 237091.14 | BD11: 49147.887 | BE11: 56624.334 | BF11: 98241.019 | BG11: 139282.27 | BH11: 158388.67 | BI11: 203588 | BJ11: 0
A12: EST | B12: 6058.6316 | C12: 3814.7606 | D12: 11570.442 | E12: 14090.071 | F12: 16227.865 | G12: 17981.1 | H12: 4909.0811 | I12: 4755.892 | J12: 9279.2384 | K12: 13469.162 | L12: 15296.949 | M12: 18289.219 | N12: 7873.0569 | O12: 8803.9482 | P12: 14878.607 | Q12: 21820.886 | R12: 24925.363 | S12: 26224.802 | T12: 6701.9275 | U12: 10678.333 | V12: 13357.869 | W12: 21549.322 | X12: 21504.308 | Y12: 28743.838 | Z12: 8668.9327 | AA12: 11121.08 | AB12: 19550.785 | AC12: 29391.979 | AD12: 32279.766 | AE12: 33292.927 | AF12: 7087.8399 | AG12: 11065.178 | AH12: 16012.306 | AI12: 27122.198 | AJ12: 27942.502 | AK12: 32899.775 | AL12: 13494.145 | AM12: 18987.175 | AN12: 27023.89 | AO12: 40564.1 | AP12: 37900.129 | AQ12: 43420.185 | AR12: 10035.76 | AS12: 15729.485 | AT12: 21886.133 | AU12: 33649.866 | AV12: 35498.115 | AW12: 39819.11 | AX12: 23560.621 | AY12: 31835.195 | AZ12: 43026.603 | BA12: 58223.02 | BB12: 57060.31 | BC12: 67202.973 | BD12: 19913.271 | BE12: 28870.471 | BF12: 40210.525 | BG12: 52201.942 | BH12: 57288.693 | BI12: 55015.575 | BJ12: 0
A13: FIN | B13: 13188.536 | C13: 22567.403 | D13: 28622.011 | E13: 47202.646 | F13: 61036.374 | G13: 63320.035 | H13: 13988.53 | I13: 26281.788 | J13: 32650.466 | K13: 50817.035 | L13: 54591.828 | M13: 70938.663 | N13: 21573.756 | O13: 36512.475 | P13: 46781.681 | Q13: 65136.25 | R13: 78056.833 | S13: 74020.241 | T13: 20588.288 | U13: 29531.008 | V13: 46465.888 | W13: 63685.558 | X13: 70935.034 | Y13: 78947.479 | Z13: 27795.442 | AA13: 40174.864 | AB13: 61316.602 | AC13: 79796.913 | AD13: 93626.19 | AE13: 95548.781 | AF13: 25285.37 | AG13: 33324.794 | AH13: 57044.696 | AI13: 76203.281 | AJ13: 85767.841 | AK13: 87139.821 | AL13: 36108.801 | AM13: 39379.626 | AN13: 79205.328 | AO13: 97197.712 | AP13: 113579.48 | AQ13: 113167.44 | AR13: 32572.022 | AS13: 44341.845 | AT13: 69501.962 | AU13: 80986.023 | AV13: 94213.834 | AW13: 99330.156 | AX13: 59130.057 | AY13: 59237.174 | AZ13: 123071.46 | BA13: 128173.41 | BB13: 163449.67 | BC13: 185776.65 | BD13: 49020.795 | BE13: 59929.811 | BF13: 95411.092 | BG13: 108450.86 | BH13: 127119.55 | BI13: 129305.51 | BJ13: 0
A14: FRA | B14: 14492.58 | C14: 22190.417 | D14: 28840.389 | E14: 36323.154 | F14: 39914.62 | G14: 43891.385 | H14: 16799.834 | I14: 17388.039 | J14: 30465.541 | K14: 37269.15 | L14: 43274.198 | M14: 46895.762 | N14: 24239.756 | O14: 29227.294 | P14: 46048.5 | Q14: 57871.092 | R14: 59134.295 | S14: 57542.376 | T14: 23944.26 | U14: 26414.36 | V14: 43381.372 | W14: 56956.011 | X14: 65156.147 | Y14: 64135.982 | Z14: 31396.037 | AA14: 29408.785 | AB14: 59351.584 | AC14: 72267.488 | AD14: 80516.479 | AE14: 79005.009 | AF14: 29058.596 | AG14: 30340.947 | AH14: 53466.935 | AI14: 65592.533 | AJ14: 76222.972 | AK14: 75411.12 | AL14: 41874.539 | AM14: 35738.926 | AN14: 77490.681 | AO14: 86691.232 | AP14: 92640.119 | AQ14: 96885.322 | AR14: 36000.952 | AS14: 33990.54 | AT14: 66497.911 | AU14: 74499.91 | AV14: 91580.35 | AW14: 87642.997 | AX14: 70590.267 | AY14: 58470.108 | AZ14: 153973.56 | BA14: 132008.88 | BB14: 162313.2 | BC14: 158387.71 | BD14: 59249.901 | BE14: 44710.285 | BF14: 102130.34 | BG14: 110611.61 | BH14: 130342.89 | BI14: 134980.14 | BJ14: 0
A15: DEU | B15: 9687.3427 | C15: 12024.462 | D15: 21441.753 | E15: 30183.342 | F15: 35177.136 | G15: 34046.506 | H15: 9596.2458 | I15: 11309.929 | J15: 21528.074 | K15: 27581.115 | L15: 38212.774 | M15: 38105.861 | N15: 15812.871 | O15: 18236.351 | P15: 34889.127 | Q15: 44357.759 | R15: 56980.799 | S15: 52126.662 | T15: 16861.533 | U15: 16840.788 | V15: 32568.466 | W15: 41591.719 | X15: 58484.201 | Y15: 56078.547 | Z15: 24095.03 | AA15: 20893.069 | AB15: 47287.484 | AC15: 56474.825 | AD15: 75675.245 | AE15: 63989.825 | AF15: 24665.262 | AG15: 20413.806 | AH15: 44106.49 | AI15: 52208.489 | AJ15: 72080.274 | AK15: 62471.177 | AL15: 36085.126 | AM15: 27387.175 | AN15: 70388.348 | AO15: 96317.815 | AP15: 107127.59 | AQ15: 78471.662 | AR15: 32264.176 | AS15: 24176.968 | AT15: 62062.275 | AU15: 66795.747 | AV15: 86319.603 | AW15: 76180.153 | AX15: 88089.746 | AY15: 51138.592 | AZ15: 191802.91 | BA15: 125249.82 | BB15: 194513.21 | BC15: 181336.64 | BD15: 73454.286 | BE15: 43018.419 | BF15: 155640.29 | BG15: 118913.28 | BH15: 210341.77 | BI15: 166639.45 | BJ15: 0
A16: GRC | B16: 5935.4006 | C16: 10271.643 | D16: 14432.07 | E16: 14085.277 | F16: 18134.971 | G16: 12611.038 | H16: 8376.2394 | I16: 9309.7192 | J16: 15535.255 | K16: 14814.69 | L16: 18119.047 | M16: 17252.909 | N16: 15909.737 | O16: 17173.539 | P16: 24229.508 | Q16: 22471.695 | R16: 32488.82 | S16: 24476.653 | T16: 15115.01 | U16: 8654.8129 | V16: 23254.817 | W16: 22703.398 | X16: 27864.212 | Y16: 28114.934 | Z16: 19562.463 | AA16: 18875.395 | AB16: 32235.387 | AC16: 33782.42 | AD16: 39997.984 | AE16: 30392.38 | AF16: 17737.474 | AG16: 19803.21 | AH16: 27914.034 | AI16: 29315.503 | AJ16: 36514.521 | AK16: 33179.167 | AL16: 23550.074 | AM16: 27634.477 | AN16: 40751.82 | AO16: 43060.094 | AP16: 52073.875 | AQ16: 42671.578 | AR16: 22558.191 | AS16: 19877.821 | AT16: 34213.181 | AU16: 38896.19 | AV16: 46338.783 | AW16: 44217.507 | AX16: 41563.018 | AY16: 43797.043 | AZ16: 61852.991 | BA16: 72191.484 | BB16: 79899.952 | BC16: 64559.181 | BD16: 34054.005 | BE16: 41530.985 | BF16: 54557.461 | BG16: 64685.728 | BH16: 70722.132 | BI16: 75839.571 | BJ16: 0
... A39: LROW | B39: 0 | C39: 0 | D39: 0 | E39: 0 | F39: 0 | G39: 0 | H39: 0 | I39: 0 | J39: 0 | K39: 0 | L39: 0 | M39: 0 | N39: 0 | O39: 0 | P39: 0 | Q39: 0 | R39: 0 | S39: 0 | T39: 0 | U39: 0 | V39: 0 | W39: 0 | X39: 0 | Y39: 0 | Z39: 0 | AA39: 0 | AB39: 0 | AC39: 0 | AD39: 0 | AE39: 0 | AF39: 0 | AG39: 0 | AH39: 0 | AI39: 0 | AJ39: 0 | AK39: 0 | AL39: 0 | AM39: 0 | AN39: 0 | AO39: 0 | AP39: 0 | AQ39: 0 | AR39: 0 | AS39: 0 | AT39: 0 | AU39: 0 | AV39: 0 | AW39: 0 | AX39: 0 | AY39: 0 | AZ39: 0 | BA39: 0 | BB39: 0 | BC39: 0 | BD39: 0 | BE39: 0 | BF39: 0 | BG39: 0 | BH39: 0 | BI39: 0 | BJ39: 11434.896

Sheet EXO_sum_income_shares
B4: INCOME1_DENSE_SINGLE | C4: INCOME1_DENSE_SINGLEWCHILDREN | D4: INCOME1_DENSE_COUPLE | E4: INCOME1_DENSE_COUPLEWCHILDREN | F4: INCOME1_DENSE_OTHER | G4: INCOME1_DENSE_OTHERWCHILDREN | H4: INCOME1_SPARSE_SINGLE | I4: INCOME1_SPARSE_SINGLEWCHILDREN | J4: INCOME1_SPARSE_COUPLE | K4: INCOME1_SPARSE_COUPLEWCHILDREN | L4: INCOME1_SPARSE_OTHER | M4: INCOME1_SPARSE_OTHERWCHILDREN | N4: INCOME2_DENSE_SINGLE | O4: INCOME2_DENSE_SINGLEWCHILDREN | P4: INCOME2_DENSE_COUPLE | Q4: INCOME2_DENSE_COUPLEWCHILDREN | R4: INCOME2_DENSE_OTHER | S4: INCOME2_DENSE_OTHERWCHILDREN | T4: INCOME2_SPARSE_SINGLE | U4: INCOME2_SPARSE_SINGLEWCHILDREN | V4: INCOME2_SPARSE_COUPLE | W4: INCOME2_SPARSE_COUPLEWCHILDREN | X4: INCOME2_SPARSE_OTHER | Y4: INCOME2_SPARSE_OTHERWCHILDREN | Z4: INCOME3_DENSE_SINGLE | AA4: INCOME3_DENSE_SINGLEWCHILDREN | AB4: INCOME3_DENSE_COUPLE | AC4: INCOME3_DENSE_COUPLEWCHILDREN | AD4: INCOME3_DENSE_OTHER | AE4: INCOME3_DENSE_OTHERWCHILDREN | AF4: INCOME3_SPARSE_SINGLE | AG4: INCOME3_SPARSE_SINGLEWCHILDREN | AH4: INCOME3_SPARSE_COUPLE | AI4: INCOME3_SPARSE_COUPLEWCHILDREN | AJ4: INCOME3_SPARSE_OTHER | AK4: INCOME3_SPARSE_OTHERWCHILDREN | AL4: INCOME4_DENSE_SINGLE | AM4: INCOME4_DENSE_SINGLEWCHILDREN | AN4: INCOME4_DENSE_COUPLE | AO4: INCOME4_DENSE_COUPLEWCHILDREN | AP4: INCOME4_DENSE_OTHER | AQ4: INCOME4_DENSE_OTHERWCHILDREN | AR4: INCOME4_SPARSE_SINGLE | AS4: INCOME4_SPARSE_SINGLEWCHILDREN | AT4: INCOME4_SPARSE_COUPLE | AU4: INCOME4_SPARSE_COUPLEWCHILDREN | AV4: INCOME4_SPARSE_OTHER | AW4: INCOME4_SPARSE_OTHERWCHILDREN | AX4: INCOME5_DENSE_SINGLE | AY4: INCOME5_DENSE_SINGLEWCHILDREN | AZ4: INCOME5_DENSE_COUPLE | BA4: INCOME5_DENSE_COUPLEWCHILDREN | BB4: INCOME5_DENSE_OTHER | BC4: INCOME5_DENSE_OTHERWCHILDREN | BD4: INCOME5_SPARSE_SINGLE | BE4: INCOME5_SPARSE_SINGLEWCHILDREN | BF4: INCOME5_SPARSE_COUPLE | BG4: INCOME5_SPARSE_COUPLEWCHILDREN | BH4: INCOME5_SPARSE_OTHER | BI4: INCOME5_SPARSE_OTHERWCHILDREN | BJ4: REPRESENTATIVE_HOUSEHOLD
A5: INCOME1_DENSE_SINGLE | B5: 1 | C5: 0 | D5: 0 | E5: 0 | F5: 0 | G5: 0 | H5: 0 | I5: 0 | J5: 0 | K5: 0 | L5: 0 | M5: 0 | N5: 1 | O5: 0 | P5: 0 | Q5: 0 | R5: 0 | S5: 0 | T5: 0 | U5: 0 | V5: 0 | W5: 0 | X5: 0 | Y5: 0 | Z5: 1 | AA5: 0 | AB5: 0 | AC5: 0 | AD5: 0 | AE5: 0 | AF5: 0 | AG5: 0 | AH5: 0 | AI5: 0 | AJ5: 0 | AK5: 0 | AL5: 1 | AM5: 0 | AN5: 0 | AO5: 0 | AP5: 0 | AQ5: 0 | AR5: 0 | AS5: 0 | AT5: 0 | AU5: 0 | AV5: 0 | AW5: 0 | AX5: 1 | AY5: 0 | AZ5: 0 | BA5: 0 | BB5: 0 | BC5: 0 | BD5: 0 | BE5: 0 | BF5: 0 | BG5: 0 | BH5: 0 | BI5: 0 | BJ5: 0
A6: INCOME1_DENSE_SINGLEWCHILDREN | B6: 0 | C6: 1 | D6: 0 | E6: 0 | F6: 0 | G6: 0 | H6: 0 | I6: 0 | J6: 0 | K6: 0 | L6: 0 | M6: 0 | N6: 0 | O6: 1 | P6: 0 | Q6: 0 | R6: 0 | S6: 0 | T6: 0 | U6: 0 | V6: 0 | W6: 0 | X6: 0 | Y6: 0 | Z6: 0 | AA6: 1 | AB6: 0 | AC6: 0 | AD6: 0 | AE6: 0 | AF6: 0 | AG6: 0 | AH6: 0 | AI6: 0 | AJ6: 0 | AK6: 0 | AL6: 0 | AM6: 1 | AN6: 0 | AO6: 0 | AP6: 0 | AQ6: 0 | AR6: 0 | AS6: 0 | AT6: 0 | AU6: 0 | AV6: 0 | AW6: 0 | AX6: 0 | AY6: 1 | AZ6: 0 | BA6: 0 | BB6: 0 | BC6: 0 | BD6: 0 | BE6: 0 | BF6: 0 | BG6: 0 | BH6: 0 | BI6: 0 | BJ6: 0
A7: INCOME1_DENSE_COUPLE | B7: 0 | C7: 0 | D7: 1 | E7: 0 | F7: 0 | G7: 0 | H7: 0 | I7: 0 | J7: 0 | K7: 0 | L7: 0 | M7: 0 | N7: 0 | O7: 0 | P7: 1 | Q7: 0 | R7: 0 | S7: 0 | T7: 0 | U7: 0 | V7: 0 | W7: 0 | X7: 0 | Y7: 0 | Z7: 0 | AA7: 0 | AB7: 1 | AC7: 0 | AD7: 0 | AE7: 0 | AF7: 0 | AG7: 0 | AH7: 0 | AI7: 0 | AJ7: 0 | AK7: 0 | AL7: 0 | AM7: 0 | AN7: 1 | AO7: 0 | AP7: 0 | AQ7: 0 | AR7: 0 | AS7: 0 | AT7: 0 | AU7: 0 | AV7: 0 | AW7: 0 | AX7: 0 | AY7: 0 | AZ7: 1 | BA7: 0 | BB7: 0 | BC7: 0 | BD7: 0 | BE7: 0 | BF7: 0 | BG7: 0 | BH7: 0 | BI7: 0 | BJ7: 0
A8: INCOME1_DENSE_COUPLEWCHILDREN | B8: 0 | C8: 0 | D8: 0 | E8: 1 | F8: 0 | G8: 0 | H8: 0 | I8: 0 | J8: 0 | K8: 0 | L8: 0 | M8: 0 | N8: 0 | O8: 0 | P8: 0 | Q8: 1 | R8: 0 | S8: 0 | T8: 0 | U8: 0 | V8: 0 | W8: 0 | X8: 0 | Y8: 0 | Z8: 0 | AA8: 0 | AB8: 0 | AC8: 1 | AD8: 0 | AE8: 0 | AF8: 0 | AG8: 0 | AH8: 0 | AI8: 0 | AJ8: 0 | AK8: 0 | AL8: 0 | AM8: 0 | AN8: 0 | AO8: 1 | AP8: 0 | AQ8: 0 | AR8: 0 | AS8: 0 | AT8: 0 | AU8: 0 | AV8: 0 | AW8: 0 | AX8: 0 | AY8: 0 | AZ8: 0 | BA8: 1 | BB8: 0 | BC8: 0 | BD8: 0 | BE8: 0 | BF8: 0 | BG8: 0 | BH8: 0 | BI8: 0 | BJ8: 0
A9: INCOME1_DENSE_OTHER | B9: 0 | C9: 0 | D9: 0 | E9: 0 | F9: 1 | G9: 0 | H9: 0 | I9: 0 | J9: 0 | K9: 0 | L9: 0 | M9: 0 | N9: 0 | O9: 0 | P9: 0 | Q9: 0 | R9: 1 | S9: 0 | T9: 0 | U9: 0 | V9: 0 | W9: 0 | X9: 0 | Y9: 0 | Z9: 0 | AA9: 0 | AB9: 0 | AC9: 0 | AD9: 1 | AE9: 0 | AF9: 0 | AG9: 0 | AH9: 0 | AI9: 0 | AJ9: 0 | AK9: 0 | AL9: 0 | AM9: 0 | AN9: 0 | AO9: 0 | AP9: 1 | AQ9: 0 | AR9: 0 | AS9: 0 | AT9: 0 | AU9: 0 | AV9: 0 | AW9: 0 | AX9: 0 | AY9: 0 | AZ9: 0 | BA9: 0 | BB9: 1 | BC9: 0 | BD9: 0 | BE9: 0 | BF9: 0 | BG9: 0 | BH9: 0 | BI9: 0 | BJ9: 0
A10: INCOME1_DENSE_OTHERWCHILDREN | B10: 0 | C10: 0 | D10: 0 | E10: 0 | F10: 0 | G10: 1 | H10: 0 | I10: 0 | J10: 0 | K10: 0 | L10: 0 | M10: 0 | N10: 0 | O10: 0 | P10: 0 | Q10: 0 | R10: 0 | S10: 1 | T10: 0 | U10: 0 | V10: 0 | W10: 0 | X10: 0 | Y10: 0 | Z10: 0 | AA10: 0 | AB10: 0 | AC10: 0 | AD10: 0 | AE10: 1 | AF10: 0 | AG10: 0 | AH10: 0 | AI10: 0 | AJ10: 0 | AK10: 0 | AL10: 0 | AM10: 0 | AN10: 0 | AO10: 0 | AP10: 0 | AQ10: 1 | AR10: 0 | AS10: 0 | AT10: 0 | AU10: 0 | AV10: 0 | AW10: 0 | AX10: 0 | AY10: 0 | AZ10: 0 | BA10: 0 | BB10: 0 | BC10: 1 | BD10: 0 | BE10: 0 | BF10: 0 | BG10: 0 | BH10: 0 | BI10: 0 | BJ10: 0
A11: INCOME1_SPARSE_SINGLE | B11: 0 | C11: 0 | D11: 0 | E11: 0 | F11: 0 | G11: 0 | H11: 1 | I11: 0 | J11: 0 | K11: 0 | L11: 0 | M11: 0 | N11: 0 | O11: 0 | P11: 0 | Q11: 0 | R11: 0 | S11: 0 | T11: 1 | U11: 0 | V11: 0 | W11: 0 | X11: 0 | Y11: 0 | Z11: 0 | AA11: 0 | AB11: 0 | AC11: 0 | AD11: 0 | AE11: 0 | AF11: 1 | AG11: 0 | AH11: 0 | AI11: 0 | AJ11: 0 | AK11: 0 | AL11: 0 | AM11: 0 | AN11: 0 | AO11: 0 | AP11: 0 | AQ11: 0 | AR11: 1 | AS11: 0 | AT11: 0 | AU11: 0 | AV11: 0 | AW11: 0 | AX11: 0 | AY11: 0 | AZ11: 0 | BA11: 0 | BB11: 0 | BC11: 0 | BD11: 1 | BE11: 0 | BF11: 0 | BG11: 0 | BH11: 0 | BI11: 0 | BJ11: 0
A12: INCOME1_SPARSE_SINGLEWCHILDREN | B12: 0 | C12: 0 | D12: 0 | E12: 0 | F12: 0 | G12: 0 | H12: 0 | I12: 1 | J12: 0 | K12: 0 | L12: 0 | M12: 0 | N12: 0 | O12: 0 | P12: 0 | Q12: 0 | R12: 0 | S12: 0 | T12: 0 | U12: 1 | V12: 0 | W12: 0 | X12: 0 | Y12: 0 | Z12: 0 | AA12: 0 | AB12: 0 | AC12: 0 | AD12: 0 | AE12: 0 | AF12: 0 | AG12: 1 | AH12: 0 | AI12: 0 | AJ12: 0 | AK12: 0 | AL12: 0 | AM12: 0 | AN12: 0 | AO12: 0 | AP12: 0 | AQ12: 0 | AR12: 0 | AS12: 1 | AT12: 0 | AU12: 0 | AV12: 0 | AW12: 0 | AX12: 0 | AY12: 0 | AZ12: 0 | BA12: 0 | BB12: 0 | BC12: 0 | BD12: 0 | BE12: 1 | BF12: 0 | BG12: 0 | BH12: 0 | BI12: 0 | BJ12: 0
A13: INCOME1_SPARSE_COUPLE | B13: 0 | C13: 0 | D13: 0 | E13: 0 | F13: 0 | G13: 0 | H13: 0 | I13: 0 | J13: 1 | K13: 0 | L13: 0 | M13: 0 | N13: 0 | O13: 0 | P13: 0 | Q13: 0 | R13: 0 | S13: 0 | T13: 0 | U13: 0 | V13: 1 | W13: 0 | X13: 0 | Y13: 0 | Z13: 0 | AA13: 0 | AB13: 0 | AC13: 0 | AD13: 0 | AE13: 0 | AF13: 0 | AG13: 0 | AH13: 1 | AI13: 0 | AJ13: 0 | AK13: 0 | AL13: 0 | AM13: 0 | AN13: 0 | AO13: 0 | AP13: 0 | AQ13: 0 | AR13: 0 | AS13: 0 | AT13: 1 | AU13: 0 | AV13: 0 | AW13: 0 | AX13: 0 | AY13: 0 | AZ13: 0 | BA13: 0 | BB13: 0 | BC13: 0 | BD13: 0 | BE13: 0 | BF13: 1 | BG13: 0 | BH13: 0 | BI13: 0 | BJ13: 0
A14: INCOME1_SPARSE_COUPLEWCHILDREN | B14: 0 | C14: 0 | D14: 0 | E14: 0 | F14: 0 | G14: 0 | H14: 0 | I14: 0 | J14: 0 | K14: 1 | L14: 0 | M14: 0 | N14: 0 | O14: 0 | P14: 0 | Q14: 0 | R14: 0 | S14: 0 | T14: 0 | U14: 0 | V14: 0 | W14: 1 | X14: 0 | Y14: 0 | Z14: 0 | AA14: 0 | AB14: 0 | AC14: 0 | AD14: 0 | AE14: 0 | AF14: 0 | AG14: 0 | AH14: 0 | AI14: 1 | AJ14: 0 | AK14: 0 | AL14: 0 | AM14: 0 | AN14: 0 | AO14: 0 | AP14: 0 | AQ14: 0 | AR14: 0 | AS14: 0 | AT14: 0 | AU14: 1 | AV14: 0 | AW14: 0 | AX14: 0 | AY14: 0 | AZ14: 0 | BA14: 0 | BB14: 0 | BC14: 0 | BD14: 0 | BE14: 0 | BF14: 0 | BG14: 1 | BH14: 0 | BI14: 0 | BJ14: 0
A15: INCOME1_SPARSE_OTHER | B15: 0 | C15: 0 | D15: 0 | E15: 0 | F15: 0 | G15: 0 | H15: 0 | I15: 0 | J15: 0 | K15: 0 | L15: 1 | M15: 0 | N15: 0 | O15: 0 | P15: 0 | Q15: 0 | R15: 0 | S15: 0 | T15: 0 | U15: 0 | V15: 0 | W15: 0 | X15: 1 | Y15: 0 | Z15: 0 | AA15: 0 | AB15: 0 | AC15: 0 | AD15: 0 | AE15: 0 | AF15: 0 | AG15: 0 | AH15: 0 | AI15: 0 | AJ15: 1 | AK15: 0 | AL15: 0 | AM15: 0 | AN15: 0 | AO15: 0 | AP15: 0 | AQ15: 0 | AR15: 0 | AS15: 0 | AT15: 0 | AU15: 0 | AV15: 1 | AW15: 0 | AX15: 0 | AY15: 0 | AZ15: 0 | BA15: 0 | BB15: 0 | BC15: 0 | BD15: 0 | BE15: 0 | BF15: 0 | BG15: 0 | BH15: 1 | BI15: 0 | BJ15: 0
A16: INCOME1_SPARSE_OTHERWCHILDREN | B16: 0 | C16: 0 | D16: 0 | E16: 0 | F16: 0 | G16: 0 | H16: 0 | I16: 0 | J16: 0 | K16: 0 | L16: 0 | M16: 1 | N16: 0 | O16: 0 | P16: 0 | Q16: 0 | R16: 0 | S16: 0 | T16: 0 | U16: 0 | V16: 0 | W16: 0 | X16: 0 | Y16: 1 | Z16: 0 | AA16: 0 | AB16: 0 | AC16: 0 | AD16: 0 | AE16: 0 | AF16: 0 | AG16: 0 | AH16: 0 | AI16: 0 | AJ16: 0 | AK16: 1 | AL16: 0 | AM16: 0 | AN16: 0 | AO16: 0 | AP16: 0 | AQ16: 0 | AR16: 0 | AS16: 0 | AT16: 0 | AU16: 0 | AV16: 0 | AW16: 1 | AX16: 0 | AY16: 0 | AZ16: 0 | BA16: 0 | BB16: 0 | BC16: 0 | BD16: 0 | BE16: 0 | BF16: 0 | BG16: 0 | BH16: 0 | BI16: 1 | BJ16: 0
... A65: REPRESENTATIVE_HOUSEHOLD | B65: 0 | C65: 0 | D65: 0 | E65: 0 | F65: 0 | G65: 0 | H65: 0 | I65: 0 | J65: 0 | K65: 0 | L65: 0 | M65: 0 | N65: 0 | O65: 0 | P65: 0 | Q65: 0 | R65: 0 | S65: 0 | T65: 0 | U65: 0 | V65: 0 | W65: 0 | X65: 0 | Y65: 0 | Z65: 0 | AA65: 0 | AB65: 0 | AC65: 0 | AD65: 0 | AE65: 0 | AF65: 0 | AG65: 0 | AH65: 0 | AI65: 0 | AJ65: 0 | AK65: 0 | AL65: 0 | AM65: 0 | AN65: 0 | AO65: 0 | AP65: 0 | AQ65: 0 | AR65: 0 | AS65: 0 | AT65: 0 | AU65: 0 | AV65: 0 | AW65: 0 | AX65: 0 | AY65: 0 | AZ65: 0 | BA65: 0 | BB65: 0 | BC65: 0 | BD65: 0 | BE65: 0 | BF65: 0 | BG65: 0 | BH65: 0 | BI65: 0 | BJ65: 1

Sheet EXO_correspondance_hh_12_to_60
B4: DENSE_SINGLE | C4: DENSE_SINGLEWCHILDREN | D4: DENSE_COUPLE | E4: DENSE_COUPLEWCHILDREN | F4: DENSE_OTHER | G4: DENSE_OTHERWCHILDREN | H4: SPARSE_SINGLE | I4: SPARSE_SINGLEWCHILDREN | J4: SPARSE_COUPLE | K4: SPARSE_COUPLEWCHILDREN | L4: SPARSE_OTHER | M4: SPARSE_OTHERWCHILDREN
A5: INCOME1_DENSE_SINGLE | B5: 1 | C5: 0 | D5: 0 | E5: 0 | F5: 0 | G5: 0 | H5: 0 | I5: 0 | J5: 0 | K5: 0 | L5: 0 | M5: 0
A6: INCOME1_DENSE_SINGLEWCHILDREN | B6: 0 | C6: 1 | D6: 0 | E6: 0 | F6: 0 | G6: 0 | H6: 0 | I6: 0 | J6: 0 | K6: 0 | L6: 0 | M6: 0
A7: INCOME1_DENSE_COUPLE | B7: 0 | C7: 0 | D7: 1 | E7: 0 | F7: 0 | G7: 0 | H7: 0 | I7: 0 | J7: 0 | K7: 0 | L7: 0 | M7: 0
A8: INCOME1_DENSE_COUPLEWCHILDREN | B8: 0 | C8: 0 | D8: 0 | E8: 1 | F8: 0 | G8: 0 | H8: 0 | I8: 0 | J8: 0 | K8: 0 | L8: 0 | M8: 0
A9: INCOME1_DENSE_OTHER | B9: 0 | C9: 0 | D9: 0 | E9: 0 | F9: 1 | G9: 0 | H9: 0 | I9: 0 | J9: 0 | K9: 0 | L9: 0 | M9: 0
A10: INCOME1_DENSE_OTHERWCHILDREN | B10: 0 | C10: 0 | D10: 0 | E10: 0 | F10: 0 | G10: 1 | H10: 0 | I10: 0 | J10: 0 | K10: 0 | L10: 0 | M10: 0
A11: INCOME1_SPARSE_SINGLE | B11: 0 | C11: 0 | D11: 0 | E11: 0 | F11: 0 | G11: 0 | H11: 1 | I11: 0 | J11: 0 | K11: 0 | L11: 0 | M11: 0
A12: INCOME1_SPARSE_SINGLEWCHILDREN | B12: 0 | C12: 0 | D12: 0 | E12: 0 | F12: 0 | G12: 0 | H12: 0 | I12: 1 | J12: 0 | K12: 0 | L12: 0 | M12: 0
A13: INCOME1_SPARSE_COUPLE | B13: 0 | C13: 0 | D13: 0 | E13: 0 | F13: 0 | G13: 0 | H13: 0 | I13: 0 | J13: 1 | K13: 0 | L13: 0 | M13: 0
A14: INCOME1_SPARSE_COUPLEWCHILDREN | B14: 0 | C14: 0 | D14: 0 | E14: 0 | F14: 0 | G14: 0 | H14: 0 | I14: 0 | J14: 0 | K14: 1 | L14: 0 | M14: 0
A15: INCOME1_SPARSE_OTHER | B15: 0 | C15: 0 | D15: 0 | E15: 0 | F15: 0 | G15: 0 | H15: 0 | I15: 0 | J15: 0 | K15: 0 | L15: 1 | M15: 0
A16: INCOME1_SPARSE_OTHERWCHILDREN | B16: 0 | C16: 0 | D16: 0 | E16: 0 | F16: 0 | G16: 0 | H16: 0 | I16: 0 | J16: 0 | K16: 0 | L16: 0 | M16: 1
... A65: REPRESENTATIVE_HOUSEHOLD | B65: 0 | C65: 0 | D65: 0 | E65: 0 | F65: 0 | G65: 0 | H65: 0 | I65: 0 | J65: 0 | K65: 0 | L65: 0 | M65: 0

Sheet EXO_Consump_Str_COICOP_CPA
C4: HH_HOUSING | D4: HH_APPLIANCES | E4: HH_VEHICLES | F4: HH_ELECTRICITY | G4: HH_GAS | H4: HH_LIQUID_FUELS | I4: HH_SOLID_FUELS | J4: HH_HEAT | K4: HH_FUEL_TRANSPORT | L4: HH_RAILWAY | M4: HH_ROAD | N4: HH_AIR | O4: HH_MARITIME | P4: HH_FOOD | Q4: HH_TEXTILES | R4: HH_FURNITURE_EQUIPMENT | S4: HH_SERVICES | T4: HH_LEISURE | U4: HH_OTHER
A5: AUT | B5: CROPS | C5: 0.00028884987 | D5: 0 | E5: 0.00017314893 | F5: 0.00050684434 | G5: 0.0002297404 | H5: 4.3790307e-05 | I5: 0.0054238677 | J5: 0.0025073124 | K5: 0.00015758357 | L5: 0.00016314713 | M5: 0.00014158593 | N5: 4.9008867e-05 | O5: 0 | P5: 0.1111814 | Q5: 0.00015021294 | R5: 0.00010709604 | S5: 0.00025906813 | T5: 0.020873689 | U5: 5.3566608e-05
A6: AUT | B6: ANIMALS | C6: 9.4103866e-05 | D6: 0 | E6: 5.6409871e-05 | F6: 0.00016512388 | G6: 7.4846701e-05 | H6: 1.4266363e-05 | I6: 0.0017670318 | J6: 0.00081685267 | K6: 5.1338861e-05 | L6: 5.3151402e-05 | M6: 4.612702e-05 | N6: 1.5966508e-05 | O6: 0 | P6: 0.036221585 | Q6: 4.8937596e-05 | R6: 3.489062e-05 | S6: 8.4401328e-05 | T6: 0.0068004006 | U6: 1.7451366e-05
A7: AUT | B7: FORESTRY | C7: 0.0005445806 | D7: 2.1838589e-05 | E7: 2.2532114e-05 | F7: 1.3657632e-05 | G7: 1.2160259e-05 | H7: 0.00012330909 | I7: 0.58218721 | J7: 0.00018579838 | K7: 1.0615776e-05 | L7: 5.3194361e-05 | M7: 6.1043706e-05 | N7: 2.9053479e-05 | O7: 1.9349576e-05 | P7: 0.0018367697 | Q7: 3.0610718e-05 | R7: 0.00010500065 | S7: 4.4546973e-06 | T7: 0.0029242028 | U7: 1.4249219e-05
A8: AUT | B8: FISHNG | C8: 8.7465851e-07 | D8: 0 | E8: 7.842125e-06 | F8: 6.9049843e-06 | G8: 6.4152492e-06 | H8: 6.5623406e-05 | I8: 3.7199613e-05 | J8: 9.6998497e-05 | K8: 4.3559007e-06 | L8: 1.5944967e-06 | M8: 1.6772985e-06 | N8: 0 | O8: 9.7827004e-05 | P8: 0.0043385501 | Q8: 1.2234051e-06 | R8: 1.1629876e-06 | S8: 1.1657311e-06 | T8: 9.9594391e-05 | U8: 2.6355289e-05
A9: AUT | B9: MINING_COAL | C9: 3.2995894e-06 | D9: 1.1377258e-07 | E9: 2.2694557e-06 | F9: 4.3829765e-06 | G9: 0.00063351348 | H9: 0.0023031867 | I9: 0.027741729 | J9: 2.2262955e-05 | K9: 0.00018435016 | L9: 2.5193351e-06 | M9: 2.6236619e-06 | N9: 3.0272004e-07 | O9: 8.0644449e-07 | P9: 8.7941975e-07 | Q9: 1.159802e-07 | R9: 1.809838e-05 | S9: 6.9843985e-07 | T9: 3.0077795e-06 | U9: 1.6942368e-05
A10: AUT | B10: EXTRACTION_OIL | C10: 3.5438756e-06 | D10: 1.2219577e-07 | E10: 2.4374757e-06 | F10: 4.7074716e-06 | G10: 0.00068041587 | H10: 0.0024737039 | I10: 0.0005950408 | J10: 2.39112e-05 | K10: 0.0024920894 | L10: 2.705855e-06 | M10: 2.8179056e-06 | N10: 3.2513202e-07 | O10: 8.6614988e-07 | P10: 9.4452789e-07 | Q10: 1.2456683e-07 | R10: 1.94383e-05 | S10: 7.5014908e-07 | T10: 3.2304615e-06 | U10: 1.8196702e-05
A11: AUT | B11: EXTRACTION_GAS | C11: 0 | D11: 0 | E11: 0 | F11: 0 | G11: 0 | H11: 0 | I11: 0 | J11: 0 | K11: 0 | L11: 0 | M11: 0 | N11: 0 | O11: 0 | P11: 0 | Q11: 0 | R11: 0 | S11: 0 | T11: 0 | U11: 0
A12: AUT | B12: EXTRACTION_OTHER_GAS | C12: 3.0638263e-07 | D12: 1.0564327e-08 | E12: 2.107298e-07 | F12: 4.0698029e-07 | G12: 0.00074039185 | H12: 0.00021386188 | I12: 5.1443725e-05 | J12: 2.0672216e-06 | K12: 1.7117792e-05 | L12: 2.339323e-07 | M12: 2.4361953e-07 | N12: 2.8109001e-08 | O12: 7.4882221e-08 | P12: 8.1658323e-08 | Q12: 1.0769315e-08 | R12: 1.680521e-06 | S12: 6.4853475e-08 | T12: 2.7928669e-07 | U12: 1.5731797e-06
A13: AUT | B13: MINING_AND_MANUFACTURING_URANIUM_THORIUM | C13: 1.9898216e-06 | D13: 2.0992809e-07 | E13: 1.1295533e-07 | F13: 1.5161519e-07 | G13: 1.1312234e-07 | H13: 1.6099624e-07 | I13: 5.4066337e-05 | J13: 7.6338231e-07 | K13: 2.5895647e-07 | L13: 2.5492129e-08 | M13: 2.4844169e-08 | N13: 2.2522803e-09 | O13: 1.2000124e-08 | P13: 1.4229455e-08 | Q13: 1.8984003e-08 | R13: 1.3190844e-05 | S13: 2.6574466e-08 | T13: 1.1173721e-06 | U13: 1.6159104e-07
A14: AUT | B14: MINING_AND_MANUFACTURING_IRON | C14: 0.00043615968 | D14: 4.6015265e-05 | E14: 2.4759284e-05 | F14: 3.3233347e-05 | G14: 2.4795892e-05 | H14: 3.5289631e-05 | I14: 0.011851091 | J14: 0.00016732987 | K14: 5.6762059e-05 | L14: 5.5877567e-06 | M14: 5.4457268e-06 | N14: 4.936894e-07 | O14: 2.6303716e-06 | P14: 3.1190307e-06 | Q14: 4.1612056e-06 | R14: 0.0028913719 | S14: 5.8249999e-06 | T14: 0.00024492279 | U14: 3.5420007e-05
A15: AUT | B15: MINING_AND_MANUFACTURING_COPPER | C15: 0.00032197576 | D15: 3.3968752e-05 | E15: 1.8277456e-05 | F15: 2.4533061e-05 | G15: 1.830448e-05 | H15: 2.6051023e-05 | I15: 0.0087485481 | J15: 0.00012352394 | K15: 4.1902102e-05 | L15: 4.1249164e-06 | M15: 4.0200691e-06 | N15: 3.6444456e-07 | O15: 1.9417565e-06 | P15: 2.3024877e-06 | Q15: 3.0718276e-06 | R15: 0.0021344285 | S15: 4.3000508e-06 | T15: 0.00018080351 | U15: 2.6147267e-05
A16: AUT | B16: MINING_AND_MANUFACTURING_NICKEL | C16: 7.6513339e-07 | D16: 8.0722307e-08 | E16: 4.343399e-08 | F16: 5.8299619e-08 | G16: 4.3498209e-08 | H16: 6.1906857e-08 | I16: 2.0789783e-05 | J16: 2.9353852e-07 | K16: 9.9574878e-08 | L16: 9.8023257e-09 | M16: 9.5531697e-09 | N16: 8.6605494e-10 | O16: 4.614331e-09 | P16: 5.4715615e-09 | Q16: 7.2997975e-09 | R16: 5.0721909e-06 | S16: 1.021851e-08 | T16: 4.2965596e-07 | U16: 6.2135569e-08
... A2174: LROW | B2174: PRIVATE_HOUSEHOLDS | C2174: 0 | D2174: 0 | E2174: 0 | F2174: 0 | G2174: 0 | H2174: 0 | I2174: 0 | J2174: 0 | K2174: 0 | L2174: 0 | M2174: 0 | N2174: 0 | O2174: 0 | P2174: 0 | Q2174: 0 | R2174: 0 | S2174: 0 | T2174: 0 | U2174: 0

Sheet EXO_Share_Labour_income
B4: INCOME1_DENSE_SINGLE | C4: INCOME1_DENSE_SINGLEWCHILDREN | D4: INCOME1_DENSE_COUPLE | E4: INCOME1_DENSE_COUPLEWCHILDREN | F4: INCOME1_DENSE_OTHER | G4: INCOME1_DENSE_OTHERWCHILDREN | H4: INCOME1_SPARSE_SINGLE | I4: INCOME1_SPARSE_SINGLEWCHILDREN | J4: INCOME1_SPARSE_COUPLE | K4: INCOME1_SPARSE_COUPLEWCHILDREN | L4: INCOME1_SPARSE_OTHER | M4: INCOME1_SPARSE_OTHERWCHILDREN | N4: INCOME2_DENSE_SINGLE | O4: INCOME2_DENSE_SINGLEWCHILDREN | P4: INCOME2_DENSE_COUPLE | Q4: INCOME2_DENSE_COUPLEWCHILDREN | R4: INCOME2_DENSE_OTHER | S4: INCOME2_DENSE_OTHERWCHILDREN | T4: INCOME2_SPARSE_SINGLE | U4: INCOME2_SPARSE_SINGLEWCHILDREN | V4: INCOME2_SPARSE_COUPLE | W4: INCOME2_SPARSE_COUPLEWCHILDREN | X4: INCOME2_SPARSE_OTHER | Y4: INCOME2_SPARSE_OTHERWCHILDREN | Z4: INCOME3_DENSE_SINGLE | AA4: INCOME3_DENSE_SINGLEWCHILDREN | AB4: INCOME3_DENSE_COUPLE | AC4: INCOME3_DENSE_COUPLEWCHILDREN | AD4: INCOME3_DENSE_OTHER | AE4: INCOME3_DENSE_OTHERWCHILDREN | AF4: INCOME3_SPARSE_SINGLE | AG4: INCOME3_SPARSE_SINGLEWCHILDREN | AH4: INCOME3_SPARSE_COUPLE | AI4: INCOME3_SPARSE_COUPLEWCHILDREN | AJ4: INCOME3_SPARSE_OTHER | AK4: INCOME3_SPARSE_OTHERWCHILDREN | AL4: INCOME4_DENSE_SINGLE | AM4: INCOME4_DENSE_SINGLEWCHILDREN | AN4: INCOME4_DENSE_COUPLE | AO4: INCOME4_DENSE_COUPLEWCHILDREN | AP4: INCOME4_DENSE_OTHER | AQ4: INCOME4_DENSE_OTHERWCHILDREN | AR4: INCOME4_SPARSE_SINGLE | AS4: INCOME4_SPARSE_SINGLEWCHILDREN | AT4: INCOME4_SPARSE_COUPLE | AU4: INCOME4_SPARSE_COUPLEWCHILDREN | AV4: INCOME4_SPARSE_OTHER | AW4: INCOME4_SPARSE_OTHERWCHILDREN | AX4: INCOME5_DENSE_SINGLE | AY4: INCOME5_DENSE_SINGLEWCHILDREN | AZ4: INCOME5_DENSE_COUPLE | BA4: INCOME5_DENSE_COUPLEWCHILDREN | BB4: INCOME5_DENSE_OTHER | BC4: INCOME5_DENSE_OTHERWCHILDREN | BD4: INCOME5_SPARSE_SINGLE | BE4: INCOME5_SPARSE_SINGLEWCHILDREN | BF4: INCOME5_SPARSE_COUPLE | BG4: INCOME5_SPARSE_COUPLEWCHILDREN | BH4: INCOME5_SPARSE_OTHER | BI4: INCOME5_SPARSE_OTHERWCHILDREN | BJ4: REPRESENTATIVE_HOUSEHOLD
A5: AUT | B5: 0 | C5: 0 | D5: 0 | E5: 0 | F5: 0 | G5: 0 | H5: 0 | I5: 0 | J5: 0 | K5: 0 | L5: 0 | M5: 0 | N5: 0 | O5: 0 | P5: 0 | Q5: 0 | R5: 0 | S5: 0 | T5: 0 | U5: 0 | V5: 0 | W5: 0 | X5: 0 | Y5: 0 | Z5: 0 | AA5: 0 | AB5: 0 | AC5: 0 | AD5: 0 | AE5: 0 | AF5: 0 | AG5: 0 | AH5: 0 | AI5: 0 | AJ5: 0 | AK5: 0 | AL5: 0 | AM5: 0 | AN5: 0 | AO5: 0 | AP5: 0 | AQ5: 0 | AR5: 0 | AS5: 0 | AT5: 0 | AU5: 0 | AV5: 0 | AW5: 0 | AX5: 0 | AY5: 0 | AZ5: 0 | BA5: 0 | BB5: 0 | BC5: 0 | BD5: 0 | BE5: 0 | BF5: 0 | BG5: 0 | BH5: 0 | BI5: 0 | BJ5: 1
A6: BEL | B6: 0.0027576737 | C6: 0.00026552215 | D6: 0.003989307 | E6: 0.004013449 | F6: 0.0013743648 | G6: 0.0011646821 | H6: 0.0051730865 | I6: 0.0013076991 | J6: 0.011272911 | K6: 0.02086751 | L6: 0.01364894 | M6: 0.0041580457 | N6: 0.0043440262 | O6: 0.0011015271 | P6: 0.0069606997 | Q6: 0.0086341309 | R6: 0.004910504 | S6: 0.0022882696 | T6: 0.0077927963 | U6: 0.0010738767 | V6: 0.015246826 | W6: 0.034718038 | X6: 0.02419879 | Y6: 0.008963031 | Z6: 0.0098035799 | AA6: 0.001534536 | AB6: 0.01120761 | AC6: 0.014766253 | AD6: 0.0095350401 | AE6: 0.0040707529 | AF6: 0.010639446 | AG6: 0.0023076253 | AH6: 0.0325255 | AI6: 0.048046716 | AJ6: 0.031519566 | AK6: 0.01302732 | AL6: 0.017859067 | AM6: 0.0022138106 | AN6: 0.017581012 | AO6: 0.02132645 | AP6: 0.0090683997 | AQ6: 0.0052681703 | AR6: 0.020102236 | AS6: 0.0039237114 | AT6: 0.047452726 | AU6: 0.055175772 | AV6: 0.040121025 | AW6: 0.016813569 | AX6: 0.040253933 | AY6: 0.0042631576 | AZ6: 0.026686482 | BA6: 0.028787434 | BB6: 0.01501548 | BC6: 0.0088728186 | BD6: 0.034803703 | BE6: 0.0053271005 | BF6: 0.055142874 | BG6: 0.065784103 | BH6: 0.056935793 | BI6: 0.022011521 | BJ6: 0
A7: BGR | B7: 0.0011996584 | C7: 6.970636e-05 | D7: 0.0040620836 | E7: 0.010139751 | F7: 0.012779637 | G7: 0.0028443997 | H7: 0.000688003 | I7: 4.1039057e-05 | J7: 0.0031455203 | K7: 0.0020540641 | L7: 0.007992787 | M7: 0.0028438522 | N7: 0.0015283097 | O7: 0.00047111959 | P7: 0.0088226671 | Q7: 0.015874258 | R7: 0.023884934 | S7: 0.0062422636 | T7: 0.00087709878 | U7: 0.00031118045 | V7: 0.0055150699 | W7: 0.0077856017 | X7: 0.016028755 | Y7: 0.0080819338 | Z7: 0.0045180476 | AA7: 0.00074435255 | AB7: 0.014396717 | AC7: 0.022637938 | AD7: 0.031935505 | AE7: 0.010850318 | AF7: 0.0012439124 | AG7: 0.00048431936 | AH7: 0.010449998 | AI7: 0.014934155 | AJ7: 0.024590871 | AK7: 0.01348113 | AL7: 0.016237125 | AM7: 0.0014174363 | AN7: 0.030014368 | AO7: 0.034605727 | AP7: 0.044722354 | AQ7: 0.013874711 | AR7: 0.0044157516 | AS7: 0.00067049923 | AT7: 0.020664386 | AU7: 0.019361827 | AV7: 0.036751796 | AW7: 0.018392922 | AX7: 0.039592059 | AY7: 0.0026803255 | AZ7: 0.061456432 | BA7: 0.05986197 | BB7: 0.086178048 | BC7: 0.02453108 | BD7: 0.017184784 | BE7: 0.0010277818 | BF7: 0.046426969 | BG7: 0.033333766 | BH7: 0.060565139 | BI7: 0.032481788 | BJ7: 0
A8: HRV | B8: 0.00024820254 | C8: 1.8949539e-05 | D8: 0.00098505639 | E8: 0.0042761874 | F8: 0.006645963 | G8: 0.0019848994 | H8: 0.00078187836 | I8: 2.357329e-05 | J8: 0.0028320348 | K8: 0.0091242975 | L8: 0.014750096 | M8: 0.0090536195 | N8: 0.0004574429 | O8: 0.00025820759 | P8: 0.0032362602 | Q8: 0.0093448757 | R8: 0.014415036 | S8: 0.0052203252 | T8: 0.0009908916 | U8: 0.00024410043 | V8: 0.0060624978 | W8: 0.020923149 | X8: 0.034841202 | Y8: 0.019103721 | Z8: 0.0018560506 | AA8: 0.0006907118 | AB8: 0.0064799007 | AC8: 0.010523682 | AD8: 0.02048168 | AE8: 0.0068718048 | AF8: 0.00081637175 | AG8: 0.00033480725 | AH8: 0.0092946006 | AI8: 0.027308176 | AJ8: 0.047216159 | AK8: 0.02897432 | AL8: 0.0070997979 | AM8: 0.00086482787 | AN8: 0.012504066 | AO8: 0.0152745 | AP8: 0.028208639 | AQ8: 0.0077510974 | AR8: 0.003111395 | AS8: 0.00053156333 | AT8: 0.018864023 | AU8: 0.036997701 | AV8: 0.06617482 | AW8: 0.038003664 | AX8: 0.019537747 | AY8: 0.0018813992 | AZ8: 0.036716513 | BA8: 0.023936822 | BB8: 0.048796514 | BC8: 0.015853643 | BD8: 0.020019126 | BE8: 0.00083344402 | BF8: 0.048218955 | BG8: 0.055726238 | BH8: 0.11062448 | BI8: 0.055798292 | BJ8: 0
A9: CYP | B9: 0.0031012946 | C9: 3.8043452e-05 | D9: 0.0058087187 | E9: 0.0075703119 | F9: 0.0088460265 | G9: 0.0051980311 | H9: 0.0024156463 | I9: 4.5559996e-05 | J9: 0.0068495234 | K9: 0.0075429332 | L9: 0.0086402098 | M9: 0.0051927789 | N9: 0.0036118498 | O9: 0.00027668161 | P9: 0.009898062 | Q9: 0.015924224 | R9: 0.01942895 | S9: 0.0091226383 | T9: 0.0022279547 | U9: 0.00071897509 | V9: 0.0067148991 | W9: 0.017756705 | X9: 0.014911998 | Y9: 0.010682913 | Z9: 0.010978468 | AA9: 0.00042278081 | AB9: 0.023411062 | AC9: 0.025785852 | AD9: 0.028803877 | AE9: 0.013206262 | AF9: 0.0028355463 | AG9: 0.00075836076 | AH9: 0.013218678 | AI9: 0.022847054 | AJ9: 0.024160929 | AK9: 0.011993072 | AL9: 0.020842971 | AM9: 0.00073290817 | AN9: 0.031606966 | AO9: 0.038084429 | AP9: 0.033159971 | AQ9: 0.019322099 | AR9: 0.0064262692 | AS9: 0.00093773805 | AT9: 0.019600431 | AU9: 0.027050306 | AV9: 0.027056303 | AW9: 0.019554263 | AX9: 0.03459096 | AY9: 0.0015164629 | AZ9: 0.062660596 | BA9: 0.068916311 | BB9: 0.053717846 | BC9: 0.02805347 | BD9: 0.010686269 | BE9: 0.0017755662 | BF9: 0.02834201 | BG9: 0.046715243 | BH9: 0.038189934 | BI9: 0.029513808 | BJ9: 0
A10: CZE | B10: 0.0018002489 | C10: 6.3390677e-05 | D10: 0.0076185502 | E10: 0.0052675738 | F10: 0.0059855511 | G10: 0.0012585275 | H10: 0.0026938971 | I10: 0.000116268 | J10: 0.011046531 | K10: 0.012649677 | L10: 0.021845311 | M10: 0.0076367719 | N10: 0.0022253396 | O10: 0.00043077539 | P10: 0.0052123608 | Q10: 0.011408457 | R10: 0.00959699 | S10: 0.0025045753 | T10: 0.00209919 | U10: 0.00090724172 | V10: 0.0091464524 | W10: 0.02421634 | X10: 0.03028338 | Y10: 0.012552864 | Z10: 0.0049343485 | AA10: 0.00070230903 | AB10: 0.010723332 | AC10: 0.015216005 | AD10: 0.01206527 | AE10: 0.0039355988 | AF10: 0.0035041034 | AG10: 0.0011996934 | AH10: 0.016197721 | AI10: 0.030979018 | AJ10: 0.036724925 | AK10: 0.015756885 | AL10: 0.012019153 | AM10: 0.001216608 | AN10: 0.027691061 | AO10: 0.022280659 | AP10: 0.016630377 | AQ10: 0.0057493975 | AR10: 0.0093728961 | AS10: 0.0018562795 | AT10: 0.035013548 | AU10: 0.037815001 | AV10: 0.044148341 | AW10: 0.019338945 | AX10: 0.029779531 | AY10: 0.0023245853 | AZ10: 0.049505911 | BA10: 0.039078102 | BB10: 0.025659926 | BC10: 0.011385979 | BD10: 0.02957504 | BE10: 0.002799048 | BF10: 0.075817349 | BG10: 0.062235804 | BH10: 0.067708266 | BI10: 0.030492719 | BJ10: 0
A11: DNK | B11: 0.0049132319 | C11: 0.00027271461 | D11: 0.0085265748 | E11: 0.0097379317 | F11: 0.002713611 | G11: 0.0019182037 | H11: 0.0083585742 | I11: 0.00032851296 | J11: 0.015235671 | K11: 0.019906729 | L11: 0.011512232 | M11: 0.0077832933 | N11: 0.00927273 | O11: 0.0013581865 | P11: 0.01174873 | Q11: 0.016467779 | R11: 0.0041342829 | S11: 0.0032541553 | T11: 0.011505656 | U11: 0.0015118508 | V11: 0.016319062 | W11: 0.032151145 | X11: 0.012920696 | Y11: 0.0080918677 | Z11: 0.01525283 | AA11: 0.0014184473 | AB11: 0.015797485 | AC11: 0.017962325 | AD11: 0.0056012143 | AE11: 0.005423656 | AF11: 0.01464772 | AG11: 0.0018589258 | AH11: 0.034104303 | AI11: 0.035298295 | AJ11: 0.016239398 | AK11: 0.010990558 | AL11: 0.025182433 | AM11: 0.0029096523 | AN11: 0.024578455 | AO11: 0.025092045 | AP11: 0.0065414132 | AQ11: 0.0064895078 | AR11: 0.02182411 | AS11: 0.0038718128 | AT11: 0.047023632 | AU11: 0.043212078 | AV11: 0.018744634 | AW11: 0.011611113 | AX11: 0.042428944 | AY11: 0.0049670198 | AZ11: 0.035846403 | BA11: 0.03135478 | BB11: 0.010743633 | BC11: 0.012633961 | BD11: 0.032147618 | BE11: 0.0057648413 | BF11: 0.068543563 | BG11: 0.061252483 | BH11: 0.029280318 | BI11: 0.033416969 | BJ11: 0
A12: EST | B12: 0.0021748391 | C12: 0.0001412103 | D12: 0.0048605268 | E12: 0.0086832069 | F12: 0.0062807541 | G12: 0.0037881024 | H12: 0.00091725224 | I12: 0.00011696336 | J12: 0.0024152708 | K12: 0.0053211436 | L12: 0.0040418252 | M12: 0.0037676776 | N12: 0.00058504788 | O12: 0.00098867908 | P12: 0.010498656 | Q12: 0.020131235 | R12: 0.014602684 | S12: 0.0086104345 | T12: 0.00049029938 | U12: 0.0010873918 | V12: 0.0027588725 | W12: 0.011607746 | X12: 0.0098519953 | Y12: 0.0076043683 | Z12: 0.0073060658 | AA12: 0.0015973312 | AB12: 0.028159195 | AC12: 0.030665908 | AD12: 0.020103546 | AE12: 0.012552119 | AF12: 0.0010148285 | AG12: 0.0012216059 | AH12: 0.011018267 | AI12: 0.014976865 | AJ12: 0.014463165 | AK12: 0.0097436586 | AL12: 0.030869074 | AM12: 0.0028562092 | AN12: 0.045243907 | AO12: 0.04150487 | AP12: 0.025946444 | AQ12: 0.017280436 | AR12: 0.010876971 | AS12: 0.0021549673 | AT12: 0.022797172 | AU12: 0.022361592 | AV12: 0.019429606 | AW12: 0.012774218 | AX12: 0.06210751 | AY12: 0.0052640954 | AZ12: 0.085005929 | BA12: 0.065679396 | BB12: 0.042735607 | BC12: 0.028591404 | BD12: 0.032479782 | BE12: 0.0031140519 | BF12: 0.048431916 | BG12: 0.034106524 | BH12: 0.034592556 | BI12: 0.019647024 | BJ12: 0
A13: FIN | B13: 0.0034053152 | C13: 0.00023559852 | D13: 0.0091110565 | E13: 0.0074307423 | F13: 0.0039980303 | G13: 0.0019235921 | H13: 0.0018173305 | I13: 0.00076978959 | J13: 0.010733512 | K13: 0.016001358 | L13: 0.0062916714 | M13: 0.0050529127 | N13: 0.0047242896 | O13: 0.00095962185 | P13: 0.017815682 | Q13: 0.015115255 | R13: 0.0060415119 | S13: 0.0031538148 | T13: 0.0022514607 | U13: 0.0005549767 | V13: 0.014369028 | W13: 0.025041943 | X13: 0.0098563663 | Y13: 0.0080181512 | Z13: 0.011602756 | AA13: 0.0012960636 | AB13: 0.025587235 | AC13: 0.020732725 | AD13: 0.0085163615 | AE13: 0.0042420052 | AF13: 0.0071543595 | AG13: 0.0014157488 | AH13: 0.030030335 | AI13: 0.033456145 | AJ13: 0.013636288 | AK13: 0.010003101 | AL13: 0.022935544 | AM13: 0.0018908175 | AN13: 0.039601853 | AO13: 0.026216921 | AP13: 0.009411592 | AQ13: 0.0058785888 | AR13: 0.018082391 | AS13: 0.0022529901 | AT13: 0.048753969 | AU13: 0.038367733 | AV13: 0.01710941 | AW13: 0.012680676 | AX13: 0.044497161 | AY13: 0.0034416652 | AZ13: 0.069354878 | BA13: 0.037975813 | BB13: 0.015636726 | BC13: 0.011355069 | BD13: 0.042920227 | BE13: 0.003208874 | BF13: 0.087230785 | BG13: 0.055475273 | BH13: 0.025179715 | BI13: 0.018195197 | BJ13: 0
A14: FRA | B14: 0.0065081708 | C14: 0.00036357094 | D14: 0.0095086289 | E14: 0.0091506729 | F14: 0.0054129156 | G14: 0.0025928562 | H14: 0.0051289985 | I14: 0.00098375121 | J14: 0.0094499292 | K14: 0.012418783 | L14: 0.0087065325 | M14: 0.0043919045 | N14: 0.015195372 | O14: 0.0015668699 | P14: 0.016650974 | Q14: 0.020934672 | R14: 0.0093745097 | S14: 0.0049040715 | T14: 0.0092477074 | U14: 0.0018052802 | V14: 0.013955683 | W14: 0.025062148 | X14: 0.01377727 | Y14: 0.0076183898 | Z14: 0.01675741 | AA14: 0.0022950767 | AB14: 0.019713348 | AC14: 0.027634369 | AD14: 0.013972349 | AE14: 0.0085001394 | AF14: 0.008814558 | AG14: 0.0024043038 | AH14: 0.018567555 | AI14: 0.031228592 | AJ14: 0.017986465 | AK14: 0.0097807979 | AL14: 0.022237005 | AM14: 0.0030756567 | AN14: 0.02809197 | AO14: 0.035133426 | AP14: 0.017421922 | AQ14: 0.010885106 | AR14: 0.012047421 | AS14: 0.0028212942 | AT14: 0.025494534 | AU14: 0.036179214 | AV14: 0.020925447 | AW14: 0.012676147 | AX14: 0.028854907 | AY14: 0.0059696432 | AZ14: 0.062534518 | BA14: 0.057083218 | BB14: 0.03294162 | BC14: 0.018222596 | BD14: 0.021172881 | BE14: 0.0045512739 | BF14: 0.041744937 | BG14: 0.05645575 | BH14: 0.031144736 | BI14: 0.01997015 | BJ14: 0
A15: DEU | B15: 0.0020610681 | C15: 0.00013598923 | D15: 0.0070338607 | E15: 0.0047921072 | F15: 0.0030813502 | G15: 0.0007105626 | H15: 0.002682915 | I15: 0.00040642898 | J15: 0.0088015526 | K15: 0.012172156 | L15: 0.012025245 | M15: 0.0027836036 | N15: 0.0064318008 | O15: 0.00035417389 | P15: 0.012050234 | Q15: 0.0095678769 | R15: 0.0067954984 | S15: 0.00097102243 | T15: 0.007091858 | U15: 0.00062163532 | V15: 0.0169851 | W15: 0.022909261 | X15: 0.021748655 | Y15: 0.0061567734 | Z15: 0.015395063 | AA15: 0.00058878608 | AB15: 0.021353472 | AC15: 0.012819496 | AD15: 0.0082578537 | AE15: 0.0017591391 | AF15: 0.013362941 | AG15: 0.00089140546 | AH15: 0.030462923 | AI15: 0.030035693 | AJ15: 0.027987556 | AK15: 0.0074049615 | AL15: 0.030994366 | AM15: 0.001473302 | AN15: 0.035459966 | AO15: 0.017209307 | AP15: 0.011265036 | AQ15: 0.002275286 | AR15: 0.028568919 | AS15: 0.0019309552 | AT15: 0.052026968 | AU15: 0.037740115 | AV15: 0.034489255 | AW15: 0.008707705 | AX15: 0.050455328 | AY15: 0.0029079643 | AZ15: 0.049940421 | BA15: 0.025788602 | BB15: 0.01649857 | BC15: 0.0032214463 | BD15: 0.04600382 | BE15: 0.0036062037 | BF15: 0.080985633 | BG15: 0.054801433 | BH15: 0.048469716 | BI15: 0.016489662 | BJ15: 0
A16: GRC | B16: 0.00080541786 | C16: 0.00011247402 | D16: 0.0028239604 | E16: 0.0067974219 | F16: 0.0071489203 | G16: 0.0016243342 | H16: 0.00074046137 | I16: 0.00020078717 | J16: 0.004830896 | K16: 0.0091463132 | L16: 0.010077805 | M16: 0.0024485343 | N16: 0.0034786792 | O16: 0.0002527184 | P16: 0.0071020176 | Q16: 0.015251564 | R16: 0.012411856 | S16: 0.0040736719 | T16: 0.0014759577 | U16: 0.00011426475 | V16: 0.0060885921 | W16: 0.02168093 | X16: 0.017236638 | Y16: 0.0081535012 | Z16: 0.0069633912 | AA16: 0.00046426793 | AB16: 0.0095810306 | AC16: 0.022619088 | AD16: 0.019752861 | AE16: 0.0053397031 | AF16: 0.0023738126 | AG16: 0.00061779102 | AH16: 0.010198336 | AI16: 0.028914275 | AJ16: 0.025881435 | AK16: 0.012090941 | AL16: 0.012141953 | AM16: 0.001160808 | AN16: 0.017223897 | AO16: 0.033290246 | AP16: 0.029547003 | AQ16: 0.0079991477 | AR16: 0.0067100048 | AS16: 0.00074590518 | AT16: 0.021810626 | AU16: 0.043899691 | AV16: 0.041191514 | AW16: 0.016445082 | AX16: 0.035745433 | AY16: 0.0022849622 | AZ16: 0.041394657 | BA16: 0.0555617 | BB16: 0.054833018 | BC16: 0.015637677 | BD16: 0.031068769 | BE16: 0.001486931 | BF16: 0.058658333 | BG16: 0.07594059 | BH16: 0.07117497 | BI16: 0.035172433 | BJ16: 0
... A39: LROW | B39: 0 | C39: 0 | D39: 0 | E39: 0 | F39: 0 | G39: 0 | H39: 0 | I39: 0 | J39: 0 | K39: 0 | L39: 0 | M39: 0 | N39: 0 | O39: 0 | P39: 0 | Q39: 0 | R39: 0 | S39: 0 | T39: 0 | U39: 0 | V39: 0 | W39: 0 | X39: 0 | Y39: 0 | Z39: 0 | AA39: 0 | AB39: 0 | AC39: 0 | AD39: 0 | AE39: 0 | AF39: 0 | AG39: 0 | AH39: 0 | AI39: 0 | AJ39: 0 | AK39: 0 | AL39: 0 | AM39: 0 | AN39: 0 | AO39: 0 | AP39: 0 | AQ39: 0 | AR39: 0 | AS39: 0 | AT39: 0 | AU39: 0 | AV39: 0 | AW39: 0 | AX39: 0 | AY39: 0 | AZ39: 0 | BA39: 0 | BB39: 0 | BC39: 0 | BD39: 0 | BE39: 0 | BF39: 0 | BG39: 0 | BH39: 0 | BI39: 0 | BJ39: 1

Sheet EXO_Share_Operating_surplus
B4: INCOME1_DENSE_SINGLE | C4: INCOME1_DENSE_SINGLEWCHILDREN | D4: INCOME1_DENSE_COUPLE | E4: INCOME1_DENSE_COUPLEWCHILDREN | F4: INCOME1_DENSE_OTHER | G4: INCOME1_DENSE_OTHERWCHILDREN | H4: INCOME1_SPARSE_SINGLE | I4: INCOME1_SPARSE_SINGLEWCHILDREN | J4: INCOME1_SPARSE_COUPLE | K4: INCOME1_SPARSE_COUPLEWCHILDREN | L4: INCOME1_SPARSE_OTHER | M4: INCOME1_SPARSE_OTHERWCHILDREN | N4: INCOME2_DENSE_SINGLE | O4: INCOME2_DENSE_SINGLEWCHILDREN | P4: INCOME2_DENSE_COUPLE | Q4: INCOME2_DENSE_COUPLEWCHILDREN | R4: INCOME2_DENSE_OTHER | S4: INCOME2_DENSE_OTHERWCHILDREN | T4: INCOME2_SPARSE_SINGLE | U4: INCOME2_SPARSE_SINGLEWCHILDREN | V4: INCOME2_SPARSE_COUPLE | W4: INCOME2_SPARSE_COUPLEWCHILDREN | X4: INCOME2_SPARSE_OTHER | Y4: INCOME2_SPARSE_OTHERWCHILDREN | Z4: INCOME3_DENSE_SINGLE | AA4: INCOME3_DENSE_SINGLEWCHILDREN | AB4: INCOME3_DENSE_COUPLE | AC4: INCOME3_DENSE_COUPLEWCHILDREN | AD4: INCOME3_DENSE_OTHER | AE4: INCOME3_DENSE_OTHERWCHILDREN | AF4: INCOME3_SPARSE_SINGLE | AG4: INCOME3_SPARSE_SINGLEWCHILDREN | AH4: INCOME3_SPARSE_COUPLE | AI4: INCOME3_SPARSE_COUPLEWCHILDREN | AJ4: INCOME3_SPARSE_OTHER | AK4: INCOME3_SPARSE_OTHERWCHILDREN | AL4: INCOME4_DENSE_SINGLE | AM4: INCOME4_DENSE_SINGLEWCHILDREN | AN4: INCOME4_DENSE_COUPLE | AO4: INCOME4_DENSE_COUPLEWCHILDREN | AP4: INCOME4_DENSE_OTHER | AQ4: INCOME4_DENSE_OTHERWCHILDREN | AR4: INCOME4_SPARSE_SINGLE | AS4: INCOME4_SPARSE_SINGLEWCHILDREN | AT4: INCOME4_SPARSE_COUPLE | AU4: INCOME4_SPARSE_COUPLEWCHILDREN | AV4: INCOME4_SPARSE_OTHER | AW4: INCOME4_SPARSE_OTHERWCHILDREN | AX4: INCOME5_DENSE_SINGLE | AY4: INCOME5_DENSE_SINGLEWCHILDREN | AZ4: INCOME5_DENSE_COUPLE | BA4: INCOME5_DENSE_COUPLEWCHILDREN | BB4: INCOME5_DENSE_OTHER | BC4: INCOME5_DENSE_OTHERWCHILDREN | BD4: INCOME5_SPARSE_SINGLE | BE4: INCOME5_SPARSE_SINGLEWCHILDREN | BF4: INCOME5_SPARSE_COUPLE | BG4: INCOME5_SPARSE_COUPLEWCHILDREN | BH4: INCOME5_SPARSE_OTHER | BI4: INCOME5_SPARSE_OTHERWCHILDREN | BJ4: REPRESENTATIVE_HOUSEHOLD
A5: AUT | B5: 0 | C5: 0 | D5: 0 | E5: 0 | F5: 0 | G5: 0 | H5: 0 | I5: 0 | J5: 0 | K5: 0 | L5: 0 | M5: 0 | N5: 0 | O5: 0 | P5: 0 | Q5: 0 | R5: 0 | S5: 0 | T5: 0 | U5: 0 | V5: 0 | W5: 0 | X5: 0 | Y5: 0 | Z5: 0 | AA5: 0 | AB5: 0 | AC5: 0 | AD5: 0 | AE5: 0 | AF5: 0 | AG5: 0 | AH5: 0 | AI5: 0 | AJ5: 0 | AK5: 0 | AL5: 0 | AM5: 0 | AN5: 0 | AO5: 0 | AP5: 0 | AQ5: 0 | AR5: 0 | AS5: 0 | AT5: 0 | AU5: 0 | AV5: 0 | AW5: 0 | AX5: 0 | AY5: 0 | AZ5: 0 | BA5: 0 | BB5: 0 | BC5: 0 | BD5: 0 | BE5: 0 | BF5: 0 | BG5: 0 | BH5: 0 | BI5: 0 | BJ5: 1
A6: BEL | B6: 0.0083551025 | C6: 0.0011306202 | D6: 0.0065648042 | E6: 0.0036297312 | F6: 0.0024910007 | G6: 0.0017500135 | H6: 0.017707382 | I6: 0.002222177 | J6: 0.028186601 | K6: 0.014972284 | L6: 0.016242453 | M6: 0.0063956917 | N6: 0.011354643 | O6: 0.0018035015 | P6: 0.0082856768 | Q6: 0.0063053888 | R6: 0.0047875698 | S6: 0.0015452067 | T6: 0.02363949 | U6: 0.0027949216 | V6: 0.03718866 | W6: 0.026262708 | X6: 0.019386187 | Y6: 0.0076673649 | Z6: 0.011710327 | AA6: 0.0017533383 | AB6: 0.013326978 | AC6: 0.0094257869 | AD6: 0.0058915642 | AE6: 0.0021364612 | AF6: 0.027444719 | AG6: 0.0022390982 | AH6: 0.042170157 | AI6: 0.029260586 | AJ6: 0.023475491 | AK6: 0.0096392799 | AL6: 0.021437158 | AM6: 0.0017411553 | AN6: 0.014584924 | AO6: 0.01258837 | AP6: 0.0068344325 | AQ6: 0.0023631547 | AR6: 0.032766671 | AS6: 0.0034523049 | AT6: 0.051732602 | AU6: 0.032757887 | AV6: 0.026819533 | AW6: 0.010755816 | AX6: 0.033868706 | AY6: 0.0024062402 | AZ6: 0.027835746 | BA6: 0.01731028 | BB6: 0.011492558 | BC6: 0.0069639951 | BD6: 0.049208108 | BE6: 0.004663112 | BF6: 0.088066015 | BG6: 0.042240324 | BH6: 0.044414875 | BI6: 0.014553069 | BJ6: 0
A7: BGR | B7: 0.019858974 | C7: 0 | D7: 0.022431858 | E7: 0.014487891 | F7: 0.016714898 | G7: 0.0073443849 | H7: 0.011680575 | I7: 0 | J7: 0.014478745 | K7: 0.0062631284 | L7: 0.014035867 | M7: 0.0066618943 | N7: 0.026562502 | O7: 0 | P7: 0.029024386 | Q7: 0.016345016 | R7: 0.021983352 | S7: 0.0061371788 | T7: 0.015181881 | U7: 0 | V7: 0.020013175 | W7: 0.0077140271 | X7: 0.015860233 | Y7: 0.0076685585 | Z7: 0.032521052 | AA7: 0.00057322135 | AB7: 0.029474323 | AC7: 0.017598163 | AD7: 0.024143459 | AE7: 0.0069686201 | AF7: 0.0214748 | AG7: 0 | AH7: 0.02414164 | AI7: 0.0094661207 | AJ7: 0.018110958 | AK7: 0.0092632689 | AL7: 0.031633594 | AM7: 0.0025551122 | AN7: 0.029668112 | AO7: 0.018636832 | AP7: 0.022498161 | AQ7: 0.008900377 | AR7: 0.023738489 | AS7: 5.1679208e-05 | AT7: 0.027988115 | AU7: 0.0132464 | AV7: 0.019388625 | AW7: 0.011334955 | AX7: 0.041854737 | AY7: 0.005708363 | AZ7: 0.039648456 | BA7: 0.023560139 | BB7: 0.037961281 | BC7: 0.010833623 | BD7: 0.031310577 | BE7: 0.0053808672 | BF7: 0.038243892 | BG7: 0.016078773 | BH7: 0.028279952 | BI7: 0.017314737 | BJ7: 0
A8: HRV | B8: 0.0082134909 | C8: 0.00023400268 | D8: 0.0099754624 | E8: 0.0035823401 | F8: 0.0088265724 | G8: 0.0061396715 | H8: 0.012060794 | I8: 0 | J8: 0.014710829 | K8: 0.0091925264 | L8: 0.017589512 | M8: 0.0087254907 | N8: 0.0098194094 | O8: 0.00054658843 | P8: 0.010136705 | Q8: 0.0058312052 | R8: 0.01043724 | S8: 0.0063166096 | T8: 0.011482661 | U8: 0 | V8: 0.016452069 | W8: 0.011422187 | X8: 0.022245998 | Y8: 0.012542864 | Z8: 0.013506175 | AA8: 0.0011212368 | AB8: 0.011349254 | AC8: 0.0072328938 | AD8: 0.012008258 | AE8: 0.0068409249 | AF8: 0.013830635 | AG8: 0 | AH8: 0.020090525 | AI8: 0.011566308 | AJ8: 0.02534438 | AK8: 0.013525852 | AL8: 0.016424767 | AM8: 0.0011314338 | AN8: 0.016449899 | AO8: 0.0054903409 | AP8: 0.015531744 | AQ8: 0.0046923274 | AR8: 0.016743762 | AS8: 1.8261857e-05 | AT8: 0.028293815 | AU8: 0.013678205 | AV8: 0.041225407 | AW8: 0.015444455 | AX8: 0.04092457 | AY8: 0.0017578737 | AZ8: 0.024831821 | BA8: 0.026843585 | BB8: 0.041213095 | BC8: 0.0088401122 | BD8: 0.059555653 | BE8: 0.0020575432 | BF8: 0.096674034 | BG8: 0.047613179 | BH8: 0.075276227 | BI8: 0.046387217 | BJ8: 0
A9: CYP | B9: 0.0088129517 | C9: 0.0010344982 | D9: 0.018620905 | E9: 0.0090232088 | F9: 0.013249302 | G9: 0.004267978 | H9: 0.0054734112 | I9: 0.00027237666 | J9: 0.017270723 | K9: 0.010024819 | L9: 0.013811208 | M9: 0.0087566822 | N9: 0.013654294 | O9: 0.0017371619 | P9: 0.022959535 | Q9: 0.012793866 | R9: 0.018208412 | S9: 0.008534152 | T9: 0.007545715 | U9: 0.00060504576 | V9: 0.019673682 | W9: 0.019504055 | X9: 0.015845202 | Y9: 0.012039425 | Z9: 0.01598947 | AA9: 0.0016299644 | AB9: 0.028373303 | AC9: 0.018025308 | AD9: 0.020830239 | AE9: 0.010523345 | AF9: 0.0097122953 | AG9: 0.0011363113 | AH9: 0.024333933 | AI9: 0.022623794 | AJ9: 0.019524169 | AK9: 0.011568118 | AL9: 0.019851013 | AM9: 0.0015644149 | AN9: 0.037737538 | AO9: 0.022552918 | AP9: 0.02388968 | AQ9: 0.012359886 | AR9: 0.010166309 | AS9: 0.00091060048 | AT9: 0.030274047 | AU9: 0.021497588 | AV9: 0.021062942 | AW9: 0.014227572 | AX9: 0.032030216 | AY9: 0.0024208227 | AZ9: 0.061056632 | BA9: 0.02854563 | BB9: 0.046556109 | BC9: 0.017241964 | BD9: 0.016106427 | BE9: 0.0023059325 | BF9: 0.051641925 | BG9: 0.027808643 | BH9: 0.032744185 | BI9: 0.017458146 | BJ9: 0
A10: CZE | B10: 0.0061714543 | C10: 0 | D10: 0.0074629144 | E10: 0.0038838321 | F10: 0.0037967678 | G10: 0.0025406327 | H10: 0.0079974284 | I10: 0 | J10: 0.016377602 | K10: 0.0087667291 | L10: 0.013487899 | M10: 0.0040796772 | N10: 0.0089847767 | O10: 0 | P10: 0.0099108366 | Q10: 0.0053044814 | R10: 0.0043758143 | S10: 0.0040813564 | T10: 0.010463445 | U10: 0 | V10: 0.022090421 | W10: 0.012798728 | X10: 0.015502828 | Y10: 0.0082950505 | Z10: 0.011513217 | AA10: 0.00020338384 | AB10: 0.013101782 | AC10: 0.00816047 | AD10: 0.0053808082 | AE10: 0.0038944918 | AF10: 0.01438844 | AG10: 0 | AH10: 0.024874361 | AI10: 0.014280044 | AJ10: 0.017257462 | AK10: 0.0092523522 | AL10: 0.010388172 | AM10: 0.00081173376 | AN10: 0.014629831 | AO10: 0.010105424 | AP10: 0.007210106 | AQ10: 0.0065468586 | AR10: 0.016089689 | AS10: 5.3638821e-05 | AT10: 0.029342474 | AU10: 0.015291966 | AV10: 0.022301937 | AW10: 0.0081230405 | AX10: 0.056663862 | AY10: 0.0018936491 | AZ10: 0.076162876 | BA10: 0.037923969 | BB10: 0.056708466 | BC10: 0.0076512168 | BD10: 0.054973338 | BE10: 0.0054938902 | BF10: 0.1029621 | BG10: 0.078144563 | BH10: 0.059595809 | BI10: 0.022251899 | BJ10: 0
A11: DNK | B11: 0.0047261996 | C11: 0 | D11: 0.0064999473 | E11: 0.006080203 | F11: 0.0017821635 | G11: 0.0015563634 | H11: 0.021557858 | I11: 0.00097145276 | J11: 0.03911691 | K11: 0.022199525 | L11: 0.012244517 | M11: 0.0097566638 | N11: 0.0095771515 | O11: 0 | P11: 0.008393326 | Q11: 0.010540941 | R11: 0.0034451951 | S11: 0.0034551863 | T11: 0.028644742 | U11: 0.0015460266 | V11: 0.038429788 | W11: 0.026551931 | X11: 0.01028568 | Y11: 0.0052782595 | Z11: 0.014112059 | AA11: 0.00022293824 | AB11: 0.015656978 | AC11: 0.0097859709 | AD11: 0.0041383119 | AE11: 0.0048453346 | AF11: 0.02448363 | AG11: 0.0010090475 | AH11: 0.045119073 | AI11: 0.025167644 | AJ11: 0.011885237 | AK11: 0.0072212278 | AL11: 0.025411677 | AM11: 0.0013308959 | AN11: 0.023559969 | AO11: 0.019793208 | AP11: 0.0049196441 | AQ11: 0.0050521071 | AR11: 0.026869576 | AS11: 0.0017815653 | AT11: 0.057005015 | AU11: 0.035843864 | AV11: 0.012363111 | AW11: 0.0088170367 | AX11: 0.042219768 | AY11: 0.0025757173 | AZ11: 0.042848845 | BA11: 0.017153695 | BB11: 0.0083966986 | BC11: 0.0069471593 | BD11: 0.054876368 | BE11: 0.0022203514 | BF11: 0.085894075 | BG11: 0.043586361 | BH11: 0.020549385 | BI11: 0.013696426 | BJ11: 0
A12: EST | B12: 0.035544409 | C12: 0 | D12: 0.033029353 | E12: 0.018020629 | F12: 0.01344236 | G12: 0.0096383702 | H12: 0.01254798 | I12: 0 | J12: 0.010172404 | K12: 0.0061019087 | L12: 0.0070199566 | M12: 0.003992006 | N12: 0.030162262 | O12: 0 | P12: 0.026915924 | Q12: 0.025341637 | R12: 0.018279371 | S12: 0.0093386317 | T12: 0.0094543664 | U12: 0 | V12: 0.011838637 | W12: 0.0084373089 | X12: 0.0065760247 | Y12: 0.004334364 | Z12: 0.027822059 | AA12: 0.00075482914 | AB12: 0.032378576 | AC12: 0.026045462 | AD12: 0.021191035 | AE12: 0.010112247 | AF12: 0.009596486 | AG12: 0 | AH12: 0.012494321 | AI12: 0.012732859 | AJ12: 0.007475054 | AK12: 0.0055169705 | AL12: 0.029665047 | AM12: 0.0031594134 | AN12: 0.035115032 | AO12: 0.032619907 | AP12: 0.021408338 | AQ12: 0.011021822 | AR12: 0.010979726 | AS12: 6.9873311e-05 | AT12: 0.013468021 | AU12: 0.010499846 | AV12: 0.0080474896 | AW12: 0.0063264307 | AX12: 0.054475534 | AY12: 0.0068795146 | AZ12: 0.063498106 | BA12: 0.051491523 | BB12: 0.028642048 | BC12: 0.027574173 | BD12: 0.034802588 | BE12: 0.0068585177 | BF12: 0.024646165 | BG12: 0.02221361 | BH12: 0.019939112 | BI12: 0.01029036 | BJ12: 0
A13: FIN | B13: 0.0070066396 | C13: 0.00088709299 | D13: 0.0062595505 | E13: 0.0072006697 | F13: 0.0035357675 | G13: 0.0018430075 | H13: 0.010068499 | I13: 0.0010151035 | J13: 0.025297862 | K13: 0.017447765 | L13: 0.0076547199 | M13: 0.0058955914 | N13: 0.012429344 | O13: 0.0014641376 | P13: 0.016124821 | Q13: 0.010596765 | R13: 0.0047208976 | S13: 0.0030435956 | T13: 0.018628033 | U13: 0.0012390168 | V13: 0.038689324 | W13: 0.020584262 | X13: 0.0090304335 | Y13: 0.0069039622 | Z13: 0.018372771 | AA13: 0.001392162 | AB13: 0.023926748 | AC13: 0.014185872 | AD13: 0.0055847801 | AE13: 0.0034572398 | AF13: 0.023483333 | AG13: 0.0010947254 | AH13: 0.046269461 | AI13: 0.025263489 | AJ13: 0.010604545 | AK13: 0.0083848151 | AL13: 0.023630924 | AM13: 0.001410098 | AN13: 0.034442895 | AO13: 0.018802941 | AP13: 0.0067466538 | AQ13: 0.004457734 | AR13: 0.031327239 | AS13: 0.0015419973 | AT13: 0.055203238 | AU13: 0.024327824 | AV13: 0.011455974 | AW13: 0.0083033131 | AX13: 0.048065743 | AY13: 0.0018770307 | AZ13: 0.06123722 | BA13: 0.026438682 | BB13: 0.015296471 | BC13: 0.0070558159 | BD13: 0.051870275 | BE13: 0.0021893205 | BF13: 0.077620557 | BG13: 0.03758286 | BH13: 0.016966677 | BI13: 0.012561713 | BJ13: 0
A14: FRA | B14: 0.0090410928 | C14: 0.00066454967 | D14: 0.0092168655 | E14: 0.0047757996 | F14: 0.0039370706 | G14: 0.0022411006 | H14: 0.011165993 | I14: 0.00074476247 | J14: 0.017001792 | K14: 0.0077721463 | L14: 0.0070721695 | M14: 0.0036152381 | N14: 0.011233282 | O14: 0.0017989431 | P14: 0.016055452 | Q14: 0.011271802 | R14: 0.0051870245 | S14: 0.0024223196 | T14: 0.014058867 | U14: 0.00083684625 | V14: 0.023533325 | W14: 0.015730084 | X14: 0.0096180412 | Y14: 0.0053039426 | Z14: 0.016805987 | AA14: 0.0011407668 | AB14: 0.026123781 | AC14: 0.017431456 | AD14: 0.0085881803 | AE14: 0.0040450289 | AF14: 0.016957873 | AG14: 0.0019489189 | AH14: 0.031577427 | AI14: 0.019148895 | AJ14: 0.0097088738 | AK14: 0.0064068713 | AL14: 0.031242909 | AM14: 0.0012576977 | AN14: 0.038215124 | AO14: 0.020663919 | AP14: 0.0090983549 | AQ14: 0.0054203163 | AR14: 0.026402547 | AS14: 0.0019258374 | AT14: 0.040940043 | AU14: 0.022278525 | AV14: 0.013467201 | AW14: 0.0073329829 | AX14: 0.070552175 | AY14: 0.0034594935 | AZ14: 0.091356079 | BA14: 0.032707086 | BB14: 0.021553321 | BC14: 0.0077634277 | BD14: 0.051789265 | BE14: 0.0039452293 | BF14: 0.074768763 | BG14: 0.03363374 | BH14: 0.022524393 | BI14: 0.013519002 | BJ14: 0
A15: DEU | B15: 0 | C15: 0 | D15: 0.00085027345 | E15: 0.00056970329 | F15: 0.00014783453 | G15: 0 | H15: 0.00067532616 | I15: 0 | J15: 0.0015309158 | K15: 0.00053821528 | L15: 0.0013509354 | M15: 0.00058827143 | N15: 0.00021110842 | O15: 0 | P15: 0.00069834965 | Q15: 0.00033110793 | R15: 0.0011039471 | S15: 0.00049978916 | T15: 0.00085461898 | U15: 0 | V15: 0.0029540832 | W15: 0.0016350744 | X15: 0.0022250115 | Y15: 0.00070576917 | Z15: 0.0014843849 | AA15: 7.4261179e-05 | AB15: 0.0054903298 | AC15: 0.0014855744 | AD15: 0.0016214918 | AE15: 0.00036781187 | AF15: 0.0034516824 | AG15: 0 | AH15: 0.010958488 | AI15: 0.0041385014 | AJ15: 0.0042775558 | AK15: 6.3782555e-05 | AL15: 0.0052078931 | AM15: 0.00031273557 | AN15: 0.022282261 | AO15: 0.0034824476 | AP15: 0.0040409618 | AQ15: 8.6532787e-05 | AR15: 0.0087672671 | AS15: 2.4545728e-05 | AT15: 0.027290482 | AU15: 0.0072470245 | AV15: 0.0098533993 | AW15: 0.0016946185 | AX15: 0.10294427 | AY15: 0.00068631482 | AZ15: 0.20099117 | BA15: 0.01174294 | BB15: 0.024864298 | BC15: 0.00065775804 | BD15: 0.11898677 | BE15: 0.0022833523 | BF15: 0.20383684 | BG15: 0.039435521 | BH15: 0.13706191 | BI15: 0.015334482 | BJ15: 0
A16: GRC | B16: 0.010014194 | C16: 0.00061646839 | D16: 0.013612828 | E16: 0.0071285969 | F16: 0.012436223 | G16: 0.0020822272 | H16: 0.013574648 | I16: 0.00033565383 | J16: 0.025255783 | K16: 0.013864776 | L16: 0.021098768 | M16: 0.00676478 | N16: 0.015530864 | O16: 0.0010399018 | P16: 0.016551452 | Q16: 0.0080721112 | R16: 0.017782125 | S16: 0.0033227039 | T16: 0.019254601 | U16: 0.00026820962 | V16: 0.028980535 | W16: 0.014672311 | X16: 0.022979809 | Y16: 0.0080899126 | Z16: 0.016649738 | AA16: 0.0010450238 | AB16: 0.020828083 | AC16: 0.013374147 | AD16: 0.018551563 | AE16: 0.0032752836 | AF16: 0.018759928 | AG16: 0.00074077009 | AH16: 0.032148321 | AI16: 0.018243475 | AJ16: 0.024884741 | AK16: 0.0080141973 | AL16: 0.016538204 | AM16: 0.00097703279 | AN16: 0.024454192 | AO16: 0.013709527 | AP16: 0.024363301 | AQ16: 0.0054894721 | AR16: 0.022863415 | AS16: 0.00081543306 | AT16: 0.037221157 | AU16: 0.020270287 | AV16: 0.03149974 | AW16: 0.010080062 | AX16: 0.033385751 | AY16: 0.001380705 | AZ16: 0.040148069 | BA16: 0.022674293 | BB16: 0.037600018 | BC16: 0.0061653859 | BD16: 0.032087332 | BE16: 0.0013637026 | BF16: 0.064156062 | BG16: 0.029907598 | BH16: 0.049349707 | BI16: 0.013654801 | BJ16: 0
... A39: LROW | B39: 0 | C39: 0 | D39: 0 | E39: 0 | F39: 0 | G39: 0 | H39: 0 | I39: 0 | J39: 0 | K39: 0 | L39: 0 | M39: 0 | N39: 0 | O39: 0 | P39: 0 | Q39: 0 | R39: 0 | S39: 0 | T39: 0 | U39: 0 | V39: 0 | W39: 0 | X39: 0 | Y39: 0 | Z39: 0 | AA39: 0 | AB39: 0 | AC39: 0 | AD39: 0 | AE39: 0 | AF39: 0 | AG39: 0 | AH39: 0 | AI39: 0 | AJ39: 0 | AK39: 0 | AL39: 0 | AM39: 0 | AN39: 0 | AO39: 0 | AP39: 0 | AQ39: 0 | AR39: 0 | AS39: 0 | AT39: 0 | AU39: 0 | AV39: 0 | AW39: 0 | AX39: 0 | AY39: 0 | AZ39: 0 | BA39: 0 | BB39: 0 | BC39: 0 | BD39: 0 | BE39: 0 | BF39: 0 | BG39: 0 | BH39: 0 | BI39: 0 | BJ39: 1

Sheet EXO_Share_Social_benefits
B4: INCOME1_DENSE_SINGLE | C4: INCOME1_DENSE_SINGLEWCHILDREN | D4: INCOME1_DENSE_COUPLE | E4: INCOME1_DENSE_COUPLEWCHILDREN | F4: INCOME1_DENSE_OTHER | G4: INCOME1_DENSE_OTHERWCHILDREN | H4: INCOME1_SPARSE_SINGLE | I4: INCOME1_SPARSE_SINGLEWCHILDREN | J4: INCOME1_SPARSE_COUPLE | K4: INCOME1_SPARSE_COUPLEWCHILDREN | L4: INCOME1_SPARSE_OTHER | M4: INCOME1_SPARSE_OTHERWCHILDREN | N4: INCOME2_DENSE_SINGLE | O4: INCOME2_DENSE_SINGLEWCHILDREN | P4: INCOME2_DENSE_COUPLE | Q4: INCOME2_DENSE_COUPLEWCHILDREN | R4: INCOME2_DENSE_OTHER | S4: INCOME2_DENSE_OTHERWCHILDREN | T4: INCOME2_SPARSE_SINGLE | U4: INCOME2_SPARSE_SINGLEWCHILDREN | V4: INCOME2_SPARSE_COUPLE | W4: INCOME2_SPARSE_COUPLEWCHILDREN | X4: INCOME2_SPARSE_OTHER | Y4: INCOME2_SPARSE_OTHERWCHILDREN | Z4: INCOME3_DENSE_SINGLE | AA4: INCOME3_DENSE_SINGLEWCHILDREN | AB4: INCOME3_DENSE_COUPLE | AC4: INCOME3_DENSE_COUPLEWCHILDREN | AD4: INCOME3_DENSE_OTHER | AE4: INCOME3_DENSE_OTHERWCHILDREN | AF4: INCOME3_SPARSE_SINGLE | AG4: INCOME3_SPARSE_SINGLEWCHILDREN | AH4: INCOME3_SPARSE_COUPLE | AI4: INCOME3_SPARSE_COUPLEWCHILDREN | AJ4: INCOME3_SPARSE_OTHER | AK4: INCOME3_SPARSE_OTHERWCHILDREN | AL4: INCOME4_DENSE_SINGLE | AM4: INCOME4_DENSE_SINGLEWCHILDREN | AN4: INCOME4_DENSE_COUPLE | AO4: INCOME4_DENSE_COUPLEWCHILDREN | AP4: INCOME4_DENSE_OTHER | AQ4: INCOME4_DENSE_OTHERWCHILDREN | AR4: INCOME4_SPARSE_SINGLE | AS4: INCOME4_SPARSE_SINGLEWCHILDREN | AT4: INCOME4_SPARSE_COUPLE | AU4: INCOME4_SPARSE_COUPLEWCHILDREN | AV4: INCOME4_SPARSE_OTHER | AW4: INCOME4_SPARSE_OTHERWCHILDREN | AX4: INCOME5_DENSE_SINGLE | AY4: INCOME5_DENSE_SINGLEWCHILDREN | AZ4: INCOME5_DENSE_COUPLE | BA4: INCOME5_DENSE_COUPLEWCHILDREN | BB4: INCOME5_DENSE_OTHER | BC4: INCOME5_DENSE_OTHERWCHILDREN | BD4: INCOME5_SPARSE_SINGLE | BE4: INCOME5_SPARSE_SINGLEWCHILDREN | BF4: INCOME5_SPARSE_COUPLE | BG4: INCOME5_SPARSE_COUPLEWCHILDREN | BH4: INCOME5_SPARSE_OTHER | BI4: INCOME5_SPARSE_OTHERWCHILDREN | BJ4: REPRESENTATIVE_HOUSEHOLD
A5: AUT | B5: 0 | C5: 0 | D5: 0 | E5: 0 | F5: 0 | G5: 0 | H5: 0 | I5: 0 | J5: 0 | K5: 0 | L5: 0 | M5: 0 | N5: 0 | O5: 0 | P5: 0 | Q5: 0 | R5: 0 | S5: 0 | T5: 0 | U5: 0 | V5: 0 | W5: 0 | X5: 0 | Y5: 0 | Z5: 0 | AA5: 0 | AB5: 0 | AC5: 0 | AD5: 0 | AE5: 0 | AF5: 0 | AG5: 0 | AH5: 0 | AI5: 0 | AJ5: 0 | AK5: 0 | AL5: 0 | AM5: 0 | AN5: 0 | AO5: 0 | AP5: 0 | AQ5: 0 | AR5: 0 | AS5: 0 | AT5: 0 | AU5: 0 | AV5: 0 | AW5: 0 | AX5: 0 | AY5: 0 | AZ5: 0 | BA5: 0 | BB5: 0 | BC5: 0 | BD5: 0 | BE5: 0 | BF5: 0 | BG5: 0 | BH5: 0 | BI5: 0 | BJ5: 1
A6: BEL | B6: 0.014169896 | C6: 0.0022199486 | D6: 0.010550765 | E6: 0.0074702124 | F6: 0.0054033365 | G6: 0.0045631088 | H6: 0.025882345 | I6: 0.0031586347 | J6: 0.048853392 | K6: 0.012718011 | L6: 0.014765825 | M6: 0.0091334123 | N6: 0.02224699 | O6: 0.0025814181 | P6: 0.018665548 | Q6: 0.0068937126 | R6: 0.0053319646 | S6: 0.0027476823 | T6: 0.035440017 | U6: 0.0045038442 | V6: 0.067948825 | W6: 0.012653529 | X6: 0.016127644 | Y6: 0.0074835742 | Z6: 0.022136902 | AA6: 0.0023729628 | AB6: 0.021437609 | AC6: 0.0045959719 | AD6: 0.0049980683 | AE6: 0.0023174083 | AF6: 0.039101281 | AG6: 0.0028470186 | AH6: 0.066514519 | AI6: 0.0085197052 | AJ6: 0.018273412 | AK6: 0.0064702567 | AL6: 0.02068891 | AM6: 0.0015109039 | AN6: 0.022546116 | AO6: 0.0041075821 | AP6: 0.0097085028 | AQ6: 0.0012665092 | AR6: 0.037196642 | AS6: 0.0024012803 | AT6: 0.067593339 | AU6: 0.0072239507 | AV6: 0.016985834 | AW6: 0.0040728465 | AX6: 0.022740366 | AY6: 0.0014556507 | AZ6: 0.026504823 | BA6: 0.0048521402 | BB6: 0.010427548 | BC6: 0.0021670335 | BD6: 0.043185955 | BE6: 0.0031565597 | BF6: 0.095499664 | BG6: 0.011653415 | BH6: 0.015150014 | BI6: 0.0068056626 | BJ6: 0
A7: BGR | B7: 0.0168405 | C7: 0.00040800892 | D7: 0.022818057 | E7: 0.0040591066 | F7: 0.012526948 | G7: 0.0032035227 | H7: 0.015389122 | I7: 0.00032848009 | J7: 0.027175077 | K7: 0.0057620808 | L7: 0.01262257 | M7: 0.0086149563 | N7: 0.025590589 | O7: 0.0004567608 | P7: 0.034552306 | Q7: 0.0086776041 | R7: 0.020257416 | S7: 0.0074312267 | T7: 0.02490127 | U7: 0.0003432667 | V7: 0.044194177 | W7: 0.0054852293 | X7: 0.023221794 | Y7: 0.011372789 | Z7: 0.027824001 | AA7: 0.00037673158 | AB7: 0.043181632 | AC7: 0.0054611582 | AD7: 0.024742632 | AE7: 0.0064884531 | AF7: 0.029497866 | AG7: 0.00021983135 | AH7: 0.048366746 | AI7: 0.0047429169 | AJ7: 0.019899135 | AK7: 0.014839801 | AL7: 0.023293513 | AM7: 0.00037365892 | AN7: 0.031165287 | AO7: 0.003926643 | AP7: 0.022156357 | AQ7: 0.0080204758 | AR7: 0.031101029 | AS7: 0.00017927639 | AT7: 0.045842571 | AU7: 0.0080353007 | AV7: 0.022954432 | AW7: 0.013437841 | AX7: 0.018931239 | AY7: 0.00022161491 | AZ7: 0.038113207 | BA7: 0.0098002204 | BB7: 0.024049637 | BC7: 0.0057777176 | BD7: 0.031288571 | BE7: 0.00042752649 | BF7: 0.052665242 | BG7: 0.0051911899 | BH7: 0.027940506 | BI7: 0.01323318 | BJ7: 0
A8: HRV | B8: 0.0072130923 | C8: 9.5073951e-05 | D8: 0.01551007 | E8: 0.0036736515 | F8: 0.013263384 | G8: 0.0033725667 | H8: 0.010682101 | I8: 0.00024607199 | J8: 0.025674993 | K8: 0.013496179 | L8: 0.029147896 | M8: 0.019715602 | N8: 0.016328268 | O8: 0.00023152444 | P8: 0.024419472 | Q8: 0.002769284 | R8: 0.014233408 | S8: 0.0048007099 | T8: 0.023299045 | U8: 0.00023735835 | V8: 0.044230376 | W8: 0.009374681 | X8: 0.031600951 | Y8: 0.022675524 | Z8: 0.018918575 | AA8: 0.00032274023 | AB8: 0.02868864 | AC8: 0.003597496 | AD8: 0.016630428 | AE8: 0.0058563913 | AF8: 0.03182024 | AG8: 0.0001466017 | AH8: 0.057909663 | AI8: 0.0090530091 | AJ8: 0.041861664 | AK8: 0.022223767 | AL8: 0.017347329 | AM8: 0.00020739798 | AN8: 0.027153663 | AO8: 0.0016654144 | AP8: 0.012626734 | AQ8: 0.0044605507 | AR8: 0.039389729 | AS8: 0.00013232803 | AT8: 0.059497532 | AU8: 0.0050786678 | AV8: 0.033005956 | AW8: 0.019305435 | AX8: 0.010809623 | AY8: 0.00014589799 | AZ8: 0.021318074 | BA8: 0.0035969264 | BB8: 0.012279284 | BC8: 0.0072404311 | BD8: 0.038152103 | BE8: 0.00034147536 | BF8: 0.057964522 | BG8: 0.0052166612 | BH8: 0.033126976 | BI8: 0.016616793 | BJ8: 0
A9: CYP | B9: 0.0083943291 | C9: 0.00038852063 | D9: 0.024615622 | E9: 0.0091174442 | F9: 0.01464607 | G9: 0.0032487592 | H9: 0.004355093 | I9: 0.00089444172 | J9: 0.018524039 | K9: 0.011575048 | L9: 0.011398868 | M9: 0.0072899143 | N9: 0.017908049 | O9: 0.00077177789 | P9: 0.040826812 | Q9: 0.0057868651 | R9: 0.011159865 | S9: 0.0049147775 | T9: 0.0083026932 | U9: 0.0020515552 | V9: 0.032013484 | W9: 0.0083852435 | X9: 0.011007406 | Y9: 0.0083241091 | Z9: 0.013975502 | AA9: 0.00071472929 | AB9: 0.037964033 | AC9: 0.0061376882 | AD9: 0.01143023 | AE9: 0.0049873865 | AF9: 0.01073551 | AG9: 0.001231911 | AH9: 0.029553156 | AI9: 0.0069880587 | AJ9: 0.01074293 | AK9: 0.0080321926 | AL9: 0.010799543 | AM9: 0.00094634459 | AN9: 0.065335737 | AO9: 0.0035789302 | AP9: 0.026839832 | AQ9: 0.0032902661 | AR9: 0.011076956 | AS9: 0.00093512613 | AT9: 0.04179537 | AU9: 0.0065357113 | AV9: 0.012574569 | AW9: 0.005038665 | AX9: 0.034105779 | AY9: 0.0014977547 | AZ9: 0.1441378 | BA9: 0.0060943558 | BB9: 0.065713826 | BC9: 0.01015054 | BD9: 0.021920184 | BE9: 0.00069819158 | BF9: 0.076095739 | BG9: 0.0041534387 | BH9: 0.027117565 | BI9: 0.011173662 | BJ9: 0
A10: CZE | B10: 0.016966427 | C10: 0.00049933591 | D10: 0.019878609 | E10: 0.0074138232 | F10: 0.0075955765 | G10: 0.0018805808 | H10: 0.023237799 | I10: 0.0015489087 | J10: 0.055415945 | K10: 0.016040776 | L10: 0.01494459 | M10: 0.0077249525 | N10: 0.026103699 | O10: 0.0010056384 | P10: 0.044038601 | Q10: 0.0062576973 | R10: 0.0070518731 | S10: 0.001213139 | T10: 0.037368866 | U10: 0.0016656983 | V10: 0.08499072 | W10: 0.011405166 | X10: 0.022567634 | Y10: 0.0066788924 | Z10: 0.025245019 | AA10: 0.00099176134 | AB10: 0.041961658 | AC10: 0.0051783241 | AD10: 0.0094165882 | AE10: 0.0026410111 | AF10: 0.040256764 | AG10: 0.00090632092 | AH10: 0.082570831 | AI10: 0.0089576983 | AJ10: 0.02375898 | AK10: 0.0075330089 | AL10: 0.018736629 | AM10: 0.0012915613 | AN10: 0.021754637 | AO10: 0.0047380858 | AP10: 0.0085700241 | AQ10: 0.0017491532 | AR10: 0.035299706 | AS10: 0.00082608004 | AT10: 0.062440259 | AU10: 0.007777666 | AV10: 0.024708917 | AW10: 0.0066908809 | AX10: 0.0098237736 | AY10: 0.0019507089 | AZ10: 0.019066298 | BA10: 0.0044103379 | BB10: 0.0040631712 | BC10: 0.0022426428 | BD10: 0.017713553 | BE10: 0.0019378777 | BF10: 0.0402531 | BG10: 0.0078662959 | BH10: 0.017782435 | BI10: 0.005393292 | BJ10: 0
A11: DNK | B11: 0.016989465 | C11: 0.0020313875 | D11: 0.016606528 | E11: 0.0071299881 | F11: 0.0026895611 | G11: 0.001924173 | H11: 0.034188718 | I11: 0.0034868875 | J11: 0.050680028 | K11: 0.011115104 | L11: 0.005061895 | M11: 0.0020733834 | N11: 0.031315529 | O11: 0.0028357294 | P11: 0.019932384 | Q11: 0.0071962864 | R11: 0.0025248084 | S11: 0.0012977188 | T11: 0.050417911 | U11: 0.0039557262 | V11: 0.06893432 | W11: 0.011007076 | X11: 0.0074011606 | Y11: 0.0041093296 | Z11: 0.040921302 | AA11: 0.0019542012 | AB11: 0.022307049 | AC11: 0.0056331847 | AD11: 0.001678344 | AE11: 0.0012271067 | AF11: 0.054801222 | AG11: 0.0031615901 | AH11: 0.057566442 | AI11: 0.010675493 | AJ11: 0.0046930216 | AK11: 0.0026118048 | AL11: 0.037546189 | AM11: 0.0017692113 | AN11: 0.019088763 | AO11: 0.0031725357 | AP11: 0.0033890976 | AQ11: 0.00058757786 | AR11: 0.054917297 | AS11: 0.0032990318 | AT11: 0.057399275 | AU11: 0.0077851723 | AV11: 0.0055879087 | AW11: 0.0025627534 | AX11: 0.041574305 | AY11: 0.001510998 | AZ11: 0.027351375 | BA11: 0.0022246162 | BB11: 0.0022964761 | BC11: 0.00098708371 | BD11: 0.06949388 | BE11: 0.0020188702 | BF11: 0.068663436 | BG11: 0.0073221084 | BH11: 0.0037959102 | BI11: 0.0035202679 | BJ11: 0
A12: EST | B12: 0.024586001 | C12: 0.0014315556 | D12: 0.044628649 | E12: 0.017774982 | F12: 0.016250868 | G12: 0.0091912875 | H12: 0.016542601 | I12: 0.0011921877 | J12: 0.027737325 | K12: 0.010596088 | L12: 0.012177645 | M12: 0.008075752 | N12: 0.049657483 | O12: 0.0016601893 | P12: 0.056403346 | Q12: 0.01393009 | R12: 0.014728824 | S12: 0.0086827173 | T12: 0.030448385 | U12: 0.0015275258 | V12: 0.042774257 | W12: 0.010386954 | X12: 0.012845477 | Y12: 0.0082080702 | Z12: 0.041888326 | AA12: 0.0014002092 | AB12: 0.036499307 | AC12: 0.019038984 | AD12: 0.015119728 | AE12: 0.0078380963 | AF12: 0.033057681 | AG12: 0.00070610952 | AH12: 0.031987906 | AI12: 0.01098263 | AJ12: 0.01139794 | AK12: 0.0093003571 | AL12: 0.019465069 | AM12: 0.0013040866 | AN12: 0.034909425 | AO12: 0.027478725 | AP12: 0.016081153 | AQ12: 0.0088135614 | AR12: 0.020607679 | AS12: 0.00073375088 | AT12: 0.022960335 | AU12: 0.012026959 | AV12: 0.011777129 | AW12: 0.0065603689 | AX12: 0.013593578 | AY12: 0.00075384105 | AZ12: 0.024566737 | BA12: 0.024802701 | BB12: 0.0146312 | BC12: 0.0064937505 | BD12: 0.013043309 | BE12: 0.0016495712 | BF12: 0.021212355 | BG12: 0.018934133 | BH12: 0.010626752 | BI12: 0.0063182974 | BJ12: 0
A13: FIN | B13: 0.017532014 | C13: 0.0023678797 | D13: 0.021355301 | E13: 0.012193153 | F13: 0.0034981092 | G13: 0.0025610019 | H13: 0.028904895 | I13: 0.0015315937 | J13: 0.047113699 | K13: 0.01766086 | L13: 0.0083471244 | M13: 0.0079433832 | N13: 0.029772513 | O13: 0.0028489712 | P13: 0.029727014 | Q13: 0.0080697726 | R13: 0.0032570717 | S13: 0.0016966999 | T13: 0.042292526 | U13: 0.0021193536 | V13: 0.07072058 | W13: 0.013554914 | X13: 0.0085020023 | Y13: 0.0041289984 | Z13: 0.028432192 | AA13: 0.0025614113 | AB13: 0.033824483 | AC13: 0.0067129864 | AD13: 0.0022527154 | AE13: 0.0012658436 | AF13: 0.04491917 | AG13: 0.001477525 | AH13: 0.066874302 | AI13: 0.010309504 | AJ13: 0.007900815 | AK13: 0.0037504379 | AL13: 0.02519312 | AM13: 0.0016634622 | AN13: 0.033708689 | AO13: 0.006038902 | AP13: 0.0043045627 | AQ13: 0.00070671045 | AR13: 0.04201665 | AS13: 0.0011384916 | AT13: 0.0633106 | AU13: 0.0088539513 | AV13: 0.0062548664 | AW13: 0.0021821083 | AX13: 0.033820298 | AY13: 0.001543668 | AZ13: 0.045550401 | BA13: 0.0056756842 | BB13: 0.0029505979 | BC13: 0.0012050954 | BD13: 0.03803766 | BE13: 0.0015731133 | BF13: 0.061432264 | BG13: 0.0077720076 | BH13: 0.0054024815 | BI13: 0.0016837979 | BJ13: 0
A14: FRA | B14: 0.014518991 | C14: 0.0033908201 | D14: 0.020567852 | E14: 0.011966495 | F14: 0.005800662 | G14: 0.0044981731 | H14: 0.017370514 | I14: 0.0020067047 | J14: 0.030039821 | K14: 0.013704757 | L14: 0.0064071908 | M14: 0.0050973522 | N14: 0.02025224 | O14: 0.002499372 | P14: 0.029999135 | Q14: 0.0067360325 | R14: 0.0068580618 | S14: 0.0036161498 | T14: 0.021571906 | U14: 0.002328221 | V14: 0.043260129 | W14: 0.0090846445 | X14: 0.0091531232 | Y14: 0.0039011191 | Z14: 0.027425888 | AA14: 0.001818239 | AB14: 0.039181057 | AC14: 0.0049710488 | AD14: 0.0067370316 | AE14: 0.0020806438 | AF14: 0.030262905 | AG14: 0.0017336416 | AH14: 0.050605811 | AI14: 0.0064126789 | AJ14: 0.0077953053 | AK14: 0.003603128 | AL14: 0.035401336 | AM14: 0.0014668565 | AN14: 0.046463983 | AO14: 0.0041710799 | AP14: 0.0070818691 | AQ14: 0.0018712639 | AR14: 0.034398588 | AS14: 0.0016227271 | AT14: 0.059934577 | AU14: 0.0061032605 | AV14: 0.010050049 | AW14: 0.0029218157 | AX14: 0.065306722 | AY14: 0.00068198026 | AZ14: 0.077912948 | BA14: 0.0034885714 | BB14: 0.0079177428 | BC14: 0.0011473036 | BD14: 0.050178401 | BE14: 0.00098013027 | BF14: 0.081413676 | BG14: 0.0070491837 | BH14: 0.011933641 | BI14: 0.0032454502 | BJ14: 0
A15: DEU | B15: 0.016594157 | C15: 0.0018348522 | D15: 0.02235248 | E15: 0.0064828309 | F15: 0.0033085387 | G15: 0.00082596804 | H15: 0.022183366 | I15: 0.0018434025 | J15: 0.042488938 | K15: 0.014010136 | L15: 0.010807368 | M15: 0.0045463087 | N15: 0.028121248 | O15: 0.0022300236 | P15: 0.037223826 | Q15: 0.0041824472 | R15: 0.0023404732 | S15: 0.001317409 | T15: 0.032782303 | U15: 0.0025076685 | V15: 0.060776861 | W15: 0.0098881409 | X15: 0.0092827061 | Y15: 0.0031383893 | Z15: 0.033623103 | AA15: 0.0019574653 | AB15: 0.035587772 | AC15: 0.0040907614 | AD15: 0.0035263032 | AE15: 0.00043867459 | AF15: 0.040065339 | AG15: 0.0024899773 | AH15: 0.061039958 | AI15: 0.0091936935 | AJ15: 0.0085485386 | AK15: 0.0026464178 | AL15: 0.030834845 | AM15: 0.001250145 | AN15: 0.035043086 | AO15: 0.0033312283 | AP15: 0.0031013502 | AQ15: 0.0005736487 | AR15: 0.034634991 | AS15: 0.0015471078 | AT15: 0.061479791 | AU15: 0.0094312731 | AV15: 0.0093363282 | AW15: 0.0026292607 | AX15: 0.042925904 | AY15: 0.0012107001 | AZ15: 0.05245346 | BA15: 0.0037174283 | BB15: 0.0045337899 | BC15: 0.00065034764 | BD15: 0.047834 | BE15: 0.00084509768 | BF15: 0.083083251 | BG15: 0.011383352 | BH15: 0.010589797 | BI15: 0.0033019721 | BJ15: 0
A16: GRC | B16: 0.0026013293 | C16: 0.00021063998 | D16: 0.013548232 | E16: 0.0038683903 | F16: 0.010825837 | G16: 0.0012799067 | H16: 0.0086001508 | I16: 0.00034585729 | J16: 0.028041096 | K16: 0.0055867377 | L16: 0.013115829 | M16: 0.0055954511 | N16: 0.017902745 | O16: 0.0002549016 | P16: 0.026573803 | Q16: 0.0029592328 | R16: 0.024214129 | S16: 0.0022975383 | T16: 0.021577998 | U16: 0.00027058218 | V16: 0.052527608 | W16: 0.0039611021 | X16: 0.02849749 | Y16: 0.0069951607 | Z16: 0.021718204 | AA16: 0.0002177706 | AB16: 0.03622055 | AC16: 0.002498369 | AD16: 0.027362972 | AE16: 0.003282631 | AF16: 0.029548556 | AG16: 0.00017270291 | AH16: 0.062628286 | AI16: 0.0040382325 | AJ16: 0.037904379 | AK16: 0.0064513944 | AL16: 0.024718284 | AM16: 0.00019154073 | AN16: 0.040290159 | AO16: 0.0017890407 | AP16: 0.029596828 | AQ16: 0.0024662659 | AR16: 0.033633163 | AS16: 0.00017280116 | AT16: 0.065987858 | AU16: 0.002671554 | AV16: 0.036164098 | AW16: 0.0091969546 | AX16: 0.019015663 | AY16: 0.00011351773 | AZ16: 0.037844527 | BA16: 0.0018015561 | BB16: 0.032750919 | BC16: 0.0014862067 | BD16: 0.024460954 | BE16: 0.00033616453 | BF16: 0.066880685 | BG16: 0.0038684202 | BH16: 0.04289645 | BI16: 0.0079705981 | BJ16: 0
... A39: LROW | B39: 0 | C39: 0 | D39: 0 | E39: 0 | F39: 0 | G39: 0 | H39: 0 | I39: 0 | J39: 0 | K39: 0 | L39: 0 | M39: 0 | N39: 0 | O39: 0 | P39: 0 | Q39: 0 | R39: 0 | S39: 0 | T39: 0 | U39: 0 | V39: 0 | W39: 0 | X39: 0 | Y39: 0 | Z39: 0 | AA39: 0 | AB39: 0 | AC39: 0 | AD39: 0 | AE39: 0 | AF39: 0 | AG39: 0 | AH39: 0 | AI39: 0 | AJ39: 0 | AK39: 0 | AL39: 0 | AM39: 0 | AN39: 0 | AO39: 0 | AP39: 0 | AQ39: 0 | AR39: 0 | AS39: 0 | AT39: 0 | AU39: 0 | AV39: 0 | AW39: 0 | AX39: 0 | AY39: 0 | AZ39: 0 | BA39: 0 | BB39: 0 | BC39: 0 | BD39: 0 | BE39: 0 | BF39: 0 | BG39: 0 | BH39: 0 | BI39: 0 | BJ39: 1

Sheet EXO_Tax_rate_Income
B4: INCOME1_DENSE_SINGLE | C4: INCOME1_DENSE_SINGLEWCHILDREN | D4: INCOME1_DENSE_COUPLE | E4: INCOME1_DENSE_COUPLEWCHILDREN | F4: INCOME1_DENSE_OTHER | G4: INCOME1_DENSE_OTHERWCHILDREN | H4: INCOME1_SPARSE_SINGLE | I4: INCOME1_SPARSE_SINGLEWCHILDREN | J4: INCOME1_SPARSE_COUPLE | K4: INCOME1_SPARSE_COUPLEWCHILDREN | L4: INCOME1_SPARSE_OTHER | M4: INCOME1_SPARSE_OTHERWCHILDREN | N4: INCOME2_DENSE_SINGLE | O4: INCOME2_DENSE_SINGLEWCHILDREN | P4: INCOME2_DENSE_COUPLE | Q4: INCOME2_DENSE_COUPLEWCHILDREN | R4: INCOME2_DENSE_OTHER | S4: INCOME2_DENSE_OTHERWCHILDREN | T4: INCOME2_SPARSE_SINGLE | U4: INCOME2_SPARSE_SINGLEWCHILDREN | V4: INCOME2_SPARSE_COUPLE | W4: INCOME2_SPARSE_COUPLEWCHILDREN | X4: INCOME2_SPARSE_OTHER | Y4: INCOME2_SPARSE_OTHERWCHILDREN | Z4: INCOME3_DENSE_SINGLE | AA4: INCOME3_DENSE_SINGLEWCHILDREN | AB4: INCOME3_DENSE_COUPLE | AC4: INCOME3_DENSE_COUPLEWCHILDREN | AD4: INCOME3_DENSE_OTHER | AE4: INCOME3_DENSE_OTHERWCHILDREN | AF4: INCOME3_SPARSE_SINGLE | AG4: INCOME3_SPARSE_SINGLEWCHILDREN | AH4: INCOME3_SPARSE_COUPLE | AI4: INCOME3_SPARSE_COUPLEWCHILDREN | AJ4: INCOME3_SPARSE_OTHER | AK4: INCOME3_SPARSE_OTHERWCHILDREN | AL4: INCOME4_DENSE_SINGLE | AM4: INCOME4_DENSE_SINGLEWCHILDREN | AN4: INCOME4_DENSE_COUPLE | AO4: INCOME4_DENSE_COUPLEWCHILDREN | AP4: INCOME4_DENSE_OTHER | AQ4: INCOME4_DENSE_OTHERWCHILDREN | AR4: INCOME4_SPARSE_SINGLE | AS4: INCOME4_SPARSE_SINGLEWCHILDREN | AT4: INCOME4_SPARSE_COUPLE | AU4: INCOME4_SPARSE_COUPLEWCHILDREN | AV4: INCOME4_SPARSE_OTHER | AW4: INCOME4_SPARSE_OTHERWCHILDREN | AX4: INCOME5_DENSE_SINGLE | AY4: INCOME5_DENSE_SINGLEWCHILDREN | AZ4: INCOME5_DENSE_COUPLE | BA4: INCOME5_DENSE_COUPLEWCHILDREN | BB4: INCOME5_DENSE_OTHER | BC4: INCOME5_DENSE_OTHERWCHILDREN | BD4: INCOME5_SPARSE_SINGLE | BE4: INCOME5_SPARSE_SINGLEWCHILDREN | BF4: INCOME5_SPARSE_COUPLE | BG4: INCOME5_SPARSE_COUPLEWCHILDREN | BH4: INCOME5_SPARSE_OTHER | BI4: INCOME5_SPARSE_OTHERWCHILDREN | BJ4: REPRESENTATIVE_HOUSEHOLD
A5: AUT | B5: 0 | C5: 0 | D5: 0 | E5: 0 | F5: 0 | G5: 0 | H5: 0 | I5: 0 | J5: 0 | K5: 0 | L5: 0 | M5: 0 | N5: 0 | O5: 0 | P5: 0 | Q5: 0 | R5: 0 | S5: 0 | T5: 0 | U5: 0 | V5: 0 | W5: 0 | X5: 0 | Y5: 0 | Z5: 0 | AA5: 0 | AB5: 0 | AC5: 0 | AD5: 0 | AE5: 0 | AF5: 0 | AG5: 0 | AH5: 0 | AI5: 0 | AJ5: 0 | AK5: 0 | AL5: 0 | AM5: 0 | AN5: 0 | AO5: 0 | AP5: 0 | AQ5: 0 | AR5: 0 | AS5: 0 | AT5: 0 | AU5: 0 | AV5: 0 | AW5: 0 | AX5: 0 | AY5: 0 | AZ5: 0 | BA5: 0 | BB5: 0 | BC5: 0 | BD5: 0 | BE5: 0 | BF5: 0 | BG5: 0 | BH5: 0 | BI5: 0 | BJ5: 0.12001477
A6: BEL | B6: 0.081180808 | C6: 0.052292095 | D6: 0.096617638 | E6: 0.046918313 | F6: 0.032124111 | G6: 0.058420076 | H6: 0.070889144 | I6: 0.072419014 | J6: 0.10080437 | K6: 0.12784727 | L6: 0.11896628 | M6: 0.07048293 | N6: 0.052767622 | O6: 0.089426316 | P6: 0.10237125 | Q6: 0.08368842 | R6: 0.11123509 | S6: 0.08850134 | T6: 0.070764509 | U6: 0.048207478 | V6: 0.081873999 | W6: 0.11574377 | X6: 0.12693893 | Y6: 0.10501885 | Z6: 0.11237781 | AA6: 0.09053387 | AB6: 0.11313213 | AC6: 0.14685211 | AD6: 0.14325291 | AE6: 0.11635465 | AF6: 0.084649173 | AG6: 0.094243422 | AH6: 0.11371662 | AI6: 0.15316606 | AJ6: 0.14108967 | AK6: 0.126527 | AL6: 0.14152668 | AM6: 0.12270815 | AN6: 0.14323982 | AO6: 0.15605741 | AP6: 0.13769746 | AQ6: 0.138859 | AR6: 0.11688153 | AS6: 0.13624226 | AT6: 0.13021399 | AU6: 0.1568897 | AV6: 0.15747185 | AW6: 0.1320935 | AX6: 0.18736233 | AY6: 0.14339865 | AZ6: 0.15295757 | BA6: 0.17866109 | BB6: 0.16480441 | BC6: 0.17200552 | BD6: 0.14890723 | BE6: 0.17263647 | BF6: 0.13362589 | BG6: 0.16900961 | BH6: 0.18113963 | BI6: 0.16728569 | BJ6: 0
A7: BGR | B7: 0.010737426 | C7: 0.014280009 | D7: 0.018140328 | E7: 0.043590991 | F7: 0.041085365 | G7: 0.034551494 | H7: 0.0054117308 | I7: 0.011891494 | J7: 0.0096262673 | K7: 0.019450668 | L7: 0.030551721 | M7: 0.017621025 | N7: 0.0071102791 | O7: 0.027250743 | P7: 0.02465476 | Q7: 0.044928347 | R7: 0.043986321 | S7: 0.036676048 | T7: 0.0038045389 | U7: 0.02333321 | V7: 0.013253781 | W7: 0.039404918 | X7: 0.0323985 | Y7: 0.028551569 | Z7: 0.01848946 | AA7: 0.035165652 | AB7: 0.027437648 | AC7: 0.053422866 | AD7: 0.039253164 | AE7: 0.050602126 | AF7: 0.0094949476 | AG7: 0.029635418 | AH7: 0.018817271 | AI7: 0.047254143 | AJ7: 0.040254851 | AK7: 0.034580767 | AL7: 0.038156772 | AM7: 0.036622529 | AN7: 0.042537395 | AO7: 0.050201532 | AP7: 0.048961361 | AQ7: 0.050794788 | AR7: 0.013568053 | AS7: 0.046738706 | AT7: 0.028611326 | AU7: 0.048704724 | AV7: 0.046619066 | AW7: 0.042526745 | AX7: 0.050108373 | AY7: 0.049662938 | AZ7: 0.045772634 | BA7: 0.052443619 | BB7: 0.050927307 | BC7: 0.051894173 | BD7: 0.03055265 | BE7: 0.038553802 | BF7: 0.038545459 | BG7: 0.052385748 | BH7: 0.046101054 | BI7: 0.045706665 | BJ7: 0
A8: HRV | B8: 0.0015088218 | C8: 0.017937706 | D8: 0.0085559599 | E8: 0.046502016 | F8: 0.037945344 | G8: 0.054979314 | H8: 0.0025716863 | I8: 0.015413924 | J8: 0.0085853881 | K8: 0.036063995 | L8: 0.032843487 | M8: 0.027661171 | N8: 0.0036674078 | O8: 0.04043846 | P8: 0.017871411 | Q8: 0.058098588 | R8: 0.049282585 | S8: 0.055872659 | T8: 0.0016374455 | U8: 0.02714788 | V8: 0.012810841 | W8: 0.052870891 | X8: 0.046621026 | Y8: 0.040437781 | Z8: 0.013416344 | AA8: 0.059106925 | AB8: 0.030918893 | AC8: 0.065520313 | AD8: 0.060837109 | AE8: 0.055616382 | AF8: 0.00059962085 | AG8: 0.036569324 | AH8: 0.017218046 | AI8: 0.05827581 | AJ8: 0.049403102 | AK8: 0.049845337 | AL8: 0.044175065 | AM8: 0.072516207 | AN8: 0.048250562 | AO8: 0.078397838 | AP8: 0.072267913 | AQ8: 0.072451588 | AR8: 0.0082272022 | AS8: 0.058532333 | AT8: 0.031018417 | AU8: 0.064118739 | AV8: 0.059802246 | AW8: 0.052946978 | AX8: 0.075478344 | AY8: 0.10524943 | AZ8: 0.088640922 | BA8: 0.090606471 | BB8: 0.089721503 | BC8: 0.071042762 | BD8: 0.046218121 | BE8: 0.071383145 | BF8: 0.055777821 | BG8: 0.07844054 | BH8: 0.073942359 | BI8: 0.062428308 | BJ8: 0
A9: CYP | B9: 0.014046619 | C9: 0.0087980068 | D9: 0.015817359 | E9: 0.035893799 | F9: 0.034799887 | G9: 0.032102433 | H9: 0.021443155 | I9: 0.0084061567 | J9: 0.022509678 | K9: 0.032660836 | L9: 0.033301814 | M9: 0.027047089 | N9: 0.015971034 | O9: 0.020126233 | P9: 0.020285422 | Q9: 0.058818503 | R9: 0.057105226 | S9: 0.058014744 | T9: 0.014719893 | U9: 0.026453487 | V9: 0.017164623 | W9: 0.056210842 | X9: 0.052377277 | Y9: 0.045608712 | Z9: 0.044492172 | AA9: 0.037201808 | AB9: 0.046872814 | AC9: 0.086344761 | AD9: 0.078903396 | AE9: 0.084199696 | AF9: 0.015528488 | AG9: 0.032750193 | AH9: 0.03341852 | AI9: 0.063819662 | AJ9: 0.06807963 | AK9: 0.060058158 | AL9: 0.088995022 | AM9: 0.055089661 | AN9: 0.099110847 | AO9: 0.10333162 | AP9: 0.10097267 | AQ9: 0.11512661 | AR9: 0.035609628 | AS9: 0.064530599 | AT9: 0.060448272 | AU9: 0.07207316 | AV9: 0.07925471 | AW9: 0.080079172 | AX9: 0.12689957 | AY9: 0.075543903 | AZ9: 0.13666429 | BA9: 0.15124573 | BB9: 0.11272059 | BC9: 0.11267167 | BD9: 0.10920231 | BE9: 0.10008258 | BF9: 0.10377028 | BG9: 0.11961684 | BH9: 0.11605111 | BI9: 0.095246916 | BJ9: 0
A10: CZE | B10: 0.0092951997 | C10: 0.010011169 | D10: 0.024809373 | E10: 0.012707311 | F10: 0.032902155 | G10: 0.061125442 | H10: 0.012056333 | I10: 0.0067248654 | J10: 0.017603712 | K10: 0.012044026 | L10: 0.033778834 | M10: 0.01472937 | N10: 0.011763891 | O10: 0.017085693 | P10: 0.015479682 | Q10: 0.041907546 | R10: 0.048408559 | S10: 0.069706396 | T10: 0.0075694559 | U10: 0.017794558 | V10: 0.012924035 | W10: 0.036489336 | X10: 0.048308273 | Y10: 0.034592784 | Z10: 0.021345937 | AA10: 0.028056763 | AB10: 0.028951766 | AC10: 0.055334467 | AD10: 0.052500187 | AE10: 0.061666357 | AF10: 0.012951624 | AG10: 0.024748205 | AH10: 0.021301181 | AI10: 0.048825874 | AJ10: 0.053034752 | AK10: 0.047966061 | AL10: 0.04812953 | AM10: 0.032597623 | AN10: 0.055475774 | AO10: 0.065717655 | AP10: 0.063593243 | AQ10: 0.044532081 | AR10: 0.026956873 | AS10: 0.043577435 | AT10: 0.041030958 | AU10: 0.060574717 | AV10: 0.057812441 | AW10: 0.054407604 | AX10: 0.069612679 | AY10: 0.045007953 | AZ10: 0.066787677 | BA10: 0.076597011 | BB10: 0.060961823 | BC10: 0.03778719 | BD10: 0.057993494 | BE10: 0.048884701 | BF10: 0.057989579 | BG10: 0.066021323 | BH10: 0.066682463 | BI10: 0.064350234 | BJ10: 0
A11: DNK | B11: 0.17887715 | C11: 0.14939505 | D11: 0.30649308 | E11: 0.25480685 | F11: 0.21684002 | G11: 0.22373045 | H11: 0.21198191 | I11: 0.15722333 | J11: 0.22025476 | K11: 0.26836263 | L11: 0.27293636 | M11: 0.27534811 | N11: 0.23985453 | O11: 0.22565677 | P11: 0.26710109 | Q11: 0.28794829 | R11: 0.2593441 | S11: 0.26650637 | T11: 0.25003727 | U11: 0.19298455 | V11: 0.24695213 | W11: 0.30519906 | X11: 0.28763478 | Y11: 0.28765571 | Z11: 0.25897166 | AA11: 0.21871086 | AB11: 0.26244715 | AC11: 0.29263035 | AD11: 0.28807922 | AE11: 0.32524885 | AF11: 0.2506286 | AG11: 0.23249116 | AH11: 0.27033985 | AI11: 0.31804506 | AJ11: 0.30123043 | AK11: 0.30056787 | AL11: 0.29571074 | AM11: 0.27585632 | AN11: 0.30134182 | AO11: 0.29232866 | AP11: 0.280303 | AQ11: 0.35503616 | AR11: 0.27773525 | AS11: 0.28365209 | AT11: 0.30062169 | AU11: 0.335174 | AV11: 0.31781567 | AW11: 0.31009397 | AX11: 0.33530796 | AY11: 0.30970989 | AZ11: 0.37067582 | BA11: 0.32179093 | BB11: 0.39092473 | BC11: 0.49955836 | BD11: 0.31896505 | BE11: 0.35787928 | BF11: 0.35584909 | BG11: 0.34089083 | BH11: 0.35389302 | BI11: 0.49440925 | BJ11: 0
A12: EST | B12: 0.014929231 | C12: 0.015474075 | D12: 0.02485921 | E12: 0.045569911 | F12: 0.051365869 | G12: 0.042092189 | H12: 0.014717749 | I12: 0.016523255 | J12: 0.038827406 | K12: 0.057145105 | L12: 0.040334552 | M12: 0.04905066 | N12: 0.0046341962 | O12: 0.032768138 | P12: 0.036167306 | Q12: 0.073152249 | R12: 0.067889275 | S12: 0.067359938 | T12: 0.0048189108 | U12: 0.035586158 | V12: 0.021190774 | W12: 0.069086719 | X12: 0.0650974 | Y12: 0.061598735 | Z12: 0.037163549 | AA12: 0.053113192 | AB12: 0.070367417 | AC12: 0.081855866 | AD12: 0.074351171 | AE12: 0.075130388 | AF12: 0.011983773 | AG12: 0.045478257 | AH12: 0.056852338 | AI12: 0.075256781 | AJ12: 0.077737437 | AK12: 0.070930977 | AL12: 0.081483111 | AM12: 0.064553602 | AN12: 0.077288356 | AO12: 0.085862898 | AP12: 0.08108587 | AQ12: 0.082580582 | AR12: 0.065803239 | AS12: 0.076799925 | AT12: 0.076226481 | AU12: 0.089592965 | AV12: 0.082056173 | AW12: 0.081505251 | AX12: 0.10513771 | AY12: 0.090375991 | AZ12: 0.093186241 | BA12: 0.097337456 | BB12: 0.090476742 | BC12: 0.09637535 | BD12: 0.11101623 | BE12: 0.10216076 | BF12: 0.095460959 | BG12: 0.095791452 | BH12: 0.10289045 | BI12: 0.10005731 | BJ12: 0
A13: FIN | B13: 0.043286157 | C13: 0.0455752 | D13: 0.070653332 | E13: 0.1027158 | F13: 0.11583397 | G13: 0.10121008 | H13: 0.042850661 | I13: 0.071733974 | J13: 0.063951686 | K13: 0.1083539 | L13: 0.098948516 | M13: 0.094195693 | N13: 0.05500129 | O13: 0.083680907 | P13: 0.10831965 | Q13: 0.13677144 | R13: 0.13971878 | S13: 0.12773956 | T13: 0.048133937 | U13: 0.049911083 | V13: 0.08854172 | W13: 0.12566617 | X13: 0.11918948 | Y13: 0.12014051 | Z13: 0.098155019 | AA13: 0.087163407 | AB13: 0.12783296 | AC13: 0.15676792 | AD13: 0.15938863 | AE13: 0.15995539 | AF13: 0.085375735 | AG13: 0.094998298 | AH13: 0.11413215 | AI13: 0.1459287 | AJ13: 0.13641136 | AK13: 0.14582047 | AL13: 0.13754747 | AM13: 0.1224057 | AN13: 0.15750303 | AO13: 0.16969301 | AP13: 0.17569211 | AQ13: 0.18245638 | AR13: 0.11645052 | AS13: 0.12789925 | AT13: 0.1404282 | AU13: 0.15958697 | AV13: 0.15455987 | AW13: 0.15966471 | AX13: 0.1969703 | AY13: 0.15584698 | AZ13: 0.20612365 | BA13: 0.20945162 | BB13: 0.21164362 | BC13: 0.25552017 | BD13: 0.16659553 | BE13: 0.16504344 | BF13: 0.18732499 | BG13: 0.19452619 | BH13: 0.18746507 | BI13: 0.19975231 | BJ13: 0
A14: FRA | B14: 0.078787071 | C14: 0.029156265 | D14: 0.063650864 | E14: 0.064429751 | F14: 0.075793359 | G14: 0.057992509 | H14: 0.075900124 | I14: 0.11470724 | J14: 0.048341499 | K14: 0.064883123 | L14: 0.080889786 | M14: 0.069097416 | N14: 0.080780507 | O14: 0.06663333 | P14: 0.069409032 | Q14: 0.085105371 | R14: 0.073961741 | S14: 0.070029792 | T14: 0.061626717 | U14: 0.067692755 | V14: 0.054718532 | W14: 0.080810082 | X14: 0.08173287 | Y14: 0.075987353 | Z14: 0.081348704 | AA14: 0.074357356 | AB14: 0.075308996 | AC14: 0.096758515 | AD14: 0.087346107 | AE14: 0.091336949 | AF14: 0.058667633 | AG14: 0.082986113 | AH14: 0.068440605 | AI14: 0.090024293 | AJ14: 0.086544682 | AK14: 0.078964978 | AL14: 0.093260243 | AM14: 0.086721164 | AN14: 0.089292872 | AO14: 0.10768532 | AP14: 0.096910542 | AQ14: 0.098808045 | AR14: 0.074224692 | AS14: 0.093562658 | AT14: 0.07937078 | AU14: 0.096047858 | AV14: 0.086801222 | AW14: 0.096903558 | AX14: 0.1201487 | AY14: 0.10557747 | AZ14: 0.12674125 | BA14: 0.13130463 | BB14: 0.12559998 | BC14: 0.11835745 | BD14: 0.095806393 | BE14: 0.11084042 | BF14: 0.095652324 | BG14: 0.11458845 | BH14: 0.10094454 | BI14: 0.11720983 | BJ14: 0
A15: DEU | B15: 0.041755621 | C15: 0.019992672 | D15: 0.067467013 | E15: 0.084007684 | F15: 0.094390263 | G15: 0.096951589 | H15: 0.083925597 | I15: 0.051890039 | J15: 0.058516553 | K15: 0.087857751 | L15: 0.086222323 | M15: 0.063771418 | N15: 0.053776218 | O15: 0.025639717 | P15: 0.081039926 | Q15: 0.11164466 | R15: 0.10591371 | S15: 0.068626653 | T15: 0.056531107 | U15: 0.034157599 | V15: 0.069474381 | W15: 0.10658891 | X15: 0.10699023 | Y15: 0.094774782 | Z15: 0.087011761 | AA15: 0.039582183 | AB15: 0.094260277 | AC15: 0.12733424 | AD15: 0.11364205 | AE15: 0.12751767 | AF15: 0.070774707 | AG15: 0.042917859 | AH15: 0.085673037 | AI15: 0.12213326 | AJ15: 0.11573073 | AK15: 0.11229557 | AL15: 0.11392343 | AM15: 0.088400045 | AN15: 0.1120773 | AO15: 0.10496982 | AP15: 0.12171836 | AQ15: 0.12370581 | AR15: 0.10899372 | AS15: 0.089352752 | AT15: 0.10377268 | AU15: 0.12278904 | AV15: 0.1281069 | AW15: 0.1193157 | AX15: 0.097181255 | AY15: 0.11048303 | AZ15: 0.080711082 | BA15: 0.13356628 | BB15: 0.11844414 | BC15: 0.088865688 | BD15: 0.10214245 | BE15: 0.12549999 | BF15: 0.081051174 | BG15: 0.12047552 | BH15: 0.09156311 | BI15: 0.11588319 | BJ15: 0
A16: GRC | B16: 0.042163207 | C16: 0.03044502 | D16: 0.04968848 | E16: 0.065090106 | F16: 0.058908762 | G16: 0.049153668 | H16: 0.042455909 | I16: 0.010462586 | J16: 0.05226381 | K16: 0.063058585 | L16: 0.060274227 | M16: 0.046993138 | N16: 0.048743605 | O16: 0.032318598 | P16: 0.055021677 | Q16: 0.067214572 | R16: 0.061066796 | S16: 0.063817717 | T16: 0.046206013 | U16: 0.059588804 | V16: 0.051087519 | W16: 0.069021071 | X16: 0.060440004 | Y16: 0.059406857 | Z16: 0.05580328 | AA16: 0.044938444 | AB16: 0.057007598 | AC16: 0.070654407 | AD16: 0.062698936 | AE16: 0.067928566 | AF16: 0.046972488 | AG16: 0.03626666 | AH16: 0.055122101 | AI16: 0.069147669 | AJ16: 0.061501656 | AK16: 0.067932514 | AL16: 0.060352473 | AM16: 0.068915998 | AN16: 0.061495133 | AO16: 0.073869997 | AP16: 0.066081101 | AQ16: 0.065970144 | AR16: 0.053921823 | AS16: 0.082684416 | AT16: 0.059763372 | AU16: 0.073746946 | AV16: 0.067657145 | AW16: 0.06602832 | AX16: 0.072207574 | AY16: 0.090149095 | AZ16: 0.073020598 | BA16: 0.078067124 | BB16: 0.07565417 | BC16: 0.076836068 | BD16: 0.070902071 | BE16: 0.079030359 | BF16: 0.068521667 | BG16: 0.076461763 | BH16: 0.07302528 | BI16: 0.07124922 | BJ16: 0
... A39: LROW | B39: 0 | C39: 0 | D39: 0 | E39: 0 | F39: 0 | G39: 0 | H39: 0 | I39: 0 | J39: 0 | K39: 0 | L39: 0 | M39: 0 | N39: 0 | O39: 0 | P39: 0 | Q39: 0 | R39: 0 | S39: 0 | T39: 0 | U39: 0 | V39: 0 | W39: 0 | X39: 0 | Y39: 0 | Z39: 0 | AA39: 0 | AB39: 0 | AC39: 0 | AD39: 0 | AE39: 0 | AF39: 0 | AG39: 0 | AH39: 0 | AI39: 0 | AJ39: 0 | AK39: 0 | AL39: 0 | AM39: 0 | AN39: 0 | AO39: 0 | AP39: 0 | AQ39: 0 | AR39: 0 | AS39: 0 | AT39: 0 | AU39: 0 | AV39: 0 | AW39: 0 | AX39: 0 | AY39: 0 | AZ39: 0 | BA39: 0 | BB39: 0 | BC39: 0 | BD39: 0 | BE39: 0 | BF39: 0 | BG39: 0 | BH39: 0 | BI39: 0 | BJ39: 0.061234011

Sheet EXO_Tax_rate_wealth
